Workbook

Sheet SINTESI
A1: SINTESI DELLO SCREENING
A2: Un foglio per mercato. Le soglie stanno in PARAMETRI: cambiale li' e tutti i giudizi si ricalcolano.
A4: Esito | B4: Titoli
A5: PASSA FORTE | B5: =COUNTIF('ITALIA'!AG2:AG67,"PASSA FORTE")+COUNTIF('GERMANIA'!AG2:AG44,"PASSA FORTE")+COUNTIF('FRANCIA'!AG2:AG36,"PASSA FORTE")+COUNTIF('PAESI BASSI'!AG2:AG21,"PASSA FORTE")+COUNTIF('SVIZZERA'!AG2:AG24,"PASSA FORTE")+COUNTIF('USA'!AG2:AG167,"PASSA FORTE")
A6: PASSA | B6: =COUNTIF('ITALIA'!AG2:AG67,"PASSA")+COUNTIF('GERMANIA'!AG2:AG44,"PASSA")+COUNTIF('FRANCIA'!AG2:AG36,"PASSA")+COUNTIF('PAESI BASSI'!AG2:AG21,"PASSA")+COUNTIF('SVIZZERA'!AG2:AG24,"PASSA")+COUNTIF('USA'!AG2:AG167,"PASSA")
A7: SCARTA | B7: =COUNTIF('ITALIA'!AG2:AG67,"SCARTA")+COUNTIF('GERMANIA'!AG2:AG44,"SCARTA")+COUNTIF('FRANCIA'!AG2:AG36,"SCARTA")+COUNTIF('PAESI BASSI'!AG2:AG21,"SCARTA")+COUNTIF('SVIZZERA'!AG2:AG24,"SCARTA")+COUNTIF('USA'!AG2:AG167,"SCARTA")
A8: DA COMPLETARE | B8: =COUNTIF('ITALIA'!AG2:AG67,"DA COMPLETARE")+COUNTIF('GERMANIA'!AG2:AG44,"DA COMPLETARE")+COUNTIF('FRANCIA'!AG2:AG36,"DA COMPLETARE")+COUNTIF('PAESI BASSI'!AG2:AG21,"DA COMPLETARE")+COUNTIF('SVIZZERA'!AG2:AG24,"DA COMPLETARE")+COUNTIF('USA'!AG2:AG167,"DA COMPLETARE")
A9: Totale | B9: =SUM(B5:B8)
A11: Per mercato
A12: Mercato | B12: Titoli | C12: Passano | D12: P/E medio | E12: Punteggio medio
A13: Italia | B13: =COUNTA('ITALIA'!B2:B67) | C13: =COUNTIF('ITALIA'!AG2:AG67,"PASSA")+COUNTIF('ITALIA'!AG2:AG67,"PASSA FORTE") | D13: =IFERROR(AVERAGE('ITALIA'!M2:M67),"") | E13: =IFERROR(AVERAGE('ITALIA'!AD2:AD67),"")
A14: Germania | B14: =COUNTA('GERMANIA'!B2:B44) | C14: =COUNTIF('GERMANIA'!AG2:AG44,"PASSA")+COUNTIF('GERMANIA'!AG2:AG44,"PASSA FORTE") | D14: =IFERROR(AVERAGE('GERMANIA'!M2:M44),"") | E14: =IFERROR(AVERAGE('GERMANIA'!AD2:AD44),"")
A15: Francia | B15: =COUNTA('FRANCIA'!B2:B36) | C15: =COUNTIF('FRANCIA'!AG2:AG36,"PASSA")+COUNTIF('FRANCIA'!AG2:AG36,"PASSA FORTE") | D15: =IFERROR(AVERAGE('FRANCIA'!M2:M36),"") | E15: =IFERROR(AVERAGE('FRANCIA'!AD2:AD36),"")
A16: Paesi Bassi | B16: =COUNTA('PAESI BASSI'!B2:B21) | C16: =COUNTIF('PAESI BASSI'!AG2:AG21,"PASSA")+COUNTIF('PAESI BASSI'!AG2:AG21,"PASSA FORTE") | D16: =IFERROR(AVERAGE('PAESI BASSI'!M2:M21),"") | E16: =IFERROR(AVERAGE('PAESI BASSI'!AD2:AD21),"")
A17: Svizzera | B17: =COUNTA('SVIZZERA'!B2:B24) | C17: =COUNTIF('SVIZZERA'!AG2:AG24,"PASSA")+COUNTIF('SVIZZERA'!AG2:AG24,"PASSA FORTE") | D17: =IFERROR(AVERAGE('SVIZZERA'!M2:M24),"") | E17: =IFERROR(AVERAGE('SVIZZERA'!AD2:AD24),"")
A18: USA | B18: =COUNTA('USA'!B2:B167) | C18: =COUNTIF('USA'!AG2:AG167,"PASSA")+COUNTIF('USA'!AG2:AG167,"PASSA FORTE") | D18: =IFERROR(AVERAGE('USA'!M2:M167),"") | E18: =IFERROR(AVERAGE('USA'!AD2:AD167),"")
A21: Per settore
A22: Settore | B22: Italia | C22: Germania | D22: Francia | E22: Paesi Bassi | F22: Svizzera | G22: USA | H22: Totale | I22: Passano | J22: ROE 1a medio
A23: Tecnologia | B23: =COUNTIF('ITALIA'!E2:E67,$A23) | C23: =COUNTIF('GERMANIA'!E2:E44,$A23) | D23: =COUNTIF('FRANCIA'!E2:E36,$A23) | E23: =COUNTIF('PAESI BASSI'!E2:E21,$A23) | F23: =COUNTIF('SVIZZERA'!E2:E24,$A23) | G23: =COUNTIF('USA'!E2:E167,$A23) | H23: =SUM(B23:G23) | I23: =COUNTIFS('ITALIA'!E2:E67,$A23,'ITALIA'!AG2:AG67,"PASSA")+COUNTIFS('ITALIA'!E2:E67,$A23,'ITALIA'!AG2:AG67,"PASSA FORTE")+COUNTIFS('GERMANIA'!E2:E44,$A23,'GERMANIA'!AG2:AG44,"PASSA")+COUNTIFS('GERMANIA'!E2:E44,$A23,'GERMANIA'!AG2:AG44,"PASSA FORTE")+COUNTIFS('FRANCIA'!E2:E36,$A23,'FRANCIA'!AG2:AG36,"PASSA")+COUNTIFS('FRANCIA'!E2:E36,$A23,'FRANCIA'!AG2:AG36,"PASSA FORTE")+COUNTIFS('PAESI BASSI'!E2:E21,$A23,'PAESI BASSI'!AG2:AG21,"PASSA")+COUNTIFS('PAESI BASSI'!E2:E21,$A23,'PAESI BASSI'!AG2:AG21,"PASSA FORTE")+COUNTIFS('SVIZZERA'!E2:E24,$A23,'SVIZZERA'!AG2:AG24,"PASSA")+COUNTIFS('SVIZZERA'!E2:E24,$A23,'SVIZZERA'!AG2:AG24,"PASSA FORTE")+COUNTIFS('USA'!E2:E167,$A23,'USA'!AG2:AG167,"PASSA")+COUNTIFS('USA'!E2:E167,$A23,'USA'!AG2:AG167,"PASSA FORTE") | J23: =IFERROR((SUMIF('ITALIA'!E2:E67,$A23,'ITALIA'!P2:P67)+SUMIF('GERMANIA'!E2:E44,$A23,'GERMANIA'!P2:P44)+SUMIF('FRANCIA'!E2:E36,$A23,'FRANCIA'!P2:P36)+SUMIF('PAESI BASSI'!E2:E21,$A23,'PAESI BASSI'!P2:P21)+SUMIF('SVIZZERA'!E2:E24,$A23,'SVIZZERA'!P2:P24)+SUMIF('USA'!E2:E167,$A23,'USA'!P2:P167))/(COUNTIFS('ITALIA'!E2:E67,$A23,'ITALIA'!P2:P67,"<>")+COUNTIFS('GERMANIA'!E2:E44,$A23,'GERMANIA'!P2:P44,"<>")+COUNTIFS('FRANCIA'!E2:E36,$A23,'FRANCIA'!P2:P36,"<>")+COUNTIFS('PAESI BASSI'!E2:E21,$A23,'PAESI BASSI'!P2:P21,"<>")+COUNTIFS('SVIZZERA'!E2:E24,$A23,'SVIZZERA'!P2:P24,"<>")+COUNTIFS('USA'!E2:E167,$A23,'USA'!P2:P167,"<>")),"")
A24: Salute | B24: =COUNTIF('ITALIA'!E2:E67,$A24) | C24: =COUNTIF('GERMANIA'!E2:E44,$A24) | D24: =COUNTIF('FRANCIA'!E2:E36,$A24) | E24: =COUNTIF('PAESI BASSI'!E2:E21,$A24) | F24: =COUNTIF('SVIZZERA'!E2:E24,$A24) | G24: =COUNTIF('USA'!E2:E167,$A24) | H24: =SUM(B24:G24) | I24: =COUNTIFS('ITALIA'!E2:E67,$A24,'ITALIA'!AG2:AG67,"PASSA")+COUNTIFS('ITALIA'!E2:E67,$A24,'ITALIA'!AG2:AG67,"PASSA FORTE")+COUNTIFS('GERMANIA'!E2:E44,$A24,'GERMANIA'!AG2:AG44,"PASSA")+COUNTIFS('GERMANIA'!E2:E44,$A24,'GERMANIA'!AG2:AG44,"PASSA FORTE")+COUNTIFS('FRANCIA'!E2:E36,$A24,'FRANCIA'!AG2:AG36,"PASSA")+COUNTIFS('FRANCIA'!E2:E36,$A24,'FRANCIA'!AG2:AG36,"PASSA FORTE")+COUNTIFS('PAESI BASSI'!E2:E21,$A24,'PAESI BASSI'!AG2:AG21,"PASSA")+COUNTIFS('PAESI BASSI'!E2:E21,$A24,'PAESI BASSI'!AG2:AG21,"PASSA FORTE")+COUNTIFS('SVIZZERA'!E2:E24,$A24,'SVIZZERA'!AG2:AG24,"PASSA")+COUNTIFS('SVIZZERA'!E2:E24,$A24,'SVIZZERA'!AG2:AG24,"PASSA FORTE")+COUNTIFS('USA'!E2:E167,$A24,'USA'!AG2:AG167,"PASSA")+COUNTIFS('USA'!E2:E167,$A24,'USA'!AG2:AG167,"PASSA FORTE") | J24: =IFERROR((SUMIF('ITALIA'!E2:E67,$A24,'ITALIA'!P2:P67)+SUMIF('GERMANIA'!E2:E44,$A24,'GERMANIA'!P2:P44)+SUMIF('FRANCIA'!E2:E36,$A24,'FRANCIA'!P2:P36)+SUMIF('PAESI BASSI'!E2:E21,$A24,'PAESI BASSI'!P2:P21)+SUMIF('SVIZZERA'!E2:E24,$A24,'SVIZZERA'!P2:P24)+SUMIF('USA'!E2:E167,$A24,'USA'!P2:P167))/(COUNTIFS('ITALIA'!E2:E67,$A24,'ITALIA'!P2:P67,"<>")+COUNTIFS('GERMANIA'!E2:E44,$A24,'GERMANIA'!P2:P44,"<>")+COUNTIFS('FRANCIA'!E2:E36,$A24,'FRANCIA'!P2:P36,"<>")+COUNTIFS('PAESI BASSI'!E2:E21,$A24,'PAESI BASSI'!P2:P21,"<>")+COUNTIFS('SVIZZERA'!E2:E24,$A24,'SVIZZERA'!P2:P24,"<>")+COUNTIFS('USA'!E2:E167,$A24,'USA'!P2:P167,"<>")),"")
A25: Finanziario | B25: =COUNTIF('ITALIA'!E2:E67,$A25) | C25: =COUNTIF('GERMANIA'!E2:E44,$A25) | D25: =COUNTIF('FRANCIA'!E2:E36,$A25) | E25: =COUNTIF('PAESI BASSI'!E2:E21,$A25) | F25: =COUNTIF('SVIZZERA'!E2:E24,$A25) | G25: =COUNTIF('USA'!E2:E167,$A25) | H25: =SUM(B25:G25) | I25: =COUNTIFS('ITALIA'!E2:E67,$A25,'ITALIA'!AG2:AG67,"PASSA")+COUNTIFS('ITALIA'!E2:E67,$A25,'ITALIA'!AG2:AG67,"PASSA FORTE")+COUNTIFS('GERMANIA'!E2:E44,$A25,'GERMANIA'!AG2:AG44,"PASSA")+COUNTIFS('GERMANIA'!E2:E44,$A25,'GERMANIA'!AG2:AG44,"PASSA FORTE")+COUNTIFS('FRANCIA'!E2:E36,$A25,'FRANCIA'!AG2:AG36,"PASSA")+COUNTIFS('FRANCIA'!E2:E36,$A25,'FRANCIA'!AG2:AG36,"PASSA FORTE")+COUNTIFS('PAESI BASSI'!E2:E21,$A25,'PAESI BASSI'!AG2:AG21,"PASSA")+COUNTIFS('PAESI BASSI'!E2:E21,$A25,'PAESI BASSI'!AG2:AG21,"PASSA FORTE")+COUNTIFS('SVIZZERA'!E2:E24,$A25,'SVIZZERA'!AG2:AG24,"PASSA")+COUNTIFS('SVIZZERA'!E2:E24,$A25,'SVIZZERA'!AG2:AG24,"PASSA FORTE")+COUNTIFS('USA'!E2:E167,$A25,'USA'!AG2:AG167,"PASSA")+COUNTIFS('USA'!E2:E167,$A25,'USA'!AG2:AG167,"PASSA FORTE") | J25: =IFERROR((SUMIF('ITALIA'!E2:E67,$A25,'ITALIA'!P2:P67)+SUMIF('GERMANIA'!E2:E44,$A25,'GERMANIA'!P2:P44)+SUMIF('FRANCIA'!E2:E36,$A25,'FRANCIA'!P2:P36)+SUMIF('PAESI BASSI'!E2:E21,$A25,'PAESI BASSI'!P2:P21)+SUMIF('SVIZZERA'!E2:E24,$A25,'SVIZZERA'!P2:P24)+SUMIF('USA'!E2:E167,$A25,'USA'!P2:P167))/(COUNTIFS('ITALIA'!E2:E67,$A25,'ITALIA'!P2:P67,"<>")+COUNTIFS('GERMANIA'!E2:E44,$A25,'GERMANIA'!P2:P44,"<>")+COUNTIFS('FRANCIA'!E2:E36,$A25,'FRANCIA'!P2:P36,"<>")+COUNTIFS('PAESI BASSI'!E2:E21,$A25,'PAESI BASSI'!P2:P21,"<>")+COUNTIFS('SVIZZERA'!E2:E24,$A25,'SVIZZERA'!P2:P24,"<>")+COUNTIFS('USA'!E2:E167,$A25,'USA'!P2:P167,"<>")),"")
A26: Industriale | B26: =COUNTIF('ITALIA'!E2:E67,$A26) | C26: =COUNTIF('GERMANIA'!E2:E44,$A26) | D26: =COUNTIF('FRANCIA'!E2:E36,$A26) | E26: =COUNTIF('PAESI BASSI'!E2:E21,$A26) | F26: =COUNTIF('SVIZZERA'!E2:E24,$A26) | G26: =COUNTIF('USA'!E2:E167,$A26) | H26: =SUM(B26:G26) | I26: =COUNTIFS('ITALIA'!E2:E67,$A26,'ITALIA'!AG2:AG67,"PASSA")+COUNTIFS('ITALIA'!E2:E67,$A26,'ITALIA'!AG2:AG67,"PASSA FORTE")+COUNTIFS('GERMANIA'!E2:E44,$A26,'GERMANIA'!AG2:AG44,"PASSA")+COUNTIFS('GERMANIA'!E2:E44,$A26,'GERMANIA'!AG2:AG44,"PASSA FORTE")+COUNTIFS('FRANCIA'!E2:E36,$A26,'FRANCIA'!AG2:AG36,"PASSA")+COUNTIFS('FRANCIA'!E2:E36,$A26,'FRANCIA'!AG2:AG36,"PASSA FORTE")+COUNTIFS('PAESI BASSI'!E2:E21,$A26,'PAESI BASSI'!AG2:AG21,"PASSA")+COUNTIFS('PAESI BASSI'!E2:E21,$A26,'PAESI BASSI'!AG2:AG21,"PASSA FORTE")+COUNTIFS('SVIZZERA'!E2:E24,$A26,'SVIZZERA'!AG2:AG24,"PASSA")+COUNTIFS('SVIZZERA'!E2:E24,$A26,'SVIZZERA'!AG2:AG24,"PASSA FORTE")+COUNTIFS('USA'!E2:E167,$A26,'USA'!AG2:AG167,"PASSA")+COUNTIFS('USA'!E2:E167,$A26,'USA'!AG2:AG167,"PASSA FORTE") | J26: =IFERROR((SUMIF('ITALIA'!E2:E67,$A26,'ITALIA'!P2:P67)+SUMIF('GERMANIA'!E2:E44,$A26,'GERMANIA'!P2:P44)+SUMIF('FRANCIA'!E2:E36,$A26,'FRANCIA'!P2:P36)+SUMIF('PAESI BASSI'!E2:E21,$A26,'PAESI BASSI'!P2:P21)+SUMIF('SVIZZERA'!E2:E24,$A26,'SVIZZERA'!P2:P24)+SUMIF('USA'!E2:E167,$A26,'USA'!P2:P167))/(COUNTIFS('ITALIA'!E2:E67,$A26,'ITALIA'!P2:P67,"<>")+COUNTIFS('GERMANIA'!E2:E44,$A26,'GERMANIA'!P2:P44,"<>")+COUNTIFS('FRANCIA'!E2:E36,$A26,'FRANCIA'!P2:P36,"<>")+COUNTIFS('PAESI BASSI'!E2:E21,$A26,'PAESI BASSI'!P2:P21,"<>")+COUNTIFS('SVIZZERA'!E2:E24,$A26,'SVIZZERA'!P2:P24,"<>")+COUNTIFS('USA'!E2:E167,$A26,'USA'!P2:P167,"<>")),"")
A27: Consumi | B27: =COUNTIF('ITALIA'!E2:E67,$A27) | C27: =COUNTIF('GERMANIA'!E2:E44,$A27) | D27: =COUNTIF('FRANCIA'!E2:E36,$A27) | E27: =COUNTIF('PAESI BASSI'!E2:E21,$A27) | F27: =COUNTIF('SVIZZERA'!E2:E24,$A27) | G27: =COUNTIF('USA'!E2:E167,$A27) | H27: =SUM(B27:G27) | I27: =COUNTIFS('ITALIA'!E2:E67,$A27,'ITALIA'!AG2:AG67,"PASSA")+COUNTIFS('ITALIA'!E2:E67,$A27,'ITALIA'!AG2:AG67,"PASSA FORTE")+COUNTIFS('GERMANIA'!E2:E44,$A27,'GERMANIA'!AG2:AG44,"PASSA")+COUNTIFS('GERMANIA'!E2:E44,$A27,'GERMANIA'!AG2:AG44,"PASSA FORTE")+COUNTIFS('FRANCIA'!E2:E36,$A27,'FRANCIA'!AG2:AG36,"PASSA")+COUNTIFS('FRANCIA'!E2:E36,$A27,'FRANCIA'!AG2:AG36,"PASSA FORTE")+COUNTIFS('PAESI BASSI'!E2:E21,$A27,'PAESI BASSI'!AG2:AG21,"PASSA")+COUNTIFS('PAESI BASSI'!E2:E21,$A27,'PAESI BASSI'!AG2:AG21,"PASSA FORTE")+COUNTIFS('SVIZZERA'!E2:E24,$A27,'SVIZZERA'!AG2:AG24,"PASSA")+COUNTIFS('SVIZZERA'!E2:E24,$A27,'SVIZZERA'!AG2:AG24,"PASSA FORTE")+COUNTIFS('USA'!E2:E167,$A27,'USA'!AG2:AG167,"PASSA")+COUNTIFS('USA'!E2:E167,$A27,'USA'!AG2:AG167,"PASSA FORTE") | J27: =IFERROR((SUMIF('ITALIA'!E2:E67,$A27,'ITALIA'!P2:P67)+SUMIF('GERMANIA'!E2:E44,$A27,'GERMANIA'!P2:P44)+SUMIF('FRANCIA'!E2:E36,$A27,'FRANCIA'!P2:P36)+SUMIF('PAESI BASSI'!E2:E21,$A27,'PAESI BASSI'!P2:P21)+SUMIF('SVIZZERA'!E2:E24,$A27,'SVIZZERA'!P2:P24)+SUMIF('USA'!E2:E167,$A27,'USA'!P2:P167))/(COUNTIFS('ITALIA'!E2:E67,$A27,'ITALIA'!P2:P67,"<>")+COUNTIFS('GERMANIA'!E2:E44,$A27,'GERMANIA'!P2:P44,"<>")+COUNTIFS('FRANCIA'!E2:E36,$A27,'FRANCIA'!P2:P36,"<>")+COUNTIFS('PAESI BASSI'!E2:E21,$A27,'PAESI BASSI'!P2:P21,"<>")+COUNTIFS('SVIZZERA'!E2:E24,$A27,'SVIZZERA'!P2:P24,"<>")+COUNTIFS('USA'!E2:E167,$A27,'USA'!P2:P167,"<>")),"")
A28: Energia | B28: =COUNTIF('ITALIA'!E2:E67,$A28) | C28: =COUNTIF('GERMANIA'!E2:E44,$A28) | D28: =COUNTIF('FRANCIA'!E2:E36,$A28) | E28: =COUNTIF('PAESI BASSI'!E2:E21,$A28) | F28: =COUNTIF('SVIZZERA'!E2:E24,$A28) | G28: =COUNTIF('USA'!E2:E167,$A28) | H28: =SUM(B28:G28) | I28: =COUNTIFS('ITALIA'!E2:E67,$A28,'ITALIA'!AG2:AG67,"PASSA")+COUNTIFS('ITALIA'!E2:E67,$A28,'ITALIA'!AG2:AG67,"PASSA FORTE")+COUNTIFS('GERMANIA'!E2:E44,$A28,'GERMANIA'!AG2:AG44,"PASSA")+COUNTIFS('GERMANIA'!E2:E44,$A28,'GERMANIA'!AG2:AG44,"PASSA FORTE")+COUNTIFS('FRANCIA'!E2:E36,$A28,'FRANCIA'!AG2:AG36,"PASSA")+COUNTIFS('FRANCIA'!E2:E36,$A28,'FRANCIA'!AG2:AG36,"PASSA FORTE")+COUNTIFS('PAESI BASSI'!E2:E21,$A28,'PAESI BASSI'!AG2:AG21,"PASSA")+COUNTIFS('PAESI BASSI'!E2:E21,$A28,'PAESI BASSI'!AG2:AG21,"PASSA FORTE")+COUNTIFS('SVIZZERA'!E2:E24,$A28,'SVIZZERA'!AG2:AG24,"PASSA")+COUNTIFS('SVIZZERA'!E2:E24,$A28,'SVIZZERA'!AG2:AG24,"PASSA FORTE")+COUNTIFS('USA'!E2:E167,$A28,'USA'!AG2:AG167,"PASSA")+COUNTIFS('USA'!E2:E167,$A28,'USA'!AG2:AG167,"PASSA FORTE") | J28: =IFERROR((SUMIF('ITALIA'!E2:E67,$A28,'ITALIA'!P2:P67)+SUMIF('GERMANIA'!E2:E44,$A28,'GERMANIA'!P2:P44)+SUMIF('FRANCIA'!E2:E36,$A28,'FRANCIA'!P2:P36)+SUMIF('PAESI BASSI'!E2:E21,$A28,'PAESI BASSI'!P2:P21)+SUMIF('SVIZZERA'!E2:E24,$A28,'SVIZZERA'!P2:P24)+SUMIF('USA'!E2:E167,$A28,'USA'!P2:P167))/(COUNTIFS('ITALIA'!E2:E67,$A28,'ITALIA'!P2:P67,"<>")+COUNTIFS('GERMANIA'!E2:E44,$A28,'GERMANIA'!P2:P44,"<>")+COUNTIFS('FRANCIA'!E2:E36,$A28,'FRANCIA'!P2:P36,"<>")+COUNTIFS('PAESI BASSI'!E2:E21,$A28,'PAESI BASSI'!P2:P21,"<>")+COUNTIFS('SVIZZERA'!E2:E24,$A28,'SVIZZERA'!P2:P24,"<>")+COUNTIFS('USA'!E2:E167,$A28,'USA'!P2:P167,"<>")),"")
A29: Utility | B29: =COUNTIF('ITALIA'!E2:E67,$A29) | C29: =COUNTIF('GERMANIA'!E2:E44,$A29) | D29: =COUNTIF('FRANCIA'!E2:E36,$A29) | E29: =COUNTIF('PAESI BASSI'!E2:E21,$A29) | F29: =COUNTIF('SVIZZERA'!E2:E24,$A29) | G29: =COUNTIF('USA'!E2:E167,$A29) | H29: =SUM(B29:G29) | I29: =COUNTIFS('ITALIA'!E2:E67,$A29,'ITALIA'!AG2:AG67,"PASSA")+COUNTIFS('ITALIA'!E2:E67,$A29,'ITALIA'!AG2:AG67,"PASSA FORTE")+COUNTIFS('GERMANIA'!E2:E44,$A29,'GERMANIA'!AG2:AG44,"PASSA")+COUNTIFS('GERMANIA'!E2:E44,$A29,'GERMANIA'!AG2:AG44,"PASSA FORTE")+COUNTIFS('FRANCIA'!E2:E36,$A29,'FRANCIA'!AG2:AG36,"PASSA")+COUNTIFS('FRANCIA'!E2:E36,$A29,'FRANCIA'!AG2:AG36,"PASSA FORTE")+COUNTIFS('PAESI BASSI'!E2:E21,$A29,'PAESI BASSI'!AG2:AG21,"PASSA")+COUNTIFS('PAESI BASSI'!E2:E21,$A29,'PAESI BASSI'!AG2:AG21,"PASSA FORTE")+COUNTIFS('SVIZZERA'!E2:E24,$A29,'SVIZZERA'!AG2:AG24,"PASSA")+COUNTIFS('SVIZZERA'!E2:E24,$A29,'SVIZZERA'!AG2:AG24,"PASSA FORTE")+COUNTIFS('USA'!E2:E167,$A29,'USA'!AG2:AG167,"PASSA")+COUNTIFS('USA'!E2:E167,$A29,'USA'!AG2:AG167,"PASSA FORTE") | J29: =IFERROR((SUMIF('ITALIA'!E2:E67,$A29,'ITALIA'!P2:P67)+SUMIF('GERMANIA'!E2:E44,$A29,'GERMANIA'!P2:P44)+SUMIF('FRANCIA'!E2:E36,$A29,'FRANCIA'!P2:P36)+SUMIF('PAESI BASSI'!E2:E21,$A29,'PAESI BASSI'!P2:P21)+SUMIF('SVIZZERA'!E2:E24,$A29,'SVIZZERA'!P2:P24)+SUMIF('USA'!E2:E167,$A29,'USA'!P2:P167))/(COUNTIFS('ITALIA'!E2:E67,$A29,'ITALIA'!P2:P67,"<>")+COUNTIFS('GERMANIA'!E2:E44,$A29,'GERMANIA'!P2:P44,"<>")+COUNTIFS('FRANCIA'!E2:E36,$A29,'FRANCIA'!P2:P36,"<>")+COUNTIFS('PAESI BASSI'!E2:E21,$A29,'PAESI BASSI'!P2:P21,"<>")+COUNTIFS('SVIZZERA'!E2:E24,$A29,'SVIZZERA'!P2:P24,"<>")+COUNTIFS('USA'!E2:E167,$A29,'USA'!P2:P167,"<>")),"")
A30: Materiali | B30: =COUNTIF('ITALIA'!E2:E67,$A30) | C30: =COUNTIF('GERMANIA'!E2:E44,$A30) | D30: =COUNTIF('FRANCIA'!E2:E36,$A30) | E30: =COUNTIF('PAESI BASSI'!E2:E21,$A30) | F30: =COUNTIF('SVIZZERA'!E2:E24,$A30) | G30: =COUNTIF('USA'!E2:E167,$A30) | H30: =SUM(B30:G30) | I30: =COUNTIFS('ITALIA'!E2:E67,$A30,'ITALIA'!AG2:AG67,"PASSA")+COUNTIFS('ITALIA'!E2:E67,$A30,'ITALIA'!AG2:AG67,"PASSA FORTE")+COUNTIFS('GERMANIA'!E2:E44,$A30,'GERMANIA'!AG2:AG44,"PASSA")+COUNTIFS('GERMANIA'!E2:E44,$A30,'GERMANIA'!AG2:AG44,"PASSA FORTE")+COUNTIFS('FRANCIA'!E2:E36,$A30,'FRANCIA'!AG2:AG36,"PASSA")+COUNTIFS('FRANCIA'!E2:E36,$A30,'FRANCIA'!AG2:AG36,"PASSA FORTE")+COUNTIFS('PAESI BASSI'!E2:E21,$A30,'PAESI BASSI'!AG2:AG21,"PASSA")+COUNTIFS('PAESI BASSI'!E2:E21,$A30,'PAESI BASSI'!AG2:AG21,"PASSA FORTE")+COUNTIFS('SVIZZERA'!E2:E24,$A30,'SVIZZERA'!AG2:AG24,"PASSA")+COUNTIFS('SVIZZERA'!E2:E24,$A30,'SVIZZERA'!AG2:AG24,"PASSA FORTE")+COUNTIFS('USA'!E2:E167,$A30,'USA'!AG2:AG167,"PASSA")+COUNTIFS('USA'!E2:E167,$A30,'USA'!AG2:AG167,"PASSA FORTE") | J30: =IFERROR((SUMIF('ITALIA'!E2:E67,$A30,'ITALIA'!P2:P67)+SUMIF('GERMANIA'!E2:E44,$A30,'GERMANIA'!P2:P44)+SUMIF('FRANCIA'!E2:E36,$A30,'FRANCIA'!P2:P36)+SUMIF('PAESI BASSI'!E2:E21,$A30,'PAESI BASSI'!P2:P21)+SUMIF('SVIZZERA'!E2:E24,$A30,'SVIZZERA'!P2:P24)+SUMIF('USA'!E2:E167,$A30,'USA'!P2:P167))/(COUNTIFS('ITALIA'!E2:E67,$A30,'ITALIA'!P2:P67,"<>")+COUNTIFS('GERMANIA'!E2:E44,$A30,'GERMANIA'!P2:P44,"<>")+COUNTIFS('FRANCIA'!E2:E36,$A30,'FRANCIA'!P2:P36,"<>")+COUNTIFS('PAESI BASSI'!E2:E21,$A30,'PAESI BASSI'!P2:P21,"<>")+COUNTIFS('SVIZZERA'!E2:E24,$A30,'SVIZZERA'!P2:P24,"<>")+COUNTIFS('USA'!E2:E167,$A30,'USA'!P2:P167,"<>")),"")
A31: Immobiliare | B31: =COUNTIF('ITALIA'!E2:E67,$A31) | C31: =COUNTIF('GERMANIA'!E2:E44,$A31) | D31: =COUNTIF('FRANCIA'!E2:E36,$A31) | E31: =COUNTIF('PAESI BASSI'!E2:E21,$A31) | F31: =COUNTIF('SVIZZERA'!E2:E24,$A31) | G31: =COUNTIF('USA'!E2:E167,$A31) | H31: =SUM(B31:G31) | I31: =COUNTIFS('ITALIA'!E2:E67,$A31,'ITALIA'!AG2:AG67,"PASSA")+COUNTIFS('ITALIA'!E2:E67,$A31,'ITALIA'!AG2:AG67,"PASSA FORTE")+COUNTIFS('GERMANIA'!E2:E44,$A31,'GERMANIA'!AG2:AG44,"PASSA")+COUNTIFS('GERMANIA'!E2:E44,$A31,'GERMANIA'!AG2:AG44,"PASSA FORTE")+COUNTIFS('FRANCIA'!E2:E36,$A31,'FRANCIA'!AG2:AG36,"PASSA")+COUNTIFS('FRANCIA'!E2:E36,$A31,'FRANCIA'!AG2:AG36,"PASSA FORTE")+COUNTIFS('PAESI BASSI'!E2:E21,$A31,'PAESI BASSI'!AG2:AG21,"PASSA")+COUNTIFS('PAESI BASSI'!E2:E21,$A31,'PAESI BASSI'!AG2:AG21,"PASSA FORTE")+COUNTIFS('SVIZZERA'!E2:E24,$A31,'SVIZZERA'!AG2:AG24,"PASSA")+COUNTIFS('SVIZZERA'!E2:E24,$A31,'SVIZZERA'!AG2:AG24,"PASSA FORTE")+COUNTIFS('USA'!E2:E167,$A31,'USA'!AG2:AG167,"PASSA")+COUNTIFS('USA'!E2:E167,$A31,'USA'!AG2:AG167,"PASSA FORTE") | J31: =IFERROR((SUMIF('ITALIA'!E2:E67,$A31,'ITALIA'!P2:P67)+SUMIF('GERMANIA'!E2:E44,$A31,'GERMANIA'!P2:P44)+SUMIF('FRANCIA'!E2:E36,$A31,'FRANCIA'!P2:P36)+SUMIF('PAESI BASSI'!E2:E21,$A31,'PAESI BASSI'!P2:P21)+SUMIF('SVIZZERA'!E2:E24,$A31,'SVIZZERA'!P2:P24)+SUMIF('USA'!E2:E167,$A31,'USA'!P2:P167))/(COUNTIFS('ITALIA'!E2:E67,$A31,'ITALIA'!P2:P67,"<>")+COUNTIFS('GERMANIA'!E2:E44,$A31,'GERMANIA'!P2:P44,"<>")+COUNTIFS('FRANCIA'!E2:E36,$A31,'FRANCIA'!P2:P36,"<>")+COUNTIFS('PAESI BASSI'!E2:E21,$A31,'PAESI BASSI'!P2:P21,"<>")+COUNTIFS('SVIZZERA'!E2:E24,$A31,'SVIZZERA'!P2:P24,"<>")+COUNTIFS('USA'!E2:E167,$A31,'USA'!P2:P167,"<>")),"")
A32: Veicolo | B32: =COUNTIF('ITALIA'!E2:E67,$A32) | C32: =COUNTIF('GERMANIA'!E2:E44,$A32) | D32: =COUNTIF('FRANCIA'!E2:E36,$A32) | E32: =COUNTIF('PAESI BASSI'!E2:E21,$A32) | F32: =COUNTIF('SVIZZERA'!E2:E24,$A32) | G32: =COUNTIF('USA'!E2:E167,$A32) | H32: =SUM(B32:G32) | I32: =COUNTIFS('ITALIA'!E2:E67,$A32,'ITALIA'!AG2:AG67,"PASSA")+COUNTIFS('ITALIA'!E2:E67,$A32,'ITALIA'!AG2:AG67,"PASSA FORTE")+COUNTIFS('GERMANIA'!E2:E44,$A32,'GERMANIA'!AG2:AG44,"PASSA")+COUNTIFS('GERMANIA'!E2:E44,$A32,'GERMANIA'!AG2:AG44,"PASSA FORTE")+COUNTIFS('FRANCIA'!E2:E36,$A32,'FRANCIA'!AG2:AG36,"PASSA")+COUNTIFS('FRANCIA'!E2:E36,$A32,'FRANCIA'!AG2:AG36,"PASSA FORTE")+COUNTIFS('PAESI BASSI'!E2:E21,$A32,'PAESI BASSI'!AG2:AG21,"PASSA")+COUNTIFS('PAESI BASSI'!E2:E21,$A32,'PAESI BASSI'!AG2:AG21,"PASSA FORTE")+COUNTIFS('SVIZZERA'!E2:E24,$A32,'SVIZZERA'!AG2:AG24,"PASSA")+COUNTIFS('SVIZZERA'!E2:E24,$A32,'SVIZZERA'!AG2:AG24,"PASSA FORTE")+COUNTIFS('USA'!E2:E167,$A32,'USA'!AG2:AG167,"PASSA")+COUNTIFS('USA'!E2:E167,$A32,'USA'!AG2:AG167,"PASSA FORTE") | J32: =IFERROR((SUMIF('ITALIA'!E2:E67,$A32,'ITALIA'!P2:P67)+SUMIF('GERMANIA'!E2:E44,$A32,'GERMANIA'!P2:P44)+SUMIF('FRANCIA'!E2:E36,$A32,'FRANCIA'!P2:P36)+SUMIF('PAESI BASSI'!E2:E21,$A32,'PAESI BASSI'!P2:P21)+SUMIF('SVIZZERA'!E2:E24,$A32,'SVIZZERA'!P2:P24)+SUMIF('USA'!E2:E167,$A32,'USA'!P2:P167))/(COUNTIFS('ITALIA'!E2:E67,$A32,'ITALIA'!P2:P67,"<>")+COUNTIFS('GERMANIA'!E2:E44,$A32,'GERMANIA'!P2:P44,"<>")+COUNTIFS('FRANCIA'!E2:E36,$A32,'FRANCIA'!P2:P36,"<>")+COUNTIFS('PAESI BASSI'!E2:E21,$A32,'PAESI BASSI'!P2:P21,"<>")+COUNTIFS('SVIZZERA'!E2:E24,$A32,'SVIZZERA'!P2:P24,"<>")+COUNTIFS('USA'!E2:E167,$A32,'USA'!P2:P167,"<>")),"")
A34: Il ROE contabile di banche e assicurazioni non e' confrontabile con quello degli industriali: leggi i settori separatamente.
A35: Le colonne PREZZO € e CAP. MLN € sono convertite al cambio del giorno della rilevazione: usa quelle per confrontare le dimensioni fra mercati diversi.
A36: PUNTEGGIO: redditivita' 40 + costanza 20 + prezzo 30 + crescita 10, meno 8 se l'ultimo esercizio e' molto sotto la media dei cinque anni. POS. e' la classifica dentro il foglio.

Sheet ITALIA
A1: POS. | B1: TITOLO | C1: TICKER | D1: SETTORE | E1: CLASSE | F1: PREZZO | G1: VAL. | H1: PREZZO € | I1: CAP. MLN € | J1: CAP. MLN locale | K1: EPS TTM | L1: EPS ATTESO | M1: P/E | N1: P/B | O1: ROE IMPL. | P1: ROE 1a | Q1: ROE 5a | R1: VARIAB. ROE | S1: ANNI | T1: 2026 | U1: 2025 | V1: 2024 | W1: 2023 | X1: 2022 | Y1: DIVID. | Z1: RENDIM. | AA1: DEBITO/MP | AB1: CRESC. RICAVI | AC1: MARGINE | AD1: PUNTEGGIO | AE1: ESITO ROE | AF1: ESITO P/E | AG1: GIUDIZIO | AH1: RILEVATO | AI1: FONTE | AJ1: NOTE
A2: =IF(AD2="","",RANK(AD2,AD$2:AD$67)) | B2: Azimut Holding | C2: AZM.MI | D2: Risparmio gestito | E2: Finanziario | F2: 36.26 | G2: EUR | H2: 36.26 | I2: 5065.8 | J2: 5065.8 | K2: 3.72 | L2: 3.59593 | M2: =IF(OR(F2="",K2="",K2<=0),"",F2/K2) | N2: 2.6043236 | O2: =IF(OR(N2="",M2="",M2<=0),"",N2/M2) | P2: 0.29348 | Q2: 0.28096481 | R2: 0.01535347 | S2: 4 | U2: 0.25725356 | V2: 0.29958273 | W2: 0.28026383 | X2: 0.28675913 | Y2: 2 | Z2: =IF(OR(Y2="",F2="",F2=0),"",Y2/F2) | AA2: 4.261 | AB2: 0.17 | AC2: 0.37491421 | AD2: =IF(OR(Q2="",M2="",M2<=0),"",ROUND(40*MAX(0,MIN(N(Q2)/0.3,1))+IF(OR(R2="",N(Q2)<=0),10,20*MAX(0,1-MIN(R2/Q2,1)))+30*MAX(0,MIN((PARAMETRI!$B$5-M2)/MAX(PARAMETRI!$B$5-10,1),1))+IF(AB2="",3,10*MAX(0,MIN(AB2/0.15,1)))+IF(AND(P2<>"",N(P2)<N(Q2)*0.6),-8,0),1)) | AE2: =IF(AND(P2="",Q2=""),"DATI MANCANTI",IF(AND(N(P2)>=PARAMETRI!$B$4,N(Q2)>=PARAMETRI!$B$4),"OK","NO")) | AF2: =IF(M2="","N/D",IF(M2<PARAMETRI!$B$6,"OTTIMO",IF(M2<PARAMETRI!$B$5,"OK","NO"))) | AG2: =IF(OR(AE2="DATI MANCANTI",AF2="N/D"),"DA COMPLETARE",IF(AND(AE2="OK",AF2="OTTIMO"),"PASSA FORTE",IF(AND(AE2="OK",AF2="OK"),"PASSA","SCARTA"))) | AH2: 2026-10-12 | AI2: yahoo
A3: =IF(AD3="","",RANK(AD3,AD$2:AD$67)) | B3: Banca Generali | C3: BGN.MI | D3: Risparmio gestito | E3: Finanziario | F3: 62.55 | G3: EUR | H3: 62.55 | I3: 7135.9 | J3: 7135.9 | K3: 4.6 | L3: 3.84504 | M3: =IF(OR(F3="",K3="",K3<=0),"",F3/K3) | N3: 5.0766983 | O3: =IF(OR(N3="",M3="",M3<=0),"",N3/M3) | P3: 0.36488 | Q3: 0.26188408 | R3: 0.037246672 | S3: 4 | U3: 0.28382224 | V3: 0.29537517 | W3: 0.26888345 | X3: 0.19945547 | Y3: 2.85 | Z3: =IF(OR(Y3="",F3="",F3=0),"",Y3/F3) | AB3: 0.464 | AC3: 0.4480064 | AD3: =IF(OR(Q3="",M3="",M3<=0),"",ROUND(40*MAX(0,MIN(N(Q3)/0.3,1))+IF(OR(R3="",N(Q3)<=0),10,20*MAX(0,1-MIN(R3/Q3,1)))+30*MAX(0,MIN((PARAMETRI!$B$5-M3)/MAX(PARAMETRI!$B$5-10,1),1))+IF(AB3="",3,10*MAX(0,MIN(AB3/0.15,1)))+IF(AND(P3<>"",N(P3)<N(Q3)*0.6),-8,0),1)) | AE3: =IF(AND(P3="",Q3=""),"DATI MANCANTI",IF(AND(N(P3)>=PARAMETRI!$B$4,N(Q3)>=PARAMETRI!$B$4),"OK","NO")) | AF3: =IF(M3="","N/D",IF(M3<PARAMETRI!$B$6,"OTTIMO",IF(M3<PARAMETRI!$B$5,"OK","NO"))) | AG3: =IF(OR(AE3="DATI MANCANTI",AF3="N/D"),"DA COMPLETARE",IF(AND(AE3="OK",AF3="OTTIMO"),"PASSA FORTE",IF(AND(AE3="OK",AF3="OK"),"PASSA","SCARTA"))) | AH3: 2026-10-12 | AI3: yahoo
A4: =IF(AD4="","",RANK(AD4,AD$2:AD$67)) | B4: Banca Mediolanum | C4: BMED.MI | D4: Banca | E4: Finanziario | F4: 23 | G4: EUR | H4: 23 | I4: 17004.2 | J4: 17004.2 | K4: 1.77 | L4: 1.57559 | M4: =IF(OR(F4="",K4="",K4<=0),"",F4/K4) | N4: 3.7210805 | O4: =IF(OR(N4="",M4="",M4<=0),"",N4/M4) | P4: 0.30062 | Q4: 0.24084367 | R4: 0.042850695 | S4: 4 | U4: 0.27543582 | V4: 0.27811895 | W4: 0.23789634 | X4: 0.17192358 | Y4: 1.3 | Z4: =IF(OR(Y4="",F4="",F4=0),"",Y4/F4) | AB4: 0.29 | AC4: 0.53929675 | AD4: =IF(OR(Q4="",M4="",M4<=0),"",ROUND(40*MAX(0,MIN(N(Q4)/0.3,1))+IF(OR(R4="",N(Q4)<=0),10,20*MAX(0,1-MIN(R4/Q4,1)))+30*MAX(0,MIN((PARAMETRI!$B$5-M4)/MAX(PARAMETRI!$B$5-10,1),1))+IF(AB4="",3,10*MAX(0,MIN(AB4/0.15,1)))+IF(AND(P4<>"",N(P4)<N(Q4)*0.6),-8,0),1)) | AE4: =IF(AND(P4="",Q4=""),"DATI MANCANTI",IF(AND(N(P4)>=PARAMETRI!$B$4,N(Q4)>=PARAMETRI!$B$4),"OK","NO")) | AF4: =IF(M4="","N/D",IF(M4<PARAMETRI!$B$6,"OTTIMO",IF(M4<PARAMETRI!$B$5,"OK","NO"))) | AG4: =IF(OR(AE4="DATI MANCANTI",AF4="N/D"),"DA COMPLETARE",IF(AND(AE4="OK",AF4="OTTIMO"),"PASSA FORTE",IF(AND(AE4="OK",AF4="OK"),"PASSA","SCARTA"))) | AH4: 2026-10-12 | AI4: yahoo
A5: =IF(AD5="","",RANK(AD5,AD$2:AD$67)) | B5: Mondadori Editore | C5: MN.MI | D5: Editoria / Media | E5: Industriale | F5: 2.04 | G5: EUR | H5: 2.04 | I5: 532.1 | J5: 532.1 | K5: 0.2 | L5: 0.23706 | M5: =IF(OR(F5="",K5="",K5<=0),"",F5/K5) | N5: 1.8279569 | O5: =IF(OR(N5="",M5="",M5<=0),"",N5/M5) | P5: 0.18361 | Q5: 0.19271184 | R5: 0.019468584 | S5: 4 | U5: 0.16310796 | V5: 0.19050135 | W5: 0.21664243 | X5: 0.20059562 | Y5: 0.15 | Z5: =IF(OR(Y5="",F5="",F5=0),"",Y5/F5) | AA5: 129.372 | AB5: 0.089 | AC5: 0.055788974 | AD5: =IF(OR(Q5="",M5="",M5<=0),"",ROUND(40*MAX(0,MIN(N(Q5)/0.3,1))+IF(OR(R5="",N(Q5)<=0),10,20*MAX(0,1-MIN(R5/Q5,1)))+30*MAX(0,MIN((PARAMETRI!$B$5-M5)/MAX(PARAMETRI!$B$5-10,1),1))+IF(AB5="",3,10*MAX(0,MIN(AB5/0.15,1)))+IF(AND(P5<>"",N(P5)<N(Q5)*0.6),-8,0),1)) | AE5: =IF(AND(P5="",Q5=""),"DATI MANCANTI",IF(AND(N(P5)>=PARAMETRI!$B$4,N(Q5)>=PARAMETRI!$B$4),"OK","NO")) | AF5: =IF(M5="","N/D",IF(M5<PARAMETRI!$B$6,"OTTIMO",IF(M5<PARAMETRI!$B$5,"OK","NO"))) | AG5: =IF(OR(AE5="DATI MANCANTI",AF5="N/D"),"DA COMPLETARE",IF(AND(AE5="OK",AF5="OTTIMO"),"PASSA FORTE",IF(AND(AE5="OK",AF5="OK"),"PASSA","SCARTA"))) | AH5: 2026-10-12 | AI5: yahoo
A6: =IF(AD6="","",RANK(AD6,AD$2:AD$67)) | B6: Italgas | C6: IG.MI | D6: Utility / Reti | E6: Utility | F6: 8.252 | G6: EUR | H6: 8.252 | I6: 8388.3 | J6: 8388.3 | K6: 0.68 | L6: 0.79922 | M6: =IF(OR(F6="",K6="",K6<=0),"",F6/K6) | N6: 2.2248583 | O6: =IF(OR(N6="",M6="",M6<=0),"",N6/M6) | P6: 0.19063 | Q6: 0.18921117 | R6: 0.007636667 | S6: 4 | U6: 0.1760501 | V6: 0.19482106 | W6: 0.19278689 | X6: 0.19318662 | Y6: 0.43 | Z6: =IF(OR(Y6="",F6="",F6=0),"",Y6/F6) | AA6: 294.061 | AB6: 0.306 | AC6: 0.20630459 | AD6: =IF(OR(Q6="",M6="",M6<=0),"",ROUND(40*MAX(0,MIN(N(Q6)/0.3,1))+IF(OR(R6="",N(Q6)<=0),10,20*MAX(0,1-MIN(R6/Q6,1)))+30*MAX(0,MIN((PARAMETRI!$B$5-M6)/MAX(PARAMETRI!$B$5-10,1),1))+IF(AB6="",3,10*MAX(0,MIN(AB6/0.15,1)))+IF(AND(P6<>"",N(P6)<N(Q6)*0.6),-8,0),1)) | AE6: =IF(AND(P6="",Q6=""),"DATI MANCANTI",IF(AND(N(P6)>=PARAMETRI!$B$4,N(Q6)>=PARAMETRI!$B$4),"OK","NO")) | AF6: =IF(M6="","N/D",IF(M6<PARAMETRI!$B$6,"OTTIMO",IF(M6<PARAMETRI!$B$5,"OK","NO"))) | AG6: =IF(OR(AE6="DATI MANCANTI",AF6="N/D"),"DA COMPLETARE",IF(AND(AE6="OK",AF6="OTTIMO"),"PASSA FORTE",IF(AND(AE6="OK",AF6="OK"),"PASSA","SCARTA"))) | AH6: 2026-10-12 | AI6: yahoo
A7: =IF(AD7="","",RANK(AD7,AD$2:AD$67)) | B7: A2A | C7: A2A.MI | D7: Utility | E7: Utility | F7: 2.32 | G7: EUR | H7: 2.32 | I7: 7263.9 | J7: 7263.9 | K7: 0.22 | L7: 0.21117 | M7: =IF(OR(F7="",K7="",K7<=0),"",F7/K7) | N7: 1.3959086 | O7: =IF(OR(N7="",M7="",M7<=0),"",N7/M7) | P7: 0.11337 | Q7: 0.13528765 | R7: 0.02216392 | S7: 4 | U7: 0.12675342 | V7: 0.15612577 | W7: 0.15542453 | X7: 0.10284688 | Y7: 0.1 | Z7: =IF(OR(Y7="",F7="",F7=0),"",Y7/F7) | AA7: 113.764 | AB7: 0.314 | AC7: 0.050003639 | AD7: =IF(OR(Q7="",M7="",M7<=0),"",ROUND(40*MAX(0,MIN(N(Q7)/0.3,1))+IF(OR(R7="",N(Q7)<=0),10,20*MAX(0,1-MIN(R7/Q7,1)))+30*MAX(0,MIN((PARAMETRI!$B$5-M7)/MAX(PARAMETRI!$B$5-10,1),1))+IF(AB7="",3,10*MAX(0,MIN(AB7/0.15,1)))+IF(AND(P7<>"",N(P7)<N(Q7)*0.6),-8,0),1)) | AE7: =IF(AND(P7="",Q7=""),"DATI MANCANTI",IF(AND(N(P7)>=PARAMETRI!$B$4,N(Q7)>=PARAMETRI!$B$4),"OK","NO")) | AF7: =IF(M7="","N/D",IF(M7<PARAMETRI!$B$6,"OTTIMO",IF(M7<PARAMETRI!$B$5,"OK","NO"))) | AG7: =IF(OR(AE7="DATI MANCANTI",AF7="N/D"),"DA COMPLETARE",IF(AND(AE7="OK",AF7="OTTIMO"),"PASSA FORTE",IF(AND(AE7="OK",AF7="OK"),"PASSA","SCARTA"))) | AH7: 2026-10-12 | AI7: yahoo
A8: =IF(AD8="","",RANK(AD8,AD$2:AD$67)) | B8: Maire | C8: MAIRE.MI | D8: Impiantistica | E8: Industriale | F8: 12.72 | G8: EUR | H8: 12.72 | I8: 4155.3 | J8: 4155.3 | K8: 0.83 | L8: 1.02473 | M8: =IF(OR(F8="",K8="",K8<=0),"",F8/K8) | N8: 7.1702366 | O8: =IF(OR(N8="",M8="",M8<=0),"",N8/M8) | P8: 0.48770002 | Q8: 0.27984755 | R8: 0.072988074 | S8: 4 | U8: 0.36511535 | V8: 0.33347432 | W8: 0.23793896 | X8: 0.18286158 | Y8: 0.59 | Z8: =IF(OR(Y8="",F8="",F8=0),"",Y8/F8) | AA8: 235.473 | AB8: 0.095 | AC8: 0.03901697 | AD8: =IF(OR(Q8="",M8="",M8<=0),"",ROUND(40*MAX(0,MIN(N(Q8)/0.3,1))+IF(OR(R8="",N(Q8)<=0),10,20*MAX(0,1-MIN(R8/Q8,1)))+30*MAX(0,MIN((PARAMETRI!$B$5-M8)/MAX(PARAMETRI!$B$5-10,1),1))+IF(AB8="",3,10*MAX(0,MIN(AB8/0.15,1)))+IF(AND(P8<>"",N(P8)<N(Q8)*0.6),-8,0),1)) | AE8: =IF(AND(P8="",Q8=""),"DATI MANCANTI",IF(AND(N(P8)>=PARAMETRI!$B$4,N(Q8)>=PARAMETRI!$B$4),"OK","NO")) | AF8: =IF(M8="","N/D",IF(M8<PARAMETRI!$B$6,"OTTIMO",IF(M8<PARAMETRI!$B$5,"OK","NO"))) | AG8: =IF(OR(AE8="DATI MANCANTI",AF8="N/D"),"DA COMPLETARE",IF(AND(AE8="OK",AF8="OTTIMO"),"PASSA FORTE",IF(AND(AE8="OK",AF8="OK"),"PASSA","SCARTA"))) | AH8: 2026-10-12 | AI8: yahoo
A9: =IF(AD9="","",RANK(AD9,AD$2:AD$67)) | B9: Unipol | C9: UNI.MI | D9: Assicurazione | E9: Finanziario | F9: 24.92 | G9: EUR | H9: 24.92 | I9: 18380.4 | J9: 18380.4 | K9: 2.39 | L9: 2.26656 | M9: =IF(OR(F9="",K9="",K9<=0),"",F9/K9) | N9: 1.7794917 | O9: =IF(OR(N9="",M9="",M9<=0),"",N9/M9) | P9: 0.16938 | Q9: 0.11813762 | R9: 0.02618848 | S9: 4 | U9: 0.14262342 | V9: 0.11522369 | W9: 0.13819505 | X9: 0.076508307 | Y9: 1.12 | Z9: =IF(OR(Y9="",F9="",F9=0),"",Y9/F9) | AA9: 40.819 | AB9: 0.232 | AC9: 0.12542843 | AD9: =IF(OR(Q9="",M9="",M9<=0),"",ROUND(40*MAX(0,MIN(N(Q9)/0.3,1))+IF(OR(R9="",N(Q9)<=0),10,20*MAX(0,1-MIN(R9/Q9,1)))+30*MAX(0,MIN((PARAMETRI!$B$5-M9)/MAX(PARAMETRI!$B$5-10,1),1))+IF(AB9="",3,10*MAX(0,MIN(AB9/0.15,1)))+IF(AND(P9<>"",N(P9)<N(Q9)*0.6),-8,0),1)) | AE9: =IF(AND(P9="",Q9=""),"DATI MANCANTI",IF(AND(N(P9)>=PARAMETRI!$B$4,N(Q9)>=PARAMETRI!$B$4),"OK","NO")) | AF9: =IF(M9="","N/D",IF(M9<PARAMETRI!$B$6,"OTTIMO",IF(M9<PARAMETRI!$B$5,"OK","NO"))) | AG9: =IF(OR(AE9="DATI MANCANTI",AF9="N/D"),"DA COMPLETARE",IF(AND(AE9="OK",AF9="OTTIMO"),"PASSA FORTE",IF(AND(AE9="OK",AF9="OK"),"PASSA","SCARTA"))) | AH9: 2026-10-12 | AI9: yahoo
A10: =IF(AD10="","",RANK(AD10,AD$2:AD$67)) | B10: BPER Banca | C10: BPE.MI | D10: Banca | E10: Finanziario | F10: 13.584 | G10: EUR | H10: 13.584 | I10: 28419.5 | J10: 28419.5 | K10: 1.12 | L10: 1.30349 | M10: =IF(OR(F10="",K10="",K10<=0),"",F10/K10) | N10: 1.5729505 | O10: =IF(OR(N10="",M10="",M10<=0),"",N10/M10) | P10: 0.15279001 | Q10: 0.1445087 | R10: 0.029165584 | S10: 4 | U10: 0.10977616 | V10: 0.12353932 | W10: 0.16223274 | X10: 0.18248658 | Y10: 0.66 | Z10: =IF(OR(Y10="",F10="",F10=0),"",Y10/F10) | AB10: 0.54 | AC10: 0.31426131 | AD10: =IF(OR(Q10="",M10="",M10<=0),"",ROUND(40*MAX(0,MIN(N(Q10)/0.3,1))+IF(OR(R10="",N(Q10)<=0),10,20*MAX(0,1-MIN(R10/Q10,1)))+30*MAX(0,MIN((PARAMETRI!$B$5-M10)/MAX(PARAMETRI!$B$5-10,1),1))+IF(AB10="",3,10*MAX(0,MIN(AB10/0.15,1)))+IF(AND(P10<>"",N(P10)<N(Q10)*0.6),-8,0),1)) | AE10: =IF(AND(P10="",Q10=""),"DATI MANCANTI",IF(AND(N(P10)>=PARAMETRI!$B$4,N(Q10)>=PARAMETRI!$B$4),"OK","NO")) | AF10: =IF(M10="","N/D",IF(M10<PARAMETRI!$B$6,"OTTIMO",IF(M10<PARAMETRI!$B$5,"OK","NO"))) | AG10: =IF(OR(AE10="DATI MANCANTI",AF10="N/D"),"DA COMPLETARE",IF(AND(AE10="OK",AF10="OTTIMO"),"PASSA FORTE",IF(AND(AE10="OK",AF10="OK"),"PASSA","SCARTA"))) | AH10: 2026-10-12 | AI10: yahoo
A11: =IF(AD11="","",RANK(AD11,AD$2:AD$67)) | B11: Hera | C11: HER.MI | D11: Utility | E11: Utility | F11: 3.48 | G11: EUR | H11: 3.48 | I11: 5144.7 | J11: 5144.7 | K11: 0.32 | L11: 0.33202 | M11: =IF(OR(F11="",K11="",K11<=0),"",F11/K11) | N11: 1.2599565 | O11: =IF(OR(N11="",M11="",M11<=0),"",N11/M11) | P11: 0.12108 | Q11: 0.11290166 | R11: 0.023079781 | S11: 4 | U11: 0.11375998 | V11: 0.13437135 | W11: 0.12838113 | X11: 0.075094162 | Y11: 0.16 | Z11: =IF(OR(Y11="",F11="",F11=0),"",Y11/F11) | AA11: 133.318 | AB11: 0.217 | AC11: 0.036293651 | AD11: =IF(OR(Q11="",M11="",M11<=0),"",ROUND(40*MAX(0,MIN(N(Q11)/0.3,1))+IF(OR(R11="",N(Q11)<=0),10,20*MAX(0,1-MIN(R11/Q11,1)))+30*MAX(0,MIN((PARAMETRI!$B$5-M11)/MAX(PARAMETRI!$B$5-10,1),1))+IF(AB11="",3,10*MAX(0,MIN(AB11/0.15,1)))+IF(AND(P11<>"",N(P11)<N(Q11)*0.6),-8,0),1)) | AE11: =IF(AND(P11="",Q11=""),"DATI MANCANTI",IF(AND(N(P11)>=PARAMETRI!$B$4,N(Q11)>=PARAMETRI!$B$4),"OK","NO")) | AF11: =IF(M11="","N/D",IF(M11<PARAMETRI!$B$6,"OTTIMO",IF(M11<PARAMETRI!$B$5,"OK","NO"))) | AG11: =IF(OR(AE11="DATI MANCANTI",AF11="N/D"),"DA COMPLETARE",IF(AND(AE11="OK",AF11="OTTIMO"),"PASSA FORTE",IF(AND(AE11="OK",AF11="OK"),"PASSA","SCARTA"))) | AH11: 2026-10-12 | AI11: yahoo
A12: =IF(AD12="","",RANK(AD12,AD$2:AD$67)) | B12: Credito Emiliano | C12: CE.MI | D12: Banca | E12: Finanziario | F12: 20.04 | G12: EUR | H12: 20.04 | I12: 6815.3 | J12: 6815.3 | K12: 1.66 | L12: 1.70798 | M12: =IF(OR(F12="",K12="",K12<=0),"",F12/K12) | N12: 1.4429724 | O12: =IF(OR(N12="",M12="",M12<=0),"",N12/M12) | P12: 0.12286 | Q12: 0.13000628 | R12: 0.019597562 | S12: 4 | U12: 0.133281 | V12: 0.14444985 | W12: 0.14522979 | X12: 0.097064484 | Y12: 0.75 | Z12: =IF(OR(Y12="",F12="",F12=0),"",Y12/F12) | AB12: 0.165 | AC12: 0.27106269 | AD12: =IF(OR(Q12="",M12="",M12<=0),"",ROUND(40*MAX(0,MIN(N(Q12)/0.3,1))+IF(OR(R12="",N(Q12)<=0),10,20*MAX(0,1-MIN(R12/Q12,1)))+30*MAX(0,MIN((PARAMETRI!$B$5-M12)/MAX(PARAMETRI!$B$5-10,1),1))+IF(AB12="",3,10*MAX(0,MIN(AB12/0.15,1)))+IF(AND(P12<>"",N(P12)<N(Q12)*0.6),-8,0),1)) | AE12: =IF(AND(P12="",Q12=""),"DATI MANCANTI",IF(AND(N(P12)>=PARAMETRI!$B$4,N(Q12)>=PARAMETRI!$B$4),"OK","NO")) | AF12: =IF(M12="","N/D",IF(M12<PARAMETRI!$B$6,"OTTIMO",IF(M12<PARAMETRI!$B$5,"OK","NO"))) | AG12: =IF(OR(AE12="DATI MANCANTI",AF12="N/D"),"DA COMPLETARE",IF(AND(AE12="OK",AF12="OTTIMO"),"PASSA FORTE",IF(AND(AE12="OK",AF12="OK"),"PASSA","SCARTA"))) | AH12: 2026-10-12 | AI12: yahoo
A13: =IF(AD13="","",RANK(AD13,AD$2:AD$67)) | B13: RCS MediaGroup | C13: RCS.MI | D13: Editoria / Media | E13: Industriale | F13: 0.831 | G13: EUR | H13: 0.831 | I13: 429.9 | J13: 429.9 | K13: 0.11 | L13: 0.11 | M13: =IF(OR(F13="",K13="",K13<=0),"",F13/K13) | N13: 0.9347581 | O13: =IF(OR(N13="",M13="",M13<=0),"",N13/M13) | P13: 0.11979999 | Q13: 0.13134594 | R13: 0.0083535013 | S13: 4 | U13: 0.11907866 | V13: 0.140494 | W13: 0.1373825 | X13: 0.12842861 | Y13: 0.07 | Z13: =IF(OR(Y13="",F13="",F13=0),"",Y13/F13) | AA13: 29.396 | AB13: 0.004 | AC13: 0.068427066 | AD13: =IF(OR(Q13="",M13="",M13<=0),"",ROUND(40*MAX(0,MIN(N(Q13)/0.3,1))+IF(OR(R13="",N(Q13)<=0),10,20*MAX(0,1-MIN(R13/Q13,1)))+30*MAX(0,MIN((PARAMETRI!$B$5-M13)/MAX(PARAMETRI!$B$5-10,1),1))+IF(AB13="",3,10*MAX(0,MIN(AB13/0.15,1)))+IF(AND(P13<>"",N(P13)<N(Q13)*0.6),-8,0),1)) | AE13: =IF(AND(P13="",Q13=""),"DATI MANCANTI",IF(AND(N(P13)>=PARAMETRI!$B$4,N(Q13)>=PARAMETRI!$B$4),"OK","NO")) | AF13: =IF(M13="","N/D",IF(M13<PARAMETRI!$B$6,"OTTIMO",IF(M13<PARAMETRI!$B$5,"OK","NO"))) | AG13: =IF(OR(AE13="DATI MANCANTI",AF13="N/D"),"DA COMPLETARE",IF(AND(AE13="OK",AF13="OTTIMO"),"PASSA FORTE",IF(AND(AE13="OK",AF13="OK"),"PASSA","SCARTA"))) | AH13: 2026-10-12 | AI13: yahoo
A14: =IF(AD14="","",RANK(AD14,AD$2:AD$67)) | B14: Poste Italiane | C14: PST.MI | D14: Servizi finanziari | E14: Finanziario | F14: 24.35 | G14: EUR | H14: 24.35 | I14: 38895.6 | J14: 38895.6 | K14: 1.85 | L14: 1.98583 | M14: =IF(OR(F14="",K14="",K14<=0),"",F14/K14) | N14: 2.4553797 | O14: =IF(OR(N14="",M14="",M14<=0),"",N14/M14) | P14: 0.18174 | Q14: 0.17994135 | R14: 0.015492288 | S14: 4 | U14: 0.15998266 | V14: 0.17214884 | W14: 0.18620422 | X14: 0.20142967 | Y14: 1.25 | Z14: =IF(OR(Y14="",F14="",F14=0),"",Y14/F14) | AA14: 631.496 | AB14: 0.034 | AC14: 0.10319474 | AD14: =IF(OR(Q14="",M14="",M14<=0),"",ROUND(40*MAX(0,MIN(N(Q14)/0.3,1))+IF(OR(R14="",N(Q14)<=0),10,20*MAX(0,1-MIN(R14/Q14,1)))+30*MAX(0,MIN((PARAMETRI!$B$5-M14)/MAX(PARAMETRI!$B$5-10,1),1))+IF(AB14="",3,10*MAX(0,MIN(AB14/0.15,1)))+IF(AND(P14<>"",N(P14)<N(Q14)*0.6),-8,0),1)) | AE14: =IF(AND(P14="",Q14=""),"DATI MANCANTI",IF(AND(N(P14)>=PARAMETRI!$B$4,N(Q14)>=PARAMETRI!$B$4),"OK","NO")) | AF14: =IF(M14="","N/D",IF(M14<PARAMETRI!$B$6,"OTTIMO",IF(M14<PARAMETRI!$B$5,"OK","NO"))) | AG14: =IF(OR(AE14="DATI MANCANTI",AF14="N/D"),"DA COMPLETARE",IF(AND(AE14="OK",AF14="OTTIMO"),"PASSA FORTE",IF(AND(AE14="OK",AF14="OK"),"PASSA","SCARTA"))) | AH14: 2026-10-12 | AI14: yahoo
A15: =IF(AD15="","",RANK(AD15,AD$2:AD$67)) | B15: FinecoBank | C15: FBK.MI | D15: Banca | E15: Finanziario | F15: 21.3 | G15: EUR | H15: 21.3 | I15: 13031.7 | J15: 13031.7 | K15: 1.1 | L15: 1.28801 | M15: =IF(OR(F15="",K15="",K15<=0),"",F15/K15) | N15: 5.4378347 | O15: =IF(OR(N15="",M15="",M15<=0),"",N15/M15) | P15: 0.28855 | Q15: 0.25706242 | R15: 0.020975024 | S15: 4 | U15: 0.25341124 | V15: 0.27300118 | W15: 0.27753573 | X15: 0.22430155 | Y15: 0.79 | Z15: =IF(OR(Y15="",F15="",F15=0),"",Y15/F15) | AB15: 0.18 | AC15: 0.43118985 | AD15: =IF(OR(Q15="",M15="",M15<=0),"",ROUND(40*MAX(0,MIN(N(Q15)/0.3,1))+IF(OR(R15="",N(Q15)<=0),10,20*MAX(0,1-MIN(R15/Q15,1)))+30*MAX(0,MIN((PARAMETRI!$B$5-M15)/MAX(PARAMETRI!$B$5-10,1),1))+IF(AB15="",3,10*MAX(0,MIN(AB15/0.15,1)))+IF(AND(P15<>"",N(P15)<N(Q15)*0.6),-8,0),1)) | AE15: =IF(AND(P15="",Q15=""),"DATI MANCANTI",IF(AND(N(P15)>=PARAMETRI!$B$4,N(Q15)>=PARAMETRI!$B$4),"OK","NO")) | AF15: =IF(M15="","N/D",IF(M15<PARAMETRI!$B$6,"OTTIMO",IF(M15<PARAMETRI!$B$5,"OK","NO"))) | AG15: =IF(OR(AE15="DATI MANCANTI",AF15="N/D"),"DA COMPLETARE",IF(AND(AE15="OK",AF15="OTTIMO"),"PASSA FORTE",IF(AND(AE15="OK",AF15="OK"),"PASSA","SCARTA"))) | AH15: 2026-10-12 | AI15: yahoo
A16: =IF(AD16="","",RANK(AD16,AD$2:AD$67)) | B16: Ferrari | C16: RACE.MI | D16: Lusso / Auto | E16: Consumi | F16: 351 | G16: EUR | H16: 351 | I16: 61565.4 | J16: 61565.4 | K16: 9.23 | L16: 11.05319 | M16: =IF(OR(F16="",K16="",K16<=0),"",F16/K16) | N16: 16.878246 | O16: =IF(OR(N16="",M16="",M16<=0),"",N16/M16) | P16: 0.45439997 | Q16: 0.4020306 | R16: 0.026010469 | S16: 4 | U16: 0.40874398 | V16: 0.43064523 | W16: 0.40904731 | X16: 0.35968586 | Y16: 3.62 | Z16: =IF(OR(Y16="",F16="",F16=0),"",Y16/F16) | AA16: 86.386 | AB16: 0.084 | AC16: 0.22896293 | AD16: =IF(OR(Q16="",M16="",M16<=0),"",ROUND(40*MAX(0,MIN(N(Q16)/0.3,1))+IF(OR(R16="",N(Q16)<=0),10,20*MAX(0,1-MIN(R16/Q16,1)))+30*MAX(0,MIN((PARAMETRI!$B$5-M16)/MAX(PARAMETRI!$B$5-10,1),1))+IF(AB16="",3,10*MAX(0,MIN(AB16/0.15,1)))+IF(AND(P16<>"",N(P16)<N(Q16)*0.6),-8,0),1)) | AE16: =IF(AND(P16="",Q16=""),"DATI MANCANTI",IF(AND(N(P16)>=PARAMETRI!$B$4,N(Q16)>=PARAMETRI!$B$4),"OK","NO")) | AF16: =IF(M16="","N/D",IF(M16<PARAMETRI!$B$6,"OTTIMO",IF(M16<PARAMETRI!$B$5,"OK","NO"))) | AG16: =IF(OR(AE16="DATI MANCANTI",AF16="N/D"),"DA COMPLETARE",IF(AND(AE16="OK",AF16="OTTIMO"),"PASSA FORTE",IF(AND(AE16="OK",AF16="OK"),"PASSA","SCARTA"))) | AH16: 2026-10-12 | AI16: yahoo
A17: =IF(AD17="","",RANK(AD17,AD$2:AD$67)) | B17: Acea | C17: ACE.MI | D17: Utility | E17: Utility | F17: 20.24 | G17: EUR | H17: 20.24 | I17: 4302 | J17: 4302 | K17: 1.7 | L17: 1.58975 | M17: =IF(OR(F17="",K17="",K17<=0),"",F17/K17) | N17: 1.4436519 | O17: =IF(OR(N17="",M17="",M17<=0),"",N17/M17) | P17: 0.12430999 | Q17: 0.1377274 | R17: 0.020635625 | S17: 4 | U17: 0.17281687 | V17: 0.13237768 | W17: 0.123632 | X17: 0.12208306 | Y17: 0.95 | Z17: =IF(OR(Y17="",F17="",F17=0),"",Y17/F17) | AA17: 169.549 | AB17: 0.063 | AC17: 0.13134802 | AD17: =IF(OR(Q17="",M17="",M17<=0),"",ROUND(40*MAX(0,MIN(N(Q17)/0.3,1))+IF(OR(R17="",N(Q17)<=0),10,20*MAX(0,1-MIN(R17/Q17,1)))+30*MAX(0,MIN((PARAMETRI!$B$5-M17)/MAX(PARAMETRI!$B$5-10,1),1))+IF(AB17="",3,10*MAX(0,MIN(AB17/0.15,1)))+IF(AND(P17<>"",N(P17)<N(Q17)*0.6),-8,0),1)) | AE17: =IF(AND(P17="",Q17=""),"DATI MANCANTI",IF(AND(N(P17)>=PARAMETRI!$B$4,N(Q17)>=PARAMETRI!$B$4),"OK","NO")) | AF17: =IF(M17="","N/D",IF(M17<PARAMETRI!$B$6,"OTTIMO",IF(M17<PARAMETRI!$B$5,"OK","NO"))) | AG17: =IF(OR(AE17="DATI MANCANTI",AF17="N/D"),"DA COMPLETARE",IF(AND(AE17="OK",AF17="OTTIMO"),"PASSA FORTE",IF(AND(AE17="OK",AF17="OK"),"PASSA","SCARTA"))) | AH17: 2026-10-12 | AI17: yahoo
A18: =IF(AD18="","",RANK(AD18,AD$2:AD$67)) | B18: Buzzi | C18: BZU.MI | D18: Materiali / Cemento | E18: Materiali | F18: 37.14 | G18: EUR | H18: 37.14 | I18: 6552 | J18: 6552 | K18: 4.76 | L18: 4.83455 | M18: =IF(OR(F18="",K18="",K18<=0),"",F18/K18) | N18: 0.9003636 | O18: =IF(OR(N18="",M18="",M18<=0),"",N18/M18) | P18: 0.12303001 | Q18: 0.13450632 | R18: 0.028097184 | S18: 4 | U18: 0.13000006 | V18: 0.14271871 | W18: 0.17178884 | X18: 0.093517651 | Y18: 0.7 | Z18: =IF(OR(Y18="",F18="",F18=0),"",Y18/F18) | AA18: 6.827 | AB18: 0.001 | AC18: 0.19009803 | AD18: =IF(OR(Q18="",M18="",M18<=0),"",ROUND(40*MAX(0,MIN(N(Q18)/0.3,1))+IF(OR(R18="",N(Q18)<=0),10,20*MAX(0,1-MIN(R18/Q18,1)))+30*MAX(0,MIN((PARAMETRI!$B$5-M18)/MAX(PARAMETRI!$B$5-10,1),1))+IF(AB18="",3,10*MAX(0,MIN(AB18/0.15,1)))+IF(AND(P18<>"",N(P18)<N(Q18)*0.6),-8,0),1)) | AE18: =IF(AND(P18="",Q18=""),"DATI MANCANTI",IF(AND(N(P18)>=PARAMETRI!$B$4,N(Q18)>=PARAMETRI!$B$4),"OK","NO")) | AF18: =IF(M18="","N/D",IF(M18<PARAMETRI!$B$6,"OTTIMO",IF(M18<PARAMETRI!$B$5,"OK","NO"))) | AG18: =IF(OR(AE18="DATI MANCANTI",AF18="N/D"),"DA COMPLETARE",IF(AND(AE18="OK",AF18="OTTIMO"),"PASSA FORTE",IF(AND(AE18="OK",AF18="OK"),"PASSA","SCARTA"))) | AH18: 2026-10-12 | AI18: yahoo
A19: =IF(AD19="","",RANK(AD19,AD$2:AD$67)) | B19: UniCredit | C19: UCG.MI | D19: Banca | E19: Finanziario | F19: 76.25 | G19: EUR | H19: 76.25 | I19: 114981.4 | J19: 114981.4 | K19: 6.98 | L19: 8.41137 | M19: =IF(OR(F19="",K19="",K19<=0),"",F19/K19) | N19: 1.6223059 | O19: =IF(OR(N19="",M19="",M19<=0),"",N19/M19) | P19: 0.15779 | Q19: 0.14179344 | R19: 0.023444428 | S19: 4 | U19: 0.16119981 | V19: 0.15565093 | W19: 0.14836374 | X19: 0.1019593 | Y19: 3.15 | Z19: =IF(OR(Y19="",F19="",F19=0),"",Y19/F19) | AB19: -0.092 | AC19: 0.42849155 | AD19: =IF(OR(Q19="",M19="",M19<=0),"",ROUND(40*MAX(0,MIN(N(Q19)/0.3,1))+IF(OR(R19="",N(Q19)<=0),10,20*MAX(0,1-MIN(R19/Q19,1)))+30*MAX(0,MIN((PARAMETRI!$B$5-M19)/MAX(PARAMETRI!$B$5-10,1),1))+IF(AB19="",3,10*MAX(0,MIN(AB19/0.15,1)))+IF(AND(P19<>"",N(P19)<N(Q19)*0.6),-8,0),1)) | AE19: =IF(AND(P19="",Q19=""),"DATI MANCANTI",IF(AND(N(P19)>=PARAMETRI!$B$4,N(Q19)>=PARAMETRI!$B$4),"OK","NO")) | AF19: =IF(M19="","N/D",IF(M19<PARAMETRI!$B$6,"OTTIMO",IF(M19<PARAMETRI!$B$5,"OK","NO"))) | AG19: =IF(OR(AE19="DATI MANCANTI",AF19="N/D"),"DA COMPLETARE",IF(AND(AE19="OK",AF19="OTTIMO"),"PASSA FORTE",IF(AND(AE19="OK",AF19="OK"),"PASSA","SCARTA"))) | AH19: 2026-10-12 | AI19: yahoo
A20: =IF(AD20="","",RANK(AD20,AD$2:AD$67)) | B20: MFE-MediaForEurope A | C20: MFEA.MI | D20: Media / TV | E20: Industriale | F20: 2.086 | G20: EUR | H20: 2.086 | I20: 1462 | J20: 1462 | K20: 0.19 | L20: 0.48792 | M20: =IF(OR(F20="",K20="",K20<=0),"",F20/K20) | N20: 0.41895962 | O20: =IF(OR(N20="",M20="",M20<=0),"",N20/M20) | P20: 0.055760004 | Q20: 0.072151633 | R20: 0.014705008 | S20: 4 | U20: 0.086321229 | V20: 0.048070555 | W20: 0.072914851 | X20: 0.081299899 | Y20: 0.22 | Z20: =IF(OR(Y20="",F20="",F20=0),"",Y20/F20) | AA20: 88.622 | AB20: 0.945 | AC20: 0.04109692 | AD20: =IF(OR(Q20="",M20="",M20<=0),"",ROUND(40*MAX(0,MIN(N(Q20)/0.3,1))+IF(OR(R20="",N(Q20)<=0),10,20*MAX(0,1-MIN(R20/Q20,1)))+30*MAX(0,MIN((PARAMETRI!$B$5-M20)/MAX(PARAMETRI!$B$5-10,1),1))+IF(AB20="",3,10*MAX(0,MIN(AB20/0.15,1)))+IF(AND(P20<>"",N(P20)<N(Q20)*0.6),-8,0),1)) | AE20: =IF(AND(P20="",Q20=""),"DATI MANCANTI",IF(AND(N(P20)>=PARAMETRI!$B$4,N(Q20)>=PARAMETRI!$B$4),"OK","NO")) | AF20: =IF(M20="","N/D",IF(M20<PARAMETRI!$B$6,"OTTIMO",IF(M20<PARAMETRI!$B$5,"OK","NO"))) | AG20: =IF(OR(AE20="DATI MANCANTI",AF20="N/D"),"DA COMPLETARE",IF(AND(AE20="OK",AF20="OTTIMO"),"PASSA FORTE",IF(AND(AE20="OK",AF20="OK"),"PASSA","SCARTA"))) | AH20: 2026-10-12 | AI20: yahoo
A21: =IF(AD21="","",RANK(AD21,AD$2:AD$67)) | B21: Intesa Sanpaolo | C21: ISP.MI | D21: Banca | E21: Finanziario | F21: 6.184 | G21: EUR | H21: 6.184 | I21: 106934.3 | J21: 106934.3 | K21: 0.56 | L21: 0.65382 | M21: =IF(OR(F21="",K21="",K21<=0),"",F21/K21) | N21: 1.5815856 | O21: =IF(OR(N21="",M21="",M21<=0),"",N21/M21) | P21: 0.14261 | Q21: 0.11707234 | R21: 0.02736362 | S21: 4 | U21: 0.14290314 | V21: 0.13296305 | W21: 0.12075731 | X21: 0.071665876 | Y21: 0.38 | Z21: =IF(OR(Y21="",F21="",F21=0),"",Y21/F21) | AB21: 0.064 | AC21: 0.33856777 | AD21: =IF(OR(Q21="",M21="",M21<=0),"",ROUND(40*MAX(0,MIN(N(Q21)/0.3,1))+IF(OR(R21="",N(Q21)<=0),10,20*MAX(0,1-MIN(R21/Q21,1)))+30*MAX(0,MIN((PARAMETRI!$B$5-M21)/MAX(PARAMETRI!$B$5-10,1),1))+IF(AB21="",3,10*MAX(0,MIN(AB21/0.15,1)))+IF(AND(P21<>"",N(P21)<N(Q21)*0.6),-8,0),1)) | AE21: =IF(AND(P21="",Q21=""),"DATI MANCANTI",IF(AND(N(P21)>=PARAMETRI!$B$4,N(Q21)>=PARAMETRI!$B$4),"OK","NO")) | AF21: =IF(M21="","N/D",IF(M21<PARAMETRI!$B$6,"OTTIMO",IF(M21<PARAMETRI!$B$5,"OK","NO"))) | AG21: =IF(OR(AE21="DATI MANCANTI",AF21="N/D"),"DA COMPLETARE",IF(AND(AE21="OK",AF21="OTTIMO"),"PASSA FORTE",IF(AND(AE21="OK",AF21="OK"),"PASSA","SCARTA"))) | AH21: 2026-10-12 | AI21: yahoo
A22: =IF(AD22="","",RANK(AD22,AD$2:AD$67)) | B22: Iren | C22: IRE.MI | D22: Utility | E22: Utility | F22: 2.402 | G22: EUR | H22: 2.402 | I22: 3081.9 | J22: 3081.9 | K22: 0.23 | L22: 0.24707 | M22: =IF(OR(F22="",K22="",K22<=0),"",F22/K22) | N22: 1.0452567 | O22: =IF(OR(N22="",M22="",M22<=0),"",N22/M22) | P22: 0.08586001 | Q22: 0.088337892 | R22: 0.0041596522 | S22: 4 | U22: 0.086886862 | V22: 0.093347969 | W22: 0.090781581 | X22: 0.082335155 | Y22: 0.14 | Z22: =IF(OR(Y22="",F22="",F22=0),"",Y22/F22) | AA22: 129.504 | AB22: 0.028 | AC22: 0.046420933 | AD22: =IF(OR(Q22="",M22="",M22<=0),"",ROUND(40*MAX(0,MIN(N(Q22)/0.3,1))+IF(OR(R22="",N(Q22)<=0),10,20*MAX(0,1-MIN(R22/Q22,1)))+30*MAX(0,MIN((PARAMETRI!$B$5-M22)/MAX(PARAMETRI!$B$5-10,1),1))+IF(AB22="",3,10*MAX(0,MIN(AB22/0.15,1)))+IF(AND(P22<>"",N(P22)<N(Q22)*0.6),-8,0),1)) | AE22: =IF(AND(P22="",Q22=""),"DATI MANCANTI",IF(AND(N(P22)>=PARAMETRI!$B$4,N(Q22)>=PARAMETRI!$B$4),"OK","NO")) | AF22: =IF(M22="","N/D",IF(M22<PARAMETRI!$B$6,"OTTIMO",IF(M22<PARAMETRI!$B$5,"OK","NO"))) | AG22: =IF(OR(AE22="DATI MANCANTI",AF22="N/D"),"DA COMPLETARE",IF(AND(AE22="OK",AF22="OTTIMO"),"PASSA FORTE",IF(AND(AE22="OK",AF22="OK"),"PASSA","SCARTA"))) | AH22: 2026-10-12 | AI22: yahoo
A23: =IF(AD23="","",RANK(AD23,AD$2:AD$67)) | B23: Banca Ifis | C23: IF.MI | D23: Banca | E23: Finanziario | F23: 10.15 | G23: EUR | H23: 10.15 | I23: 620 | J23: 620 | K23: 4.22 | L23: 1.95776 | M23: =IF(OR(F23="",K23="",K23<=0),"",F23/K23) | N23: 0.30243436 | O23: =IF(OR(N23="",M23="",M23<=0),"",N23/M23) | P23: 0.12864 | Q23: 0.10808371 | R23: 0.027030354 | S23: 4 | U23: 0.15473378 | V23: 0.093273144 | W23: 0.095334271 | X23: 0.088993654 | Y23: 2.12 | Z23: =IF(OR(Y23="",F23="",F23=0),"",Y23/F23) | AB23: -0.253 | AC23: 0.34675755 | AD23: =IF(OR(Q23="",M23="",M23<=0),"",ROUND(40*MAX(0,MIN(N(Q23)/0.3,1))+IF(OR(R23="",N(Q23)<=0),10,20*MAX(0,1-MIN(R23/Q23,1)))+30*MAX(0,MIN((PARAMETRI!$B$5-M23)/MAX(PARAMETRI!$B$5-10,1),1))+IF(AB23="",3,10*MAX(0,MIN(AB23/0.15,1)))+IF(AND(P23<>"",N(P23)<N(Q23)*0.6),-8,0),1)) | AE23: =IF(AND(P23="",Q23=""),"DATI MANCANTI",IF(AND(N(P23)>=PARAMETRI!$B$4,N(Q23)>=PARAMETRI!$B$4),"OK","NO")) | AF23: =IF(M23="","N/D",IF(M23<PARAMETRI!$B$6,"OTTIMO",IF(M23<PARAMETRI!$B$5,"OK","NO"))) | AG23: =IF(OR(AE23="DATI MANCANTI",AF23="N/D"),"DA COMPLETARE",IF(AND(AE23="OK",AF23="OTTIMO"),"PASSA FORTE",IF(AND(AE23="OK",AF23="OK"),"PASSA","SCARTA"))) | AH23: 2026-10-12 | AI23: yahoo
A24: =IF(AD24="","",RANK(AD24,AD$2:AD$67)) | B24: Banca Monte dei Paschi | C24: BMPS.MI | D24: Banca | E24: Finanziario | F24: 11.15 | G24: EUR | H24: 11.15 | I24: 33878.4 | J24: 33878.4 | K24: 1.19 | L24: 0.89188 | M24: =IF(OR(F24="",K24="",K24<=0),"",F24/K24) | N24: 1.283084 | O24: =IF(OR(N24="",M24="",M24<=0),"",N24/M24) | P24: 0.15022 | Q24: 0.1118793 | R24: 0.086897105 | S24: 4 | U24: 0.097124119 | V24: 0.16746431 | W24: 0.20562105 | X24: -0.022692257 | Y24: 0.86 | Z24: =IF(OR(Y24="",F24="",F24=0),"",Y24/F24) | AB24: 0.995 | AC24: 0.58804123 | AD24: =IF(OR(Q24="",M24="",M24<=0),"",ROUND(40*MAX(0,MIN(N(Q24)/0.3,1))+IF(OR(R24="",N(Q24)<=0),10,20*MAX(0,1-MIN(R24/Q24,1)))+30*MAX(0,MIN((PARAMETRI!$B$5-M24)/MAX(PARAMETRI!$B$5-10,1),1))+IF(AB24="",3,10*MAX(0,MIN(AB24/0.15,1)))+IF(AND(P24<>"",N(P24)<N(Q24)*0.6),-8,0),1)) | AE24: =IF(AND(P24="",Q24=""),"DATI MANCANTI",IF(AND(N(P24)>=PARAMETRI!$B$4,N(Q24)>=PARAMETRI!$B$4),"OK","NO")) | AF24: =IF(M24="","N/D",IF(M24<PARAMETRI!$B$6,"OTTIMO",IF(M24<PARAMETRI!$B$5,"OK","NO"))) | AG24: =IF(OR(AE24="DATI MANCANTI",AF24="N/D"),"DA COMPLETARE",IF(AND(AE24="OK",AF24="OTTIMO"),"PASSA FORTE",IF(AND(AE24="OK",AF24="OK"),"PASSA","SCARTA"))) | AH24: 2026-10-12 | AI24: yahoo
A25: =IF(AD25="","",RANK(AD25,AD$2:AD$67)) | B25: Brunello Cucinelli | C25: BC.MI | D25: Lusso | E25: Consumi | F25: 81.2 | G25: EUR | H25: 81.2 | I25: 5521.6 | J25: 5521.6 | K25: 2.03 | L25: 2.62682 | M25: =IF(OR(F25="",K25="",K25<=0),"",F25/K25) | N25: 10.076942 | O25: =IF(OR(N25="",M25="",M25<=0),"",N25/M25) | P25: 0.26791 | Q25: 0.24032482 | R25: 0.01805966 | S25: 4 | U25: 0.24730596 | V25: 0.24386351 | W25: 0.25943715 | X25: 0.21069265 | Y25: 1.04 | Z25: =IF(OR(Y25="",F25="",F25=0),"",Y25/F25) | AA25: 217.133 | AB25: 0.095 | AC25: 0.097938772 | AD25: =IF(OR(Q25="",M25="",M25<=0),"",ROUND(40*MAX(0,MIN(N(Q25)/0.3,1))+IF(OR(R25="",N(Q25)<=0),10,20*MAX(0,1-MIN(R25/Q25,1)))+30*MAX(0,MIN((PARAMETRI!$B$5-M25)/MAX(PARAMETRI!$B$5-10,1),1))+IF(AB25="",3,10*MAX(0,MIN(AB25/0.15,1)))+IF(AND(P25<>"",N(P25)<N(Q25)*0.6),-8,0),1)) | AE25: =IF(AND(P25="",Q25=""),"DATI MANCANTI",IF(AND(N(P25)>=PARAMETRI!$B$4,N(Q25)>=PARAMETRI!$B$4),"OK","NO")) | AF25: =IF(M25="","N/D",IF(M25<PARAMETRI!$B$6,"OTTIMO",IF(M25<PARAMETRI!$B$5,"OK","NO"))) | AG25: =IF(OR(AE25="DATI MANCANTI",AF25="N/D"),"DA COMPLETARE",IF(AND(AE25="OK",AF25="OTTIMO"),"PASSA FORTE",IF(AND(AE25="OK",AF25="OK"),"PASSA","SCARTA"))) | AH25: 2026-10-12 | AI25: yahoo
A26: =IF(AD26="","",RANK(AD26,AD$2:AD$67)) | B26: Brembo | C26: BRE.MI | D26: Componentistica auto | E26: Industriale | F26: 9.94 | G26: EUR | H26: 9.94 | I26: 3162 | J26: 3162 | K26: 0.72 | L26: 0.84929 | M26: =IF(OR(F26="",K26="",K26<=0),"",F26/K26) | N26: 1.3496265 | O26: =IF(OR(N26="",M26="",M26<=0),"",N26/M26) | P26: 0.10133001 | Q26: 0.12656566 | R26: 0.025146184 | S26: 4 | U26: 0.091288645 | V26: 0.1144502 | W26: 0.14751898 | X26: 0.15300481 | Y26: 0.3 | Z26: =IF(OR(Y26="",F26="",F26=0),"",Y26/F26) | AA26: 58.738 | AB26: 0.061 | AC26: 0.061535021 | AD26: =IF(OR(Q26="",M26="",M26<=0),"",ROUND(40*MAX(0,MIN(N(Q26)/0.3,1))+IF(OR(R26="",N(Q26)<=0),10,20*MAX(0,1-MIN(R26/Q26,1)))+30*MAX(0,MIN((PARAMETRI!$B$5-M26)/MAX(PARAMETRI!$B$5-10,1),1))+IF(AB26="",3,10*MAX(0,MIN(AB26/0.15,1)))+IF(AND(P26<>"",N(P26)<N(Q26)*0.6),-8,0),1)) | AE26: =IF(AND(P26="",Q26=""),"DATI MANCANTI",IF(AND(N(P26)>=PARAMETRI!$B$4,N(Q26)>=PARAMETRI!$B$4),"OK","NO")) | AF26: =IF(M26="","N/D",IF(M26<PARAMETRI!$B$6,"OTTIMO",IF(M26<PARAMETRI!$B$5,"OK","NO"))) | AG26: =IF(OR(AE26="DATI MANCANTI",AF26="N/D"),"DA COMPLETARE",IF(AND(AE26="OK",AF26="OTTIMO"),"PASSA FORTE",IF(AND(AE26="OK",AF26="OK"),"PASSA","SCARTA"))) | AH26: 2026-10-12 | AI26: yahoo
A27: =IF(AD27="","",RANK(AD27,AD$2:AD$67)) | B27: Recordati | C27: REC.MI | D27: Farmaceutica | E27: Salute | F27: 52.95 | G27: EUR | H27: 52.95 | I27: 11013.6 | J27: 11013.6 | K27: 2.38 | L27: 3.7615 | M27: =IF(OR(F27="",K27="",K27<=0),"",F27/K27) | N27: 5.089878 | O27: =IF(OR(N27="",M27="",M27<=0),"",N27/M27) | P27: 0.24851999 | Q27: 0.22144951 | R27: 0.011819602 | S27: 4 | U27: 0.23108161 | V27: 0.22192349 | W27: 0.23079687 | X27: 0.20199606 | Y27: 1.42 | Z27: =IF(OR(Y27="",F27="",F27=0),"",Y27/F27) | AA27: 108.586 | AB27: 0.083 | AC27: 0.1898794 | AD27: =IF(OR(Q27="",M27="",M27<=0),"",ROUND(40*MAX(0,MIN(N(Q27)/0.3,1))+IF(OR(R27="",N(Q27)<=0),10,20*MAX(0,1-MIN(R27/Q27,1)))+30*MAX(0,MIN((PARAMETRI!$B$5-M27)/MAX(PARAMETRI!$B$5-10,1),1))+IF(AB27="",3,10*MAX(0,MIN(AB27/0.15,1)))+IF(AND(P27<>"",N(P27)<N(Q27)*0.6),-8,0),1)) | AE27: =IF(AND(P27="",Q27=""),"DATI MANCANTI",IF(AND(N(P27)>=PARAMETRI!$B$4,N(Q27)>=PARAMETRI!$B$4),"OK","NO")) | AF27: =IF(M27="","N/D",IF(M27<PARAMETRI!$B$6,"OTTIMO",IF(M27<PARAMETRI!$B$5,"OK","NO"))) | AG27: =IF(OR(AE27="DATI MANCANTI",AF27="N/D"),"DA COMPLETARE",IF(AND(AE27="OK",AF27="OTTIMO"),"PASSA FORTE",IF(AND(AE27="OK",AF27="OK"),"PASSA","SCARTA"))) | AH27: 2026-10-12 | AI27: yahoo
A28: =IF(AD28="","",RANK(AD28,AD$2:AD$67)) | B28: Assicurazioni Generali | C28: G.MI | D28: Assicurazione | E28: Finanziario | F28: 42.06 | G28: EUR | H28: 42.06 | I28: 63182.9 | J28: 63182.9 | K28: 2.95 | L28: 3.40268 | M28: =IF(OR(F28="",K28="",K28<=0),"",F28/K28) | N28: 1.9810654 | O28: =IF(OR(N28="",M28="",M28<=0),"",N28/M28) | P28: 0.1514 | Q28: 0.1164673 | R28: 0.019052157 | S28: 4 | U28: 0.13011477 | V28: 0.12254434 | W28: 0.12934516 | X28: 0.083864916 | Y28: 1.64 | Z28: =IF(OR(Y28="",F28="",F28=0),"",Y28/F28) | AA28: 118.93 | AB28: 0.054 | AC28: 0.061052435 | AD28: =IF(OR(Q28="",M28="",M28<=0),"",ROUND(40*MAX(0,MIN(N(Q28)/0.3,1))+IF(OR(R28="",N(Q28)<=0),10,20*MAX(0,1-MIN(R28/Q28,1)))+30*MAX(0,MIN((PARAMETRI!$B$5-M28)/MAX(PARAMETRI!$B$5-10,1),1))+IF(AB28="",3,10*MAX(0,MIN(AB28/0.15,1)))+IF(AND(P28<>"",N(P28)<N(Q28)*0.6),-8,0),1)) | AE28: =IF(AND(P28="",Q28=""),"DATI MANCANTI",IF(AND(N(P28)>=PARAMETRI!$B$4,N(Q28)>=PARAMETRI!$B$4),"OK","NO")) | AF28: =IF(M28="","N/D",IF(M28<PARAMETRI!$B$6,"OTTIMO",IF(M28<PARAMETRI!$B$5,"OK","NO"))) | AG28: =IF(OR(AE28="DATI MANCANTI",AF28="N/D"),"DA COMPLETARE",IF(AND(AE28="OK",AF28="OTTIMO"),"PASSA FORTE",IF(AND(AE28="OK",AF28="OK"),"PASSA","SCARTA"))) | AH28: 2026-10-12 | AI28: yahoo
A29: =IF(AD29="","",RANK(AD29,AD$2:AD$67)) | B29: Banca Profilo | C29: PRO.MI | D29: Banca | E29: Finanziario | F29: 1.482 | G29: EUR | H29: 1.482 | I29: 97.9 | J29: 97.9 | K29: 0.13 | L29: 0.158 | M29: =IF(OR(F29="",K29="",K29<=0),"",F29/K29) | N29: 0.60663116 | O29: =IF(OR(N29="",M29="",M29<=0),"",N29/M29) | P29: 0.05441 | Q29: 0.065030776 | R29: 0.006357037 | S29: 4 | U29: 0.060088544 | V29: 0.057656964 | W29: 0.073060489 | X29: 0.069317106 | Y29: 0.07 | Z29: =IF(OR(Y29="",F29="",F29=0),"",Y29/F29) | AB29: -0.28 | AC29: 0.1279504 | AD29: =IF(OR(Q29="",M29="",M29<=0),"",ROUND(40*MAX(0,MIN(N(Q29)/0.3,1))+IF(OR(R29="",N(Q29)<=0),10,20*MAX(0,1-MIN(R29/Q29,1)))+30*MAX(0,MIN((PARAMETRI!$B$5-M29)/MAX(PARAMETRI!$B$5-10,1),1))+IF(AB29="",3,10*MAX(0,MIN(AB29/0.15,1)))+IF(AND(P29<>"",N(P29)<N(Q29)*0.6),-8,0),1)) | AE29: =IF(AND(P29="",Q29=""),"DATI MANCANTI",IF(AND(N(P29)>=PARAMETRI!$B$4,N(Q29)>=PARAMETRI!$B$4),"OK","NO")) | AF29: =IF(M29="","N/D",IF(M29<PARAMETRI!$B$6,"OTTIMO",IF(M29<PARAMETRI!$B$5,"OK","NO"))) | AG29: =IF(OR(AE29="DATI MANCANTI",AF29="N/D"),"DA COMPLETARE",IF(AND(AE29="OK",AF29="OTTIMO"),"PASSA FORTE",IF(AND(AE29="OK",AF29="OK"),"PASSA","SCARTA"))) | AH29: 2026-10-12 | AI29: yahoo
A30: =IF(AD30="","",RANK(AD30,AD$2:AD$67)) | B30: Banco BPM | C30: BAMI.MI | D30: Banca | E30: Finanziario | F30: 14.735 | G30: EUR | H30: 14.735 | I30: 22182.1 | J30: 22182.1 | K30: 1.27 | L30: 1.42879 | M30: =IF(OR(F30="",K30="",K30<=0),"",F30/K30) | N30: 1.4202409 | O30: =IF(OR(N30="",M30="",M30<=0),"",N30/M30) | P30: 0.12613 | Q30: 0.10212113 | R30: 0.033509752 | S30: 4 | U30: 0.13428123 | V30: 0.13149825 | W30: 0.090072996 | X30: 0.052632052 | Y30: 1 | Z30: =IF(OR(Y30="",F30="",F30=0),"",Y30/F30) | AB30: -0.055 | AC30: 0.29035565 | AD30: =IF(OR(Q30="",M30="",M30<=0),"",ROUND(40*MAX(0,MIN(N(Q30)/0.3,1))+IF(OR(R30="",N(Q30)<=0),10,20*MAX(0,1-MIN(R30/Q30,1)))+30*MAX(0,MIN((PARAMETRI!$B$5-M30)/MAX(PARAMETRI!$B$5-10,1),1))+IF(AB30="",3,10*MAX(0,MIN(AB30/0.15,1)))+IF(AND(P30<>"",N(P30)<N(Q30)*0.6),-8,0),1)) | AE30: =IF(AND(P30="",Q30=""),"DATI MANCANTI",IF(AND(N(P30)>=PARAMETRI!$B$4,N(Q30)>=PARAMETRI!$B$4),"OK","NO")) | AF30: =IF(M30="","N/D",IF(M30<PARAMETRI!$B$6,"OTTIMO",IF(M30<PARAMETRI!$B$5,"OK","NO"))) | AG30: =IF(OR(AE30="DATI MANCANTI",AF30="N/D"),"DA COMPLETARE",IF(AND(AE30="OK",AF30="OTTIMO"),"PASSA FORTE",IF(AND(AE30="OK",AF30="OK"),"PASSA","SCARTA"))) | AH30: 2026-10-09 | AI30: yahoo
A31: =IF(AD31="","",RANK(AD31,AD$2:AD$67)) | B31: Terna | C31: TRN.MI | D31: Utility / Reti | E31: Utility | F31: 9.174 | G31: EUR | H31: 9.174 | I31: 18399.1 | J31: 18399.1 | K31: 0.51 | L31: 0.55945 | M31: =IF(OR(F31="",K31="",K31<=0),"",F31/K31) | N31: 3.0951416 | O31: =IF(OR(N31="",M31="",M31<=0),"",N31/M31) | P31: 0.13828 | Q31: 0.14731665 | R31: 0.012305617 | S31: 4 | V31: 0.14113128 | W31: 0.13999747 | X31: 0.1395311 | Y31: 0.4 | Z31: =IF(OR(Y31="",F31="",F31=0),"",Y31/F31) | AA31: 172.37 | AB31: 0.123 | AC31: 0.29185489 | AD31: =IF(OR(Q31="",M31="",M31<=0),"",ROUND(40*MAX(0,MIN(N(Q31)/0.3,1))+IF(OR(R31="",N(Q31)<=0),10,20*MAX(0,1-MIN(R31/Q31,1)))+30*MAX(0,MIN((PARAMETRI!$B$5-M31)/MAX(PARAMETRI!$B$5-10,1),1))+IF(AB31="",3,10*MAX(0,MIN(AB31/0.15,1)))+IF(AND(P31<>"",N(P31)<N(Q31)*0.6),-8,0),1)) | AE31: =IF(AND(P31="",Q31=""),"DATI MANCANTI",IF(AND(N(P31)>=PARAMETRI!$B$4,N(Q31)>=PARAMETRI!$B$4),"OK","NO")) | AF31: =IF(M31="","N/D",IF(M31<PARAMETRI!$B$6,"OTTIMO",IF(M31<PARAMETRI!$B$5,"OK","NO"))) | AG31: =IF(OR(AE31="DATI MANCANTI",AF31="N/D"),"DA COMPLETARE",IF(AND(AE31="OK",AF31="OTTIMO"),"PASSA FORTE",IF(AND(AE31="OK",AF31="OK"),"PASSA","SCARTA"))) | AH31: 2026-10-12 | AI31: yahoo
A32: =IF(AD32="","",RANK(AD32,AD$2:AD$67)) | B32: MFE-MediaForEurope B | C32: MFEB.MI | D32: Media / TV | E32: Industriale | F32: 2.78 | G32: EUR | H32: 2.78 | I32: 1945 | J32: 1945 | K32: 0.19 | L32: 0.5222 | M32: =IF(OR(F32="",K32="",K32<=0),"",F32/K32) | N32: 0.558345 | O32: =IF(OR(N32="",M32="",M32<=0),"",N32/M32) | P32: 0.055760004 | Q32: 0.072151633 | R32: 0.014705008 | S32: 4 | U32: 0.086321229 | V32: 0.048070555 | W32: 0.072914851 | X32: 0.081299899 | Y32: 0.22 | Z32: =IF(OR(Y32="",F32="",F32=0),"",Y32/F32) | AA32: 88.622 | AB32: 0.945 | AC32: 0.04109692 | AD32: =IF(OR(Q32="",M32="",M32<=0),"",ROUND(40*MAX(0,MIN(N(Q32)/0.3,1))+IF(OR(R32="",N(Q32)<=0),10,20*MAX(0,1-MIN(R32/Q32,1)))+30*MAX(0,MIN((PARAMETRI!$B$5-M32)/MAX(PARAMETRI!$B$5-10,1),1))+IF(AB32="",3,10*MAX(0,MIN(AB32/0.15,1)))+IF(AND(P32<>"",N(P32)<N(Q32)*0.6),-8,0),1)) | AE32: =IF(AND(P32="",Q32=""),"DATI MANCANTI",IF(AND(N(P32)>=PARAMETRI!$B$4,N(Q32)>=PARAMETRI!$B$4),"OK","NO")) | AF32: =IF(M32="","N/D",IF(M32<PARAMETRI!$B$6,"OTTIMO",IF(M32<PARAMETRI!$B$5,"OK","NO"))) | AG32: =IF(OR(AE32="DATI MANCANTI",AF32="N/D"),"DA COMPLETARE",IF(AND(AE32="OK",AF32="OTTIMO"),"PASSA FORTE",IF(AND(AE32="OK",AF32="OK"),"PASSA","SCARTA"))) | AH32: 2026-10-12 | AI32: yahoo | AJ32: Stessa societa' di MFEA, voto multiplo
A33: =IF(AD33="","",RANK(AD33,AD$2:AD$67)) | B33: Pirelli & C. | C33: PIRC.MI | D33: Componentistica auto | E33: Industriale | F33: 6.63 | G33: EUR | H33: 6.63 | I33: 7192.8 | J33: 7192.8 | K33: 0.5 | L33: 0.57562 | M33: =IF(OR(F33="",K33="",K33<=0),"",F33/K33) | N33: 1.1244912 | O33: =IF(OR(N33="",M33="",M33<=0),"",N33/M33) | P33: 0.09134 | Q33: 0.081554515 | R33: 0.0034164553 | S33: 4 | U33: 0.079251202 | V33: 0.081302159 | W33: 0.087194345 | X33: 0.078470354 | Y33: 0.24 | Z33: =IF(OR(Y33="",F33="",F33=0),"",Y33/F33) | AA33: 46.887 | AB33: 0.005 | AC33: 0.076365579 | AD33: =IF(OR(Q33="",M33="",M33<=0),"",ROUND(40*MAX(0,MIN(N(Q33)/0.3,1))+IF(OR(R33="",N(Q33)<=0),10,20*MAX(0,1-MIN(R33/Q33,1)))+30*MAX(0,MIN((PARAMETRI!$B$5-M33)/MAX(PARAMETRI!$B$5-10,1),1))+IF(AB33="",3,10*MAX(0,MIN(AB33/0.15,1)))+IF(AND(P33<>"",N(P33)<N(Q33)*0.6),-8,0),1)) | AE33: =IF(AND(P33="",Q33=""),"DATI MANCANTI",IF(AND(N(P33)>=PARAMETRI!$B$4,N(Q33)>=PARAMETRI!$B$4),"OK","NO")) | AF33: =IF(M33="","N/D",IF(M33<PARAMETRI!$B$6,"OTTIMO",IF(M33<PARAMETRI!$B$5,"OK","NO"))) | AG33: =IF(OR(AE33="DATI MANCANTI",AF33="N/D"),"DA COMPLETARE",IF(AND(AE33="OK",AF33="OTTIMO"),"PASSA FORTE",IF(AND(AE33="OK",AF33="OK"),"PASSA","SCARTA"))) | AH33: 2026-10-12 | AI33: yahoo
A34: =IF(AD34="","",RANK(AD34,AD$2:AD$67)) | B34: Mediobanca | C34: MB.MI | D34: Banca | E34: Finanziario | F34: 25.57 | G34: EUR | H34: 25.57 | I34: 20623.1 | J34: 20623.1 | K34: 1.51 | L34: 1.86656 | M34: =IF(OR(F34="",K34="",K34<=0),"",F34/K34) | N34: 1.781261 | O34: =IF(OR(N34="",M34="",M34<=0),"",N34/M34) | P34: 0.091996066 | Q34: 0.10177075 | R34: 0.014055353 | S34: 4 | U34: 0.11717542 | V34: 0.11413228 | W34: 0.090591319 | X34: 0.085183988 | Y34: 1.26 | Z34: =IF(OR(Y34="",F34="",F34=0),"",Y34/F34) | AB34: 0.151 | AC34: 0.32776287 | AD34: =IF(OR(Q34="",M34="",M34<=0),"",ROUND(40*MAX(0,MIN(N(Q34)/0.3,1))+IF(OR(R34="",N(Q34)<=0),10,20*MAX(0,1-MIN(R34/Q34,1)))+30*MAX(0,MIN((PARAMETRI!$B$5-M34)/MAX(PARAMETRI!$B$5-10,1),1))+IF(AB34="",3,10*MAX(0,MIN(AB34/0.15,1)))+IF(AND(P34<>"",N(P34)<N(Q34)*0.6),-8,0),1)) | AE34: =IF(AND(P34="",Q34=""),"DATI MANCANTI",IF(AND(N(P34)>=PARAMETRI!$B$4,N(Q34)>=PARAMETRI!$B$4),"OK","NO")) | AF34: =IF(M34="","N/D",IF(M34<PARAMETRI!$B$6,"OTTIMO",IF(M34<PARAMETRI!$B$5,"OK","NO"))) | AG34: =IF(OR(AE34="DATI MANCANTI",AF34="N/D"),"DA COMPLETARE",IF(AND(AE34="OK",AF34="OTTIMO"),"PASSA FORTE",IF(AND(AE34="OK",AF34="OK"),"PASSA","SCARTA"))) | AH34: 2026-10-12 | AI34: yahoo | AJ34: Coinvolta nel risiko bancario: verificare se ancora quotata
A35: =IF(AD35="","",RANK(AD35,AD$2:AD$67)) | B35: Moncler | C35: MONC.MI | D35: Lusso | E35: Consumi | F35: 44.09 | G35: EUR | H35: 44.09 | I35: 11992 | J35: 11992 | K35: 2.35 | L35: 2.54811 | M35: =IF(OR(F35="",K35="",K35<=0),"",F35/K35) | N35: 3.2866194 | O35: =IF(OR(N35="",M35="",M35<=0),"",N35/M35) | P35: 0.18122 | Q35: 0.18513494 | R35: 0.016920539 | S35: 4 | U35: 0.16278437 | V35: 0.17833033 | W35: 0.19037561 | X35: 0.20904944 | Y35: 1.4 | Z35: =IF(OR(Y35="",F35="",F35=0),"",Y35/F35) | AA35: 33.88 | AB35: 0.052 | AC35: 0.20367047 | AD35: =IF(OR(Q35="",M35="",M35<=0),"",ROUND(40*MAX(0,MIN(N(Q35)/0.3,1))+IF(OR(R35="",N(Q35)<=0),10,20*MAX(0,1-MIN(R35/Q35,1)))+30*MAX(0,MIN((PARAMETRI!$B$5-M35)/MAX(PARAMETRI!$B$5-10,1),1))+IF(AB35="",3,10*MAX(0,MIN(AB35/0.15,1)))+IF(AND(P35<>"",N(P35)<N(Q35)*0.6),-8,0),1)) | AE35: =IF(AND(P35="",Q35=""),"DATI MANCANTI",IF(AND(N(P35)>=PARAMETRI!$B$4,N(Q35)>=PARAMETRI!$B$4),"OK","NO")) | AF35: =IF(M35="","N/D",IF(M35<PARAMETRI!$B$6,"OTTIMO",IF(M35<PARAMETRI!$B$5,"OK","NO"))) | AG35: =IF(OR(AE35="DATI MANCANTI",AF35="N/D"),"DA COMPLETARE",IF(AND(AE35="OK",AF35="OTTIMO"),"PASSA FORTE",IF(AND(AE35="OK",AF35="OK"),"PASSA","SCARTA"))) | AH35: 2026-10-12 | AI35: yahoo
A36: =IF(AD36="","",RANK(AD36,AD$2:AD$67)) | B36: Webuild | C36: WBD.MI | D36: Costruzioni | E36: Industriale | F36: 1.912 | G36: EUR | H36: 1.912 | I36: 1890.6 | J36: 1890.6 | K36: 0.25 | L36: 0.35671 | M36: =IF(OR(F36="",K36="",K36<=0),"",F36/K36) | N36: 1.0765765 | O36: =IF(OR(N36="",M36="",M36<=0),"",N36/M36) | P36: 0.11915 | Q36: 0.086239053 | R36: 0.050993013 | S36: 4 | U36: 0.14319686 | V36: 0.11350257 | W36: 0.081990279 | X36: 0.0062665127 | Y36: 0.08 | Z36: =IF(OR(Y36="",F36="",F36=0),"",Y36/F36) | AA36: 175.257 | AB36: -0.034 | AC36: 0.019232604 | AD36: =IF(OR(Q36="",M36="",M36<=0),"",ROUND(40*MAX(0,MIN(N(Q36)/0.3,1))+IF(OR(R36="",N(Q36)<=0),10,20*MAX(0,1-MIN(R36/Q36,1)))+30*MAX(0,MIN((PARAMETRI!$B$5-M36)/MAX(PARAMETRI!$B$5-10,1),1))+IF(AB36="",3,10*MAX(0,MIN(AB36/0.15,1)))+IF(AND(P36<>"",N(P36)<N(Q36)*0.6),-8,0),1)) | AE36: =IF(AND(P36="",Q36=""),"DATI MANCANTI",IF(AND(N(P36)>=PARAMETRI!$B$4,N(Q36)>=PARAMETRI!$B$4),"OK","NO")) | AF36: =IF(M36="","N/D",IF(M36<PARAMETRI!$B$6,"OTTIMO",IF(M36<PARAMETRI!$B$5,"OK","NO"))) | AG36: =IF(OR(AE36="DATI MANCANTI",AF36="N/D"),"DA COMPLETARE",IF(AND(AE36="OK",AF36="OTTIMO"),"PASSA FORTE",IF(AND(AE36="OK",AF36="OK"),"PASSA","SCARTA"))) | AH36: 2026-10-12 | AI36: yahoo
A37: =IF(AD37="","",RANK(AD37,AD$2:AD$67)) | B37: Snam | C37: SRG.MI | D37: Utility / Reti | E37: Utility | F37: 5.664 | G37: EUR | H37: 5.664 | I37: 19010.7 | J37: 19010.7 | K37: 0.33 | L37: 0.43643 | M37: =IF(OR(F37="",K37="",K37<=0),"",F37/K37) | N37: 2.2977688 | O37: =IF(OR(N37="",M37="",M37<=0),"",N37/M37) | P37: 0.1238 | Q37: 0.12924982 | R37: 0.023103066 | S37: 4 | U37: 0.13749053 | V37: 0.14100123 | W37: 0.1486575 | X37: 0.089850027 | Y37: 0.3 | Z37: =IF(OR(Y37="",F37="",F37=0),"",Y37/F37) | AA37: 234.16 | AB37: 0.097 | AC37: 0.28894079 | AD37: =IF(OR(Q37="",M37="",M37<=0),"",ROUND(40*MAX(0,MIN(N(Q37)/0.3,1))+IF(OR(R37="",N(Q37)<=0),10,20*MAX(0,1-MIN(R37/Q37,1)))+30*MAX(0,MIN((PARAMETRI!$B$5-M37)/MAX(PARAMETRI!$B$5-10,1),1))+IF(AB37="",3,10*MAX(0,MIN(AB37/0.15,1)))+IF(AND(P37<>"",N(P37)<N(Q37)*0.6),-8,0),1)) | AE37: =IF(AND(P37="",Q37=""),"DATI MANCANTI",IF(AND(N(P37)>=PARAMETRI!$B$4,N(Q37)>=PARAMETRI!$B$4),"OK","NO")) | AF37: =IF(M37="","N/D",IF(M37<PARAMETRI!$B$6,"OTTIMO",IF(M37<PARAMETRI!$B$5,"OK","NO"))) | AG37: =IF(OR(AE37="DATI MANCANTI",AF37="N/D"),"DA COMPLETARE",IF(AND(AE37="OK",AF37="OTTIMO"),"PASSA FORTE",IF(AND(AE37="OK",AF37="OK"),"PASSA","SCARTA"))) | AH37: 2026-10-12 | AI37: yahoo
A38: =IF(AD38="","",RANK(AD38,AD$2:AD$67)) | B38: Prysmian | C38: PRY.MI | D38: Cavi / Elettrificazione | E38: Industriale | F38: 122.45 | G38: EUR | H38: 122.45 | I38: 36646.1 | J38: 36646.1 | K38: 4.7 | L38: 6.14147 | M38: =IF(OR(F38="",K38="",K38<=0),"",F38/K38) | N38: 5.0453234 | O38: =IF(OR(N38="",M38="",M38<=0),"",N38/M38) | P38: 0.22361 | Q38: 0.1549929 | R38: 0.023807167 | S38: 4 | U38: 0.19616929 | V38: 0.14330647 | W38: 0.13991008 | X38: 0.14058577 | Y38: 0.9 | Z38: =IF(OR(Y38="",F38="",F38=0),"",Y38/F38) | AA38: 74.976 | AB38: 0.226 | AC38: 0.069363871 | AD38: =IF(OR(Q38="",M38="",M38<=0),"",ROUND(40*MAX(0,MIN(N(Q38)/0.3,1))+IF(OR(R38="",N(Q38)<=0),10,20*MAX(0,1-MIN(R38/Q38,1)))+30*MAX(0,MIN((PARAMETRI!$B$5-M38)/MAX(PARAMETRI!$B$5-10,1),1))+IF(AB38="",3,10*MAX(0,MIN(AB38/0.15,1)))+IF(AND(P38<>"",N(P38)<N(Q38)*0.6),-8,0),1)) | AE38: =IF(AND(P38="",Q38=""),"DATI MANCANTI",IF(AND(N(P38)>=PARAMETRI!$B$4,N(Q38)>=PARAMETRI!$B$4),"OK","NO")) | AF38: =IF(M38="","N/D",IF(M38<PARAMETRI!$B$6,"OTTIMO",IF(M38<PARAMETRI!$B$5,"OK","NO"))) | AG38: =IF(OR(AE38="DATI MANCANTI",AF38="N/D"),"DA COMPLETARE",IF(AND(AE38="OK",AF38="OTTIMO"),"PASSA FORTE",IF(AND(AE38="OK",AF38="OK"),"PASSA","SCARTA"))) | AH38: 2026-10-12 | AI38: yahoo
A39: =IF(AD39="","",RANK(AD39,AD$2:AD$67)) | B39: Tenaris | C39: TEN.MI | D39: Oil service | E39: Energia | F39: 25.97 | G39: EUR | H39: 25.97 | I39: 26220.3 | J39: 26220.3 | K39: 1.61 | L39: 1.9102482 | M39: =IF(OR(F39="",K39="",K39<=0),"",F39/K39) | N39: 1.733116 | O39: =IF(OR(N39="",M39="",M39<=0),"",N39/M39) | P39: 0.11584 | Q39: 0.1638511 | R39: 0.047589709 | S39: 4 | U39: 0.11644019 | V39: 0.12272726 | W39: 0.23262314 | X39: 0.18361379 | Y39: 0.77 | Z39: =IF(OR(Y39="",F39="",F39=0),"",Y39/F39) | AA39: 2.596 | AB39: -0.039 | AC39: 0.15961706 | AD39: =IF(OR(Q39="",M39="",M39<=0),"",ROUND(40*MAX(0,MIN(N(Q39)/0.3,1))+IF(OR(R39="",N(Q39)<=0),10,20*MAX(0,1-MIN(R39/Q39,1)))+30*MAX(0,MIN((PARAMETRI!$B$5-M39)/MAX(PARAMETRI!$B$5-10,1),1))+IF(AB39="",3,10*MAX(0,MIN(AB39/0.15,1)))+IF(AND(P39<>"",N(P39)<N(Q39)*0.6),-8,0),1)) | AE39: =IF(AND(P39="",Q39=""),"DATI MANCANTI",IF(AND(N(P39)>=PARAMETRI!$B$4,N(Q39)>=PARAMETRI!$B$4),"OK","NO")) | AF39: =IF(M39="","N/D",IF(M39<PARAMETRI!$B$6,"OTTIMO",IF(M39<PARAMETRI!$B$5,"OK","NO"))) | AG39: =IF(OR(AE39="DATI MANCANTI",AF39="N/D"),"DA COMPLETARE",IF(AND(AE39="OK",AF39="OTTIMO"),"PASSA FORTE",IF(AND(AE39="OK",AF39="OK"),"PASSA","SCARTA"))) | AH39: 2026-10-12 | AI39: yahoo | AJ39: Bilancio in USD
A40: =IF(AD40="","",RANK(AD40,AD$2:AD$67)) | B40: Danieli & C. ord. | C40: DAN.MI | D40: Impiantistica | E40: Industriale | F40: 49.56 | G40: EUR | H40: 49.56 | I40: 3547.1 | J40: 3547.1 | K40: 3.21 | L40: 4.40998 | M40: =IF(OR(F40="",K40="",K40<=0),"",F40/K40) | N40: 1.2427282 | O40: =IF(OR(N40="",M40="",M40<=0),"",N40/M40) | P40: 0.08036 | Q40: 0.096844093 | R40: 0.0039747084 | S40: 3 | V40: 0.091660351 | W40: 0.10131854 | X40: 0.097553393 | Y40: 0.31 | Z40: =IF(OR(Y40="",F40="",F40=0),"",Y40/F40) | AA40: 29.397 | AB40: -0.048 | AC40: 0.053364433 | AD40: =IF(OR(Q40="",M40="",M40<=0),"",ROUND(40*MAX(0,MIN(N(Q40)/0.3,1))+IF(OR(R40="",N(Q40)<=0),10,20*MAX(0,1-MIN(R40/Q40,1)))+30*MAX(0,MIN((PARAMETRI!$B$5-M40)/MAX(PARAMETRI!$B$5-10,1),1))+IF(AB40="",3,10*MAX(0,MIN(AB40/0.15,1)))+IF(AND(P40<>"",N(P40)<N(Q40)*0.6),-8,0),1)) | AE40: =IF(AND(P40="",Q40=""),"DATI MANCANTI",IF(AND(N(P40)>=PARAMETRI!$B$4,N(Q40)>=PARAMETRI!$B$4),"OK","NO")) | AF40: =IF(M40="","N/D",IF(M40<PARAMETRI!$B$6,"OTTIMO",IF(M40<PARAMETRI!$B$5,"OK","NO"))) | AG40: =IF(OR(AE40="DATI MANCANTI",AF40="N/D"),"DA COMPLETARE",IF(AND(AE40="OK",AF40="OTTIMO"),"PASSA FORTE",IF(AND(AE40="OK",AF40="OK"),"PASSA","SCARTA"))) | AH40: 2026-10-12 | AI40: yahoo | AJ40: Verificare se posizione e' su risparmio (DANR.MI)
A41: =IF(AD41="","",RANK(AD41,AD$2:AD$67)) | B41: Lottomatica Group | C41: LTMC.MI | D41: Gaming / Concessioni | E41: Consumi | F41: 24.36 | G41: EUR | H41: 24.36 | I41: 5627.8 | J41: 5627.8 | K41: 0.9 | L41: 2.24474 | M41: =IF(OR(F41="",K41="",K41<=0),"",F41/K41) | N41: 25.29595 | O41: =IF(OR(N41="",M41="",M41<=0),"",N41/M41) | P41: 0.54611 | Q41: 0.56658119 | R41: 0.50688088 | S41: 4 | U41: 0.53617682 | V41: 0.19035309 | W41: 0.13642844 | X41: 1.4033664 | Y41: 0.44 | Z41: =IF(OR(Y41="",F41="",F41=0),"",Y41/F41) | AA41: 889.71 | AB41: 0.043 | AC41: 0.098034102 | AD41: =IF(OR(Q41="",M41="",M41<=0),"",ROUND(40*MAX(0,MIN(N(Q41)/0.3,1))+IF(OR(R41="",N(Q41)<=0),10,20*MAX(0,1-MIN(R41/Q41,1)))+30*MAX(0,MIN((PARAMETRI!$B$5-M41)/MAX(PARAMETRI!$B$5-10,1),1))+IF(AB41="",3,10*MAX(0,MIN(AB41/0.15,1)))+IF(AND(P41<>"",N(P41)<N(Q41)*0.6),-8,0),1)) | AE41: =IF(AND(P41="",Q41=""),"DATI MANCANTI",IF(AND(N(P41)>=PARAMETRI!$B$4,N(Q41)>=PARAMETRI!$B$4),"OK","NO")) | AF41: =IF(M41="","N/D",IF(M41<PARAMETRI!$B$6,"OTTIMO",IF(M41<PARAMETRI!$B$5,"OK","NO"))) | AG41: =IF(OR(AE41="DATI MANCANTI",AF41="N/D"),"DA COMPLETARE",IF(AND(AE41="OK",AF41="OTTIMO"),"PASSA FORTE",IF(AND(AE41="OK",AF41="OK"),"PASSA","SCARTA"))) | AH41: 2026-10-12 | AI41: yahoo
A42: =IF(AD42="","",RANK(AD42,AD$2:AD$67)) | B42: Banco Desio e Brianza | C42: BDB.MI | D42: Banca | E42: Finanziario | F42: 16.62 | G42: EUR | H42: 16.62 | I42: 2185.1 | J42: 2185.1 | K42: 1.02 | M42: =IF(OR(F42="",K42="",K42<=0),"",F42/K42) | N42: 1.4598156 | O42: =IF(OR(N42="",M42="",M42<=0),"",N42/M42) | P42: 0.09042 | Q42: 0.10577326 | R42: 0.041816717 | S42: 4 | U42: 0.085412703 | V42: 0.087587281 | W42: 0.17751724 | X42: 0.072575803 | Y42: 0.51 | Z42: =IF(OR(Y42="",F42="",F42=0),"",Y42/F42) | AB42: 0.079 | AC42: 0.20614905 | AD42: =IF(OR(Q42="",M42="",M42<=0),"",ROUND(40*MAX(0,MIN(N(Q42)/0.3,1))+IF(OR(R42="",N(Q42)<=0),10,20*MAX(0,1-MIN(R42/Q42,1)))+30*MAX(0,MIN((PARAMETRI!$B$5-M42)/MAX(PARAMETRI!$B$5-10,1),1))+IF(AB42="",3,10*MAX(0,MIN(AB42/0.15,1)))+IF(AND(P42<>"",N(P42)<N(Q42)*0.6),-8,0),1)) | AE42: =IF(AND(P42="",Q42=""),"DATI MANCANTI",IF(AND(N(P42)>=PARAMETRI!$B$4,N(Q42)>=PARAMETRI!$B$4),"OK","NO")) | AF42: =IF(M42="","N/D",IF(M42<PARAMETRI!$B$6,"OTTIMO",IF(M42<PARAMETRI!$B$5,"OK","NO"))) | AG42: =IF(OR(AE42="DATI MANCANTI",AF42="N/D"),"DA COMPLETARE",IF(AND(AE42="OK",AF42="OTTIMO"),"PASSA FORTE",IF(AND(AE42="OK",AF42="OK"),"PASSA","SCARTA"))) | AH42: 2026-10-12 | AI42: yahoo
A43: =IF(AD43="","",RANK(AD43,AD$2:AD$67)) | B43: Leonardo | C43: LDO.MI | D43: Difesa / Aerospazio | E43: Industriale | F43: 47.64 | G43: EUR | H43: 47.64 | I43: 27478.6 | J43: 27478.6 | K43: 2 | L43: 2.86701 | M43: =IF(OR(F43="",K43="",K43<=0),"",F43/K43) | N43: 2.8463883 | O43: =IF(OR(N43="",M43="",M43<=0),"",N43/M43) | P43: 0.11893 | Q43: 0.11522831 | R43: 0.018207252 | S43: 4 | U43: 0.12803347 | V43: 0.11946607 | W43: 0.084358974 | X43: 0.12905471 | Y43: 0.63 | Z43: =IF(OR(Y43="",F43="",F43=0),"",Y43/F43) | AA43: 41.533 | AB43: 0.167 | AC43: 0.057734707 | AD43: =IF(OR(Q43="",M43="",M43<=0),"",ROUND(40*MAX(0,MIN(N(Q43)/0.3,1))+IF(OR(R43="",N(Q43)<=0),10,20*MAX(0,1-MIN(R43/Q43,1)))+30*MAX(0,MIN((PARAMETRI!$B$5-M43)/MAX(PARAMETRI!$B$5-10,1),1))+IF(AB43="",3,10*MAX(0,MIN(AB43/0.15,1)))+IF(AND(P43<>"",N(P43)<N(Q43)*0.6),-8,0),1)) | AE43: =IF(AND(P43="",Q43=""),"DATI MANCANTI",IF(AND(N(P43)>=PARAMETRI!$B$4,N(Q43)>=PARAMETRI!$B$4),"OK","NO")) | AF43: =IF(M43="","N/D",IF(M43<PARAMETRI!$B$6,"OTTIMO",IF(M43<PARAMETRI!$B$5,"OK","NO"))) | AG43: =IF(OR(AE43="DATI MANCANTI",AF43="N/D"),"DA COMPLETARE",IF(AND(AE43="OK",AF43="OTTIMO"),"PASSA FORTE",IF(AND(AE43="OK",AF43="OK"),"PASSA","SCARTA"))) | AH43: 2026-10-12 | AI43: yahoo
A44: =IF(AD44="","",RANK(AD44,AD$2:AD$67)) | B44: Interpump Group | C44: IP.MI | D44: Meccanica | E44: Industriale | F44: 35.7 | G44: EUR | H44: 35.7 | I44: 3751.9 | J44: 3751.9 | K44: 2 | L44: 2.38908 | M44: =IF(OR(F44="",K44="",K44<=0),"",F44/K44) | N44: 1.7415483 | O44: =IF(OR(N44="",M44="",M44<=0),"",N44/M44) | P44: 0.10251001 | Q44: 0.13417074 | R44: 0.029235474 | S44: 4 | U44: 0.099171451 | V44: 0.11305339 | W44: 0.15291724 | X44: 0.17154089 | Y44: 0.35 | Z44: =IF(OR(Y44="",F44="",F44=0),"",Y44/F44) | AA44: 31.196 | AB44: 0.011 | AC44: 0.10264096 | AD44: =IF(OR(Q44="",M44="",M44<=0),"",ROUND(40*MAX(0,MIN(N(Q44)/0.3,1))+IF(OR(R44="",N(Q44)<=0),10,20*MAX(0,1-MIN(R44/Q44,1)))+30*MAX(0,MIN((PARAMETRI!$B$5-M44)/MAX(PARAMETRI!$B$5-10,1),1))+IF(AB44="",3,10*MAX(0,MIN(AB44/0.15,1)))+IF(AND(P44<>"",N(P44)<N(Q44)*0.6),-8,0),1)) | AE44: =IF(AND(P44="",Q44=""),"DATI MANCANTI",IF(AND(N(P44)>=PARAMETRI!$B$4,N(Q44)>=PARAMETRI!$B$4),"OK","NO")) | AF44: =IF(M44="","N/D",IF(M44<PARAMETRI!$B$6,"OTTIMO",IF(M44<PARAMETRI!$B$5,"OK","NO"))) | AG44: =IF(OR(AE44="DATI MANCANTI",AF44="N/D"),"DA COMPLETARE",IF(AND(AE44="OK",AF44="OTTIMO"),"PASSA FORTE",IF(AND(AE44="OK",AF44="OK"),"PASSA","SCARTA"))) | AH44: 2026-10-12 | AI44: yahoo
A45: =IF(AD45="","",RANK(AD45,AD$2:AD$67)) | B45: BB Biotech | C45: BION.SW | D45: Veicolo biotech | E45: Veicolo | F45: 49.5 | G45: CHF | H45: 53.150367 | I45: 2931.2159 | J45: 2729.9 | K45: 24.55 | L45: -0.65777 | M45: =IF(OR(F45="",K45="",K45<=0),"",F45/K45) | N45: 0.88503486 | O45: =IF(OR(N45="",M45="",M45<=0),"",N45/M45) | P45: 0.54764 | Q45: 0.0047778577 | R45: 0.13223982 | S45: 4 | U45: 0.20805244 | V45: 0.033197422 | W45: -0.088931426 | X45: -0.13320701 | Y45: 2.25 | Z45: =IF(OR(Y45="",F45="",F45=0),"",Y45/F45) | AB45: 1162.577 | AC45: 2.2982606 | AD45: =IF(OR(Q45="",M45="",M45<=0),"",ROUND(40*MAX(0,MIN(N(Q45)/0.3,1))+IF(OR(R45="",N(Q45)<=0),10,20*MAX(0,1-MIN(R45/Q45,1)))+30*MAX(0,MIN((PARAMETRI!$B$5-M45)/MAX(PARAMETRI!$B$5-10,1),1))+IF(AB45="",3,10*MAX(0,MIN(AB45/0.15,1)))+IF(AND(P45<>"",N(P45)<N(Q45)*0.6),-8,0),1)) | AE45: =IF(AND(P45="",Q45=""),"DATI MANCANTI",IF(AND(N(P45)>=PARAMETRI!$B$4,N(Q45)>=PARAMETRI!$B$4),"OK","NO")) | AF45: =IF(M45="","N/D",IF(M45<PARAMETRI!$B$6,"OTTIMO",IF(M45<PARAMETRI!$B$5,"OK","NO"))) | AG45: =IF(OR(AE45="DATI MANCANTI",AF45="N/D"),"DA COMPLETARE",IF(AND(AE45="OK",AF45="OTTIMO"),"PASSA FORTE",IF(AND(AE45="OK",AF45="OK"),"PASSA","SCARTA"))) | AH45: 2026-10-12 | AI45: yahoo | AJ45: Quotata Zurigo/Xetra, NAV-driven: ROE poco significativo
A46: =IF(AD46="","",RANK(AD46,AD$2:AD$67)) | B46: Enel | C46: ENEL.MI | D46: Utility | E46: Utility | F46: 8.918 | G46: EUR | H46: 8.918 | I46: 88472.5 | J46: 88472.5 | K46: 0.42 | L46: 0.75591 | M46: =IF(OR(F46="",K46="",K46<=0),"",F46/K46) | N46: 3.5844054 | O46: =IF(OR(N46="",M46="",M46<=0),"",N46/M46) | P46: 0.12255999 | Q46: 0.12667864 | R46: 0.053849326 | S46: 4 | U46: 0.13175128 | V46: 0.20799858 | W46: 0.10826641 | X46: 0.058698307 | Y46: 0.52 | Z46: =IF(OR(Y46="",F46="",F46=0),"",Y46/F46) | AA46: 147.743 | AB46: 0.085 | AC46: 0.063096721 | AD46: =IF(OR(Q46="",M46="",M46<=0),"",ROUND(40*MAX(0,MIN(N(Q46)/0.3,1))+IF(OR(R46="",N(Q46)<=0),10,20*MAX(0,1-MIN(R46/Q46,1)))+30*MAX(0,MIN((PARAMETRI!$B$5-M46)/MAX(PARAMETRI!$B$5-10,1),1))+IF(AB46="",3,10*MAX(0,MIN(AB46/0.15,1)))+IF(AND(P46<>"",N(P46)<N(Q46)*0.6),-8,0),1)) | AE46: =IF(AND(P46="",Q46=""),"DATI MANCANTI",IF(AND(N(P46)>=PARAMETRI!$B$4,N(Q46)>=PARAMETRI!$B$4),"OK","NO")) | AF46: =IF(M46="","N/D",IF(M46<PARAMETRI!$B$6,"OTTIMO",IF(M46<PARAMETRI!$B$5,"OK","NO"))) | AG46: =IF(OR(AE46="DATI MANCANTI",AF46="N/D"),"DA COMPLETARE",IF(AND(AE46="OK",AF46="OTTIMO"),"PASSA FORTE",IF(AND(AE46="OK",AF46="OK"),"PASSA","SCARTA"))) | AH46: 2026-10-12 | AI46: yahoo
A47: =IF(AD47="","",RANK(AD47,AD$2:AD$67)) | B47: DiaSorin | C47: DIA.MI | D47: Diagnostica | E47: Salute | F47: 77.8 | G47: EUR | H47: 77.8 | I47: 3832.8 | J47: 3832.8 | K47: 2.72 | L47: 4.3364 | M47: =IF(OR(F47="",K47="",K47<=0),"",F47/K47) | N47: 2.7053344 | O47: =IF(OR(N47="",M47="",M47<=0),"",N47/M47) | P47: 0.091630004 | Q47: 0.11628878 | R47: 0.024548051 | S47: 4 | U47: 0.098216906 | V47: 0.10444951 | W47: 0.10389176 | X47: 0.15859694 | Y47: 1.3 | Z47: =IF(OR(Y47="",F47="",F47=0),"",Y47/F47) | AA47: 68.183 | AB47: 0.027 | AC47: 0.11762806 | AD47: =IF(OR(Q47="",M47="",M47<=0),"",ROUND(40*MAX(0,MIN(N(Q47)/0.3,1))+IF(OR(R47="",N(Q47)<=0),10,20*MAX(0,1-MIN(R47/Q47,1)))+30*MAX(0,MIN((PARAMETRI!$B$5-M47)/MAX(PARAMETRI!$B$5-10,1),1))+IF(AB47="",3,10*MAX(0,MIN(AB47/0.15,1)))+IF(AND(P47<>"",N(P47)<N(Q47)*0.6),-8,0),1)) | AE47: =IF(AND(P47="",Q47=""),"DATI MANCANTI",IF(AND(N(P47)>=PARAMETRI!$B$4,N(Q47)>=PARAMETRI!$B$4),"OK","NO")) | AF47: =IF(M47="","N/D",IF(M47<PARAMETRI!$B$6,"OTTIMO",IF(M47<PARAMETRI!$B$5,"OK","NO"))) | AG47: =IF(OR(AE47="DATI MANCANTI",AF47="N/D"),"DA COMPLETARE",IF(AND(AE47="OK",AF47="OTTIMO"),"PASSA FORTE",IF(AND(AE47="OK",AF47="OK"),"PASSA","SCARTA"))) | AH47: 2026-10-12 | AI47: yahoo
A48: =IF(AD48="","",RANK(AD48,AD$2:AD$67)) | B48: CNH Industrial | C48: CNH | D48: Industria pesante | E48: Industriale | F48: 11.645 | G48: USD | H48: 10.431591 | I48: 16775.647 | J48: 18727 | K48: 0.25 | L48: 0.68691 | M48: =IF(OR(F48="",K48="",K48<=0),"",F48/K48) | N48: 1.8584425 | O48: =IF(OR(N48="",M48="",M48<=0),"",N48/M48) | P48: 0.03914 | Q48: 0.2012639 | R48: 0.093420052 | S48: 4 | U48: 0.065976714 | V48: 0.16285453 | W48: 0.28331258 | X48: 0.29291179 | Y48: 0.1 | Z48: =IF(OR(Y48="",F48="",F48=0),"",Y48/F48) | AA48: 335.044 | AB48: 0.02 | AC48: 0.017187068 | AD48: =IF(OR(Q48="",M48="",M48<=0),"",ROUND(40*MAX(0,MIN(N(Q48)/0.3,1))+IF(OR(R48="",N(Q48)<=0),10,20*MAX(0,1-MIN(R48/Q48,1)))+30*MAX(0,MIN((PARAMETRI!$B$5-M48)/MAX(PARAMETRI!$B$5-10,1),1))+IF(AB48="",3,10*MAX(0,MIN(AB48/0.15,1)))+IF(AND(P48<>"",N(P48)<N(Q48)*0.6),-8,0),1)) | AE48: =IF(AND(P48="",Q48=""),"DATI MANCANTI",IF(AND(N(P48)>=PARAMETRI!$B$4,N(Q48)>=PARAMETRI!$B$4),"OK","NO")) | AF48: =IF(M48="","N/D",IF(M48<PARAMETRI!$B$6,"OTTIMO",IF(M48<PARAMETRI!$B$5,"OK","NO"))) | AG48: =IF(OR(AE48="DATI MANCANTI",AF48="N/D"),"DA COMPLETARE",IF(AND(AE48="OK",AF48="OTTIMO"),"PASSA FORTE",IF(AND(AE48="OK",AF48="OK"),"PASSA","SCARTA"))) | AH48: 2026-10-12 | AI48: yahoo | AJ48: Delistata da Milano (gen-2024), quota solo NYSE in USD
A49: =IF(AD49="","",RANK(AD49,AD$2:AD$67)) | B49: Eni | C49: ENI.MI | D49: Energia | E49: Energia | F49: 25.405 | G49: EUR | H49: 25.405 | I49: 72756.8 | J49: 72756.8 | K49: 1.23 | L49: 2.62823 | M49: =IF(OR(F49="",K49="",K49<=0),"",F49/K49) | N49: 1.6095413 | O49: =IF(OR(N49="",M49="",M49<=0),"",N49/M49) | P49: 0.10901 | Q49: 0.1118555 | R49: 0.083284989 | S49: 4 | U49: 0.054401335 | V49: 0.049711092 | W49: 0.089707431 | X49: 0.25360215 | Y49: 1.08 | Z49: =IF(OR(Y49="",F49="",F49=0),"",Y49/F49) | AA49: 64.975 | AB49: 0.185 | AC49: 0.070419106 | AD49: =IF(OR(Q49="",M49="",M49<=0),"",ROUND(40*MAX(0,MIN(N(Q49)/0.3,1))+IF(OR(R49="",N(Q49)<=0),10,20*MAX(0,1-MIN(R49/Q49,1)))+30*MAX(0,MIN((PARAMETRI!$B$5-M49)/MAX(PARAMETRI!$B$5-10,1),1))+IF(AB49="",3,10*MAX(0,MIN(AB49/0.15,1)))+IF(AND(P49<>"",N(P49)<N(Q49)*0.6),-8,0),1)) | AE49: =IF(AND(P49="",Q49=""),"DATI MANCANTI",IF(AND(N(P49)>=PARAMETRI!$B$4,N(Q49)>=PARAMETRI!$B$4),"OK","NO")) | AF49: =IF(M49="","N/D",IF(M49<PARAMETRI!$B$6,"OTTIMO",IF(M49<PARAMETRI!$B$5,"OK","NO"))) | AG49: =IF(OR(AE49="DATI MANCANTI",AF49="N/D"),"DA COMPLETARE",IF(AND(AE49="OK",AF49="OTTIMO"),"PASSA FORTE",IF(AND(AE49="OK",AF49="OK"),"PASSA","SCARTA"))) | AH49: 2026-10-12 | AI49: yahoo
A50: =IF(AD50="","",RANK(AD50,AD$2:AD$67)) | B50: INWIT | C50: INW.MI | D50: Torri / Infrastrutture | E50: Industriale | F50: 7.15 | G50: EUR | H50: 7.15 | I50: 6452.8 | J50: 6452.8 | K50: 0.37 | L50: 0.35595 | M50: =IF(OR(F50="",K50="",K50<=0),"",F50/K50) | N50: 2.1254458 | O50: =IF(OR(N50="",M50="",M50<=0),"",N50/M50) | P50: 0.098620005 | Q50: 0.083757189 | R50: 0.0140155 | S50: 4 | U50: 0.1042395 | V50: 0.086823011 | W50: 0.078290074 | X50: 0.06567617 | Y50: 0.55 | Z50: =IF(OR(Y50="",F50="",F50=0),"",Y50/F50) | AA50: 176.713 | AB50: -0.008 | AC50: 0.31333511 | AD50: =IF(OR(Q50="",M50="",M50<=0),"",ROUND(40*MAX(0,MIN(N(Q50)/0.3,1))+IF(OR(R50="",N(Q50)<=0),10,20*MAX(0,1-MIN(R50/Q50,1)))+30*MAX(0,MIN((PARAMETRI!$B$5-M50)/MAX(PARAMETRI!$B$5-10,1),1))+IF(AB50="",3,10*MAX(0,MIN(AB50/0.15,1)))+IF(AND(P50<>"",N(P50)<N(Q50)*0.6),-8,0),1)) | AE50: =IF(AND(P50="",Q50=""),"DATI MANCANTI",IF(AND(N(P50)>=PARAMETRI!$B$4,N(Q50)>=PARAMETRI!$B$4),"OK","NO")) | AF50: =IF(M50="","N/D",IF(M50<PARAMETRI!$B$6,"OTTIMO",IF(M50<PARAMETRI!$B$5,"OK","NO"))) | AG50: =IF(OR(AE50="DATI MANCANTI",AF50="N/D"),"DA COMPLETARE",IF(AND(AE50="OK",AF50="OTTIMO"),"PASSA FORTE",IF(AND(AE50="OK",AF50="OK"),"PASSA","SCARTA"))) | AH50: 2026-10-12 | AI50: yahoo
A51: =IF(AD51="","",RANK(AD51,AD$2:AD$67)) | B51: STMicroelectronics | C51: STMMI.MI | D51: Semiconduttori | E51: Tecnologia | F51: 45.575 | G51: EUR | H51: 45.575 | I51: 40821.5 | J51: 40821.5 | K51: 0.03 | L51: 1.42 | M51: =IF(OR(F51="",K51="",K51<=0),"",F51/K51) | N51: 2.6806207 | O51: =IF(OR(N51="",M51="",M51<=0),"",N51/M51) | P51: 0.02686 | Q51: 0.16556106 | R51: 0.12155526 | S51: 4 | U51: 0.0093111959 | V51: 0.089231475 | W51: 0.25171857 | X51: 0.31198298 | Y51: 0.32 | Z51: =IF(OR(Y51="",F51="",F51=0),"",Y51/F51) | AA51: 23.446 | AB51: 0.261 | AC51: 0.039491525 | AD51: =IF(OR(Q51="",M51="",M51<=0),"",ROUND(40*MAX(0,MIN(N(Q51)/0.3,1))+IF(OR(R51="",N(Q51)<=0),10,20*MAX(0,1-MIN(R51/Q51,1)))+30*MAX(0,MIN((PARAMETRI!$B$5-M51)/MAX(PARAMETRI!$B$5-10,1),1))+IF(AB51="",3,10*MAX(0,MIN(AB51/0.15,1)))+IF(AND(P51<>"",N(P51)<N(Q51)*0.6),-8,0),1)) | AE51: =IF(AND(P51="",Q51=""),"DATI MANCANTI",IF(AND(N(P51)>=PARAMETRI!$B$4,N(Q51)>=PARAMETRI!$B$4),"OK","NO")) | AF51: =IF(M51="","N/D",IF(M51<PARAMETRI!$B$6,"OTTIMO",IF(M51<PARAMETRI!$B$5,"OK","NO"))) | AG51: =IF(OR(AE51="DATI MANCANTI",AF51="N/D"),"DA COMPLETARE",IF(AND(AE51="OK",AF51="OTTIMO"),"PASSA FORTE",IF(AND(AE51="OK",AF51="OK"),"PASSA","SCARTA"))) | AH51: 2026-10-12 | AI51: yahoo | AJ51: Bilancio in USD
A52: =IF(AD52="","",RANK(AD52,AD$2:AD$67)) | B52: Amplifon | C52: AMP.MI | D52: Dispositivi medicali | E52: Salute | F52: 12.65 | G52: EUR | H52: 12.65 | I52: 3361.7 | J52: 3361.7 | K52: 0.31 | L52: 0.87932 | M52: =IF(OR(F52="",K52="",K52<=0),"",F52/K52) | N52: 2.2208567 | O52: =IF(OR(N52="",M52="",M52<=0),"",N52/M52) | P52: 0.05737 | Q52: 0.13268305 | R52: 0.028903991 | S52: 4 | U52: 0.091497414 | V52: 0.12641195 | W52: 0.14091772 | X52: 0.17190511 | Y52: 0.29 | Z52: =IF(OR(Y52="",F52="",F52=0),"",Y52/F52) | AA52: 117.681 | AB52: 0.022 | AC52: 0.030173999 | AD52: =IF(OR(Q52="",M52="",M52<=0),"",ROUND(40*MAX(0,MIN(N(Q52)/0.3,1))+IF(OR(R52="",N(Q52)<=0),10,20*MAX(0,1-MIN(R52/Q52,1)))+30*MAX(0,MIN((PARAMETRI!$B$5-M52)/MAX(PARAMETRI!$B$5-10,1),1))+IF(AB52="",3,10*MAX(0,MIN(AB52/0.15,1)))+IF(AND(P52<>"",N(P52)<N(Q52)*0.6),-8,0),1)) | AE52: =IF(AND(P52="",Q52=""),"DATI MANCANTI",IF(AND(N(P52)>=PARAMETRI!$B$4,N(Q52)>=PARAMETRI!$B$4),"OK","NO")) | AF52: =IF(M52="","N/D",IF(M52<PARAMETRI!$B$6,"OTTIMO",IF(M52<PARAMETRI!$B$5,"OK","NO"))) | AG52: =IF(OR(AE52="DATI MANCANTI",AF52="N/D"),"DA COMPLETARE",IF(AND(AE52="OK",AF52="OTTIMO"),"PASSA FORTE",IF(AND(AE52="OK",AF52="OK"),"PASSA","SCARTA"))) | AH52: 2026-10-12 | AI52: yahoo
A53: =IF(AD53="","",RANK(AD53,AD$2:AD$67)) | B53: Davide Campari-Milano | C53: CPR.MI | D53: Bevande | E53: Consumi | F53: 6.274 | G53: EUR | H53: 6.274 | I53: 7524.8 | J53: 7524.8 | K53: 0.15 | L53: 0.35152 | M53: =IF(OR(F53="",K53="",K53<=0),"",F53/K53) | N53: 1.8852164 | O53: =IF(OR(N53="",M53="",M53<=0),"",N53/M53) | P53: 0.06676 | Q53: 0.094843293 | R53: 0.027570682 | S53: 4 | U53: 0.089649995 | V53: 0.052309289 | W53: 0.11298373 | X53: 0.12443016 | Y53: 0.1 | Z53: =IF(OR(Y53="",F53="",F53=0),"",Y53/F53) | AA53: 70.273 | AB53: -0.01 | AC53: 0.088263249 | AD53: =IF(OR(Q53="",M53="",M53<=0),"",ROUND(40*MAX(0,MIN(N(Q53)/0.3,1))+IF(OR(R53="",N(Q53)<=0),10,20*MAX(0,1-MIN(R53/Q53,1)))+30*MAX(0,MIN((PARAMETRI!$B$5-M53)/MAX(PARAMETRI!$B$5-10,1),1))+IF(AB53="",3,10*MAX(0,MIN(AB53/0.15,1)))+IF(AND(P53<>"",N(P53)<N(Q53)*0.6),-8,0),1)) | AE53: =IF(AND(P53="",Q53=""),"DATI MANCANTI",IF(AND(N(P53)>=PARAMETRI!$B$4,N(Q53)>=PARAMETRI!$B$4),"OK","NO")) | AF53: =IF(M53="","N/D",IF(M53<PARAMETRI!$B$6,"OTTIMO",IF(M53<PARAMETRI!$B$5,"OK","NO"))) | AG53: =IF(OR(AE53="DATI MANCANTI",AF53="N/D"),"DA COMPLETARE",IF(AND(AE53="OK",AF53="OTTIMO"),"PASSA FORTE",IF(AND(AE53="OK",AF53="OK"),"PASSA","SCARTA"))) | AH53: 2026-10-12 | AI53: yahoo
A54: =IF(AD54="","",RANK(AD54,AD$2:AD$67)) | B54: Iveco Group | C54: IVG.MI | D54: Veicoli industriali | E54: Industriale | F54: 14.335 | G54: EUR | H54: 14.335 | I54: 3818.1 | J54: 3818.1 | K54: 0.23 | L54: 2.04691 | M54: =IF(OR(F54="",K54="",K54<=0),"",F54/K54) | N54: 1.5470538 | O54: =IF(OR(N54="",M54="",M54<=0),"",N54/M54) | P54: 0.02429 | Q54: 0.09726813 | R54: 0.024063013 | S54: 4 | U54: 0.10471014 | V54: 0.12930715 | W54: 0.092608326 | X54: 0.062446899 | Y54: 0.33 | Z54: =IF(OR(Y54="",F54="",F54=0),"",Y54/F54) | AA54: 233.426 | AB54: 0.073 | AC54: 0.004691689 | AD54: =IF(OR(Q54="",M54="",M54<=0),"",ROUND(40*MAX(0,MIN(N(Q54)/0.3,1))+IF(OR(R54="",N(Q54)<=0),10,20*MAX(0,1-MIN(R54/Q54,1)))+30*MAX(0,MIN((PARAMETRI!$B$5-M54)/MAX(PARAMETRI!$B$5-10,1),1))+IF(AB54="",3,10*MAX(0,MIN(AB54/0.15,1)))+IF(AND(P54<>"",N(P54)<N(Q54)*0.6),-8,0),1)) | AE54: =IF(AND(P54="",Q54=""),"DATI MANCANTI",IF(AND(N(P54)>=PARAMETRI!$B$4,N(Q54)>=PARAMETRI!$B$4),"OK","NO")) | AF54: =IF(M54="","N/D",IF(M54<PARAMETRI!$B$6,"OTTIMO",IF(M54<PARAMETRI!$B$5,"OK","NO"))) | AG54: =IF(OR(AE54="DATI MANCANTI",AF54="N/D"),"DA COMPLETARE",IF(AND(AE54="OK",AF54="OTTIMO"),"PASSA FORTE",IF(AND(AE54="OK",AF54="OK"),"PASSA","SCARTA"))) | AH54: 2026-10-12 | AI54: yahoo
A55: =IF(AD55="","",RANK(AD55,AD$2:AD$67)) | B55: ERG | C55: ERG.MI | D55: Utility / Rinnovabili | E55: Utility | F55: 22.2 | G55: EUR | H55: 22.2 | I55: 3226.9 | J55: 3226.9 | K55: 0.55 | L55: 1.16663 | M55: =IF(OR(F55="",K55="",K55<=0),"",F55/K55) | N55: 1.7078238 | O55: =IF(OR(N55="",M55="",M55<=0),"",N55/M55) | P55: 0.04065 | Q55: 0.097247413 | R55: 0.055191341 | S55: 4 | U55: 0.032804395 | V55: 0.087154305 | W55: 0.083762417 | X55: 0.18526854 | Y55: 1 | Z55: =IF(OR(Y55="",F55="",F55=0),"",Y55/F55) | AA55: 137.035 | AC55: 0.10464017 | AD55: =IF(OR(Q55="",M55="",M55<=0),"",ROUND(40*MAX(0,MIN(N(Q55)/0.3,1))+IF(OR(R55="",N(Q55)<=0),10,20*MAX(0,1-MIN(R55/Q55,1)))+30*MAX(0,MIN((PARAMETRI!$B$5-M55)/MAX(PARAMETRI!$B$5-10,1),1))+IF(AB55="",3,10*MAX(0,MIN(AB55/0.15,1)))+IF(AND(P55<>"",N(P55)<N(Q55)*0.6),-8,0),1)) | AE55: =IF(AND(P55="",Q55=""),"DATI MANCANTI",IF(AND(N(P55)>=PARAMETRI!$B$4,N(Q55)>=PARAMETRI!$B$4),"OK","NO")) | AF55: =IF(M55="","N/D",IF(M55<PARAMETRI!$B$6,"OTTIMO",IF(M55<PARAMETRI!$B$5,"OK","NO"))) | AG55: =IF(OR(AE55="DATI MANCANTI",AF55="N/D"),"DA COMPLETARE",IF(AND(AE55="OK",AF55="OTTIMO"),"PASSA FORTE",IF(AND(AE55="OK",AF55="OK"),"PASSA","SCARTA"))) | AH55: 2026-10-12 | AI55: yahoo
A56: =IF(AD56="","",RANK(AD56,AD$2:AD$67)) | B56: Esprinet | C56: PRT.MI | D56: Distribuzione IT | E56: Tecnologia | F56: 7.925 | G56: EUR | H56: 7.925 | I56: 391.8 | J56: 391.8 | K56: 0.44 | L56: 0.63139 | M56: =IF(OR(F56="",K56="",K56<=0),"",F56/K56) | N56: 1.0397533 | O56: =IF(OR(N56="",M56="",M56<=0),"",N56/M56) | P56: 0.05738 | Q56: 0.047615749 | R56: 0.05268192 | S56: 4 | U56: 0.051796031 | V56: 0.055288801 | W56: -0.03232084 | X56: 0.11569901 | Y56: 0.35 | Z56: =IF(OR(Y56="",F56="",F56=0),"",Y56/F56) | AA56: 118.59 | AB56: 0.057 | AC56: 0.0050139211 | AD56: =IF(OR(Q56="",M56="",M56<=0),"",ROUND(40*MAX(0,MIN(N(Q56)/0.3,1))+IF(OR(R56="",N(Q56)<=0),10,20*MAX(0,1-MIN(R56/Q56,1)))+30*MAX(0,MIN((PARAMETRI!$B$5-M56)/MAX(PARAMETRI!$B$5-10,1),1))+IF(AB56="",3,10*MAX(0,MIN(AB56/0.15,1)))+IF(AND(P56<>"",N(P56)<N(Q56)*0.6),-8,0),1)) | AE56: =IF(AND(P56="",Q56=""),"DATI MANCANTI",IF(AND(N(P56)>=PARAMETRI!$B$4,N(Q56)>=PARAMETRI!$B$4),"OK","NO")) | AF56: =IF(M56="","N/D",IF(M56<PARAMETRI!$B$6,"OTTIMO",IF(M56<PARAMETRI!$B$5,"OK","NO"))) | AG56: =IF(OR(AE56="DATI MANCANTI",AF56="N/D"),"DA COMPLETARE",IF(AND(AE56="OK",AF56="OTTIMO"),"PASSA FORTE",IF(AND(AE56="OK",AF56="OK"),"PASSA","SCARTA"))) | AH56: 2026-10-12 | AI56: yahoo
A57: =IF(AD57="","",RANK(AD57,AD$2:AD$67)) | B57: Telecom Italia ord. | C57: TIT.MI | D57: Telecomunicazioni | E57: Industriale | F57: 5.486 | G57: EUR | H57: 5.486 | I57: 11703.1 | J57: 11703.1 | K57: 0.21 | L57: 0.28418 | M57: =IF(OR(F57="",K57="",K57<=0),"",F57/K57) | N57: 1.0123639 | O57: =IF(OR(N57="",M57="",M57<=0),"",N57/M57) | P57: 0.03897 | Q57: -0.081629664 | R57: 0.079700273 | S57: 4 | U57: 0.024306408 | V57: -0.051016141 | W57: -0.10559871 | X57: -0.19421021 | Z57: =IF(OR(Y57="",F57="",F57=0),"",Y57/F57) | AA57: 104.611 | AB57: 0.064 | AC57: 0.020678608 | AD57: =IF(OR(Q57="",M57="",M57<=0),"",ROUND(40*MAX(0,MIN(N(Q57)/0.3,1))+IF(OR(R57="",N(Q57)<=0),10,20*MAX(0,1-MIN(R57/Q57,1)))+30*MAX(0,MIN((PARAMETRI!$B$5-M57)/MAX(PARAMETRI!$B$5-10,1),1))+IF(AB57="",3,10*MAX(0,MIN(AB57/0.15,1)))+IF(AND(P57<>"",N(P57)<N(Q57)*0.6),-8,0),1)) | AE57: =IF(AND(P57="",Q57=""),"DATI MANCANTI",IF(AND(N(P57)>=PARAMETRI!$B$4,N(Q57)>=PARAMETRI!$B$4),"OK","NO")) | AF57: =IF(M57="","N/D",IF(M57<PARAMETRI!$B$6,"OTTIMO",IF(M57<PARAMETRI!$B$5,"OK","NO"))) | AG57: =IF(OR(AE57="DATI MANCANTI",AF57="N/D"),"DA COMPLETARE",IF(AND(AE57="OK",AF57="OTTIMO"),"PASSA FORTE",IF(AND(AE57="OK",AF57="OK"),"PASSA","SCARTA"))) | AH57: 2026-10-12 | AI57: yahoo
A58: =IF(AD58="","",RANK(AD58,AD$2:AD$67)) | B58: Fincantieri | C58: FCT.MI | D58: Cantieristica | E58: Industriale | F58: 12.57 | G58: EUR | H58: 12.57 | I58: 4760.4 | J58: 4760.4 | K58: 0.53 | L58: 0.82133 | M58: =IF(OR(F58="",K58="",K58<=0),"",F58/K58) | N58: 2.7883763 | O58: =IF(OR(N58="",M58="",M58<=0),"",N58/M58) | P58: 0.14936 | Q58: -0.12188113 | R58: 0.25022912 | S58: 4 | U58: 0.12333595 | V58: 0.038651477 | W58: -0.12197543 | X58: -0.52753653 | Z58: =IF(OR(Y58="",F58="",F58=0),"",Y58/F58) | AA58: 157.274 | AB58: -0.027 | AC58: 0.021393501 | AD58: =IF(OR(Q58="",M58="",M58<=0),"",ROUND(40*MAX(0,MIN(N(Q58)/0.3,1))+IF(OR(R58="",N(Q58)<=0),10,20*MAX(0,1-MIN(R58/Q58,1)))+30*MAX(0,MIN((PARAMETRI!$B$5-M58)/MAX(PARAMETRI!$B$5-10,1),1))+IF(AB58="",3,10*MAX(0,MIN(AB58/0.15,1)))+IF(AND(P58<>"",N(P58)<N(Q58)*0.6),-8,0),1)) | AE58: =IF(AND(P58="",Q58=""),"DATI MANCANTI",IF(AND(N(P58)>=PARAMETRI!$B$4,N(Q58)>=PARAMETRI!$B$4),"OK","NO")) | AF58: =IF(M58="","N/D",IF(M58<PARAMETRI!$B$6,"OTTIMO",IF(M58<PARAMETRI!$B$5,"OK","NO"))) | AG58: =IF(OR(AE58="DATI MANCANTI",AF58="N/D"),"DA COMPLETARE",IF(AND(AE58="OK",AF58="OTTIMO"),"PASSA FORTE",IF(AND(AE58="OK",AF58="OK"),"PASSA","SCARTA"))) | AH58: 2026-10-12 | AI58: yahoo | AJ58: Prezzo storico pre-raggruppamento 2025
A59: =IF(AD59="","",RANK(AD59,AD$2:AD$67)) | B59: Salvatore Ferragamo | C59: SFER.MI | D59: Lusso | E59: Consumi | F59: 6.85 | G59: EUR | H59: 6.85 | I59: 1128.1 | J59: 1128.1 | K59: 0.06 | L59: 0.17709 | M59: =IF(OR(F59="",K59="",K59<=0),"",F59/K59) | N59: 1.9361221 | O59: =IF(OR(N59="",M59="",M59<=0),"",N59/M59) | P59: 0.01652 | Q59: -0.016213977 | R59: 0.083533593 | S59: 4 | U59: -0.0836014 | V59: -0.10997899 | W59: 0.036135924 | X59: 0.092588553 | Z59: =IF(OR(Y59="",F59="",F59=0),"",Y59/F59) | AA59: 111.111 | AB59: -0.013 | AC59: 0.0099300483 | AD59: =IF(OR(Q59="",M59="",M59<=0),"",ROUND(40*MAX(0,MIN(N(Q59)/0.3,1))+IF(OR(R59="",N(Q59)<=0),10,20*MAX(0,1-MIN(R59/Q59,1)))+30*MAX(0,MIN((PARAMETRI!$B$5-M59)/MAX(PARAMETRI!$B$5-10,1),1))+IF(AB59="",3,10*MAX(0,MIN(AB59/0.15,1)))+IF(AND(P59<>"",N(P59)<N(Q59)*0.6),-8,0),1)) | AE59: =IF(AND(P59="",Q59=""),"DATI MANCANTI",IF(AND(N(P59)>=PARAMETRI!$B$4,N(Q59)>=PARAMETRI!$B$4),"OK","NO")) | AF59: =IF(M59="","N/D",IF(M59<PARAMETRI!$B$6,"OTTIMO",IF(M59<PARAMETRI!$B$5,"OK","NO"))) | AG59: =IF(OR(AE59="DATI MANCANTI",AF59="N/D"),"DA COMPLETARE",IF(AND(AE59="OK",AF59="OTTIMO"),"PASSA FORTE",IF(AND(AE59="OK",AF59="OK"),"PASSA","SCARTA"))) | AH59: 2026-10-12 | AI59: yahoo
A60: =IF(AD60="","",RANK(AD60,AD$2:AD$67)) | B60: Saipem | C60: SPM.MI | D60: Oil service | E60: Energia | F60: 4.647 | G60: EUR | H60: 4.647 | I60: 9016.5 | J60: 9016.5 | K60: 0.13 | L60: 0.3006 | M60: =IF(OR(F60="",K60="",K60<=0),"",F60/K60) | N60: 3.8984897 | O60: =IF(OR(N60="",M60="",M60<=0),"",N60/M60) | P60: 0.10850999 | Q60: 0.053125098 | R60: 0.090875504 | S60: 4 | U60: 0.11755783 | V60: 0.12123613 | W60: 0.074770259 | X60: -0.10106383 | Y60: 0.17 | Z60: =IF(OR(Y60="",F60="",F60=0),"",Y60/F60) | AA60: 128.967 | AB60: 0.035 | AC60: 0.017221362 | AD60: =IF(OR(Q60="",M60="",M60<=0),"",ROUND(40*MAX(0,MIN(N(Q60)/0.3,1))+IF(OR(R60="",N(Q60)<=0),10,20*MAX(0,1-MIN(R60/Q60,1)))+30*MAX(0,MIN((PARAMETRI!$B$5-M60)/MAX(PARAMETRI!$B$5-10,1),1))+IF(AB60="",3,10*MAX(0,MIN(AB60/0.15,1)))+IF(AND(P60<>"",N(P60)<N(Q60)*0.6),-8,0),1)) | AE60: =IF(AND(P60="",Q60=""),"DATI MANCANTI",IF(AND(N(P60)>=PARAMETRI!$B$4,N(Q60)>=PARAMETRI!$B$4),"OK","NO")) | AF60: =IF(M60="","N/D",IF(M60<PARAMETRI!$B$6,"OTTIMO",IF(M60<PARAMETRI!$B$5,"OK","NO"))) | AG60: =IF(OR(AE60="DATI MANCANTI",AF60="N/D"),"DA COMPLETARE",IF(AND(AE60="OK",AF60="OTTIMO"),"PASSA FORTE",IF(AND(AE60="OK",AF60="OK"),"PASSA","SCARTA"))) | AH60: 2026-10-12 | AI60: yahoo
A61: =IF(AD61="","",RANK(AD61,AD$2:AD$67)) | B61: Exor | C61: EXO.AS | D61: Holding | E61: Finanziario | F61: 69.5 | G61: EUR | H61: 69.5 | I61: 22878 | J61: 22878 | K61: -21.02 | L61: 1.19258 | M61: =IF(OR(F61="",K61="",K61<=0),"",F61/K61) | N61: 0.44019103 | O61: =IF(OR(N61="",M61="",M61<=0),"",N61/M61) | P61: -0.12553 | Q61: 0.16375101 | R61: 0.17864343 | S61: 4 | U61: -0.11410607 | V61: 0.38393698 | W61: 0.18024755 | X61: 0.20492558 | Y61: 0.49 | Z61: =IF(OR(Y61="",F61="",F61=0),"",Y61/F61) | AA61: 11.531 | AC61: 1.1949318 | AD61: =IF(OR(Q61="",M61="",M61<=0),"",ROUND(40*MAX(0,MIN(N(Q61)/0.3,1))+IF(OR(R61="",N(Q61)<=0),10,20*MAX(0,1-MIN(R61/Q61,1)))+30*MAX(0,MIN((PARAMETRI!$B$5-M61)/MAX(PARAMETRI!$B$5-10,1),1))+IF(AB61="",3,10*MAX(0,MIN(AB61/0.15,1)))+IF(AND(P61<>"",N(P61)<N(Q61)*0.6),-8,0),1)) | AE61: =IF(AND(P61="",Q61=""),"DATI MANCANTI",IF(AND(N(P61)>=PARAMETRI!$B$4,N(Q61)>=PARAMETRI!$B$4),"OK","NO")) | AF61: =IF(M61="","N/D",IF(M61<PARAMETRI!$B$6,"OTTIMO",IF(M61<PARAMETRI!$B$5,"OK","NO"))) | AG61: =IF(OR(AE61="DATI MANCANTI",AF61="N/D"),"DA COMPLETARE",IF(AND(AE61="OK",AF61="OTTIMO"),"PASSA FORTE",IF(AND(AE61="OK",AF61="OK"),"PASSA","SCARTA"))) | AH61: 2026-10-12 | AI61: yahoo | AJ61: Quotata ad Amsterdam
A62: =IF(AD62="","",RANK(AD62,AD$2:AD$67)) | B62: Forvia (ex Faurecia) | C62: FRVIA.PA | D62: Componentistica auto | E62: Industriale | F62: 8.55 | G62: EUR | H62: 8.55 | I62: 1573.7 | J62: 1573.7 | K62: -6.23 | L62: 2.305 | M62: =IF(OR(F62="",K62="",K62<=0),"",F62/K62) | N62: 0.8248119 | O62: =IF(OR(N62="",M62="",M62<=0),"",N62/M62) | P62: -0.2566 | Q62: -0.29704111 | R62: 0.47203148 | S62: 4 | U62: -1.1103382 | V62: -0.043152057 | W62: 0.049274848 | X62: -0.083948989 | Z62: =IF(OR(Y62="",F62="",F62=0),"",Y62/F62) | AA62: 254.917 | AB62: -0.043 | AC62: -0.059521799 | AD62: =IF(OR(Q62="",M62="",M62<=0),"",ROUND(40*MAX(0,MIN(N(Q62)/0.3,1))+IF(OR(R62="",N(Q62)<=0),10,20*MAX(0,1-MIN(R62/Q62,1)))+30*MAX(0,MIN((PARAMETRI!$B$5-M62)/MAX(PARAMETRI!$B$5-10,1),1))+IF(AB62="",3,10*MAX(0,MIN(AB62/0.15,1)))+IF(AND(P62<>"",N(P62)<N(Q62)*0.6),-8,0),1)) | AE62: =IF(AND(P62="",Q62=""),"DATI MANCANTI",IF(AND(N(P62)>=PARAMETRI!$B$4,N(Q62)>=PARAMETRI!$B$4),"OK","NO")) | AF62: =IF(M62="","N/D",IF(M62<PARAMETRI!$B$6,"OTTIMO",IF(M62<PARAMETRI!$B$5,"OK","NO"))) | AG62: =IF(OR(AE62="DATI MANCANTI",AF62="N/D"),"DA COMPLETARE",IF(AND(AE62="OK",AF62="OTTIMO"),"PASSA FORTE",IF(AND(AE62="OK",AF62="OK"),"PASSA","SCARTA"))) | AH62: 2026-10-12 | AI62: yahoo | AJ62: Quotata a Parigi
A63: =IF(AD63="","",RANK(AD63,AD$2:AD$67)) | B63: Geox | C63: GEO.MI | D63: Abbigliamento | E63: Consumi | F63: 0.26 | G63: EUR | H63: 0.26 | I63: 95.2 | J63: 95.2 | K63: -0.04 | L63: 0.01 | M63: =IF(OR(F63="",K63="",K63<=0),"",F63/K63) | N63: 1.2560385 | O63: =IF(OR(N63="",M63="",M63<=0),"",N63/M63) | P63: -0.19634001 | Q63: -0.21356557 | R63: 0.1443956 | S63: 4 | U63: -0.21583615 | V63: -0.44688434 | W63: -0.07121095 | X63: -0.12033084 | Z63: =IF(OR(Y63="",F63="",F63=0),"",Y63/F63) | AA63: 395.272 | AB63: -0.114 | AC63: -0.025015896 | AD63: =IF(OR(Q63="",M63="",M63<=0),"",ROUND(40*MAX(0,MIN(N(Q63)/0.3,1))+IF(OR(R63="",N(Q63)<=0),10,20*MAX(0,1-MIN(R63/Q63,1)))+30*MAX(0,MIN((PARAMETRI!$B$5-M63)/MAX(PARAMETRI!$B$5-10,1),1))+IF(AB63="",3,10*MAX(0,MIN(AB63/0.15,1)))+IF(AND(P63<>"",N(P63)<N(Q63)*0.6),-8,0),1)) | AE63: =IF(AND(P63="",Q63=""),"DATI MANCANTI",IF(AND(N(P63)>=PARAMETRI!$B$4,N(Q63)>=PARAMETRI!$B$4),"OK","NO")) | AF63: =IF(M63="","N/D",IF(M63<PARAMETRI!$B$6,"OTTIMO",IF(M63<PARAMETRI!$B$5,"OK","NO"))) | AG63: =IF(OR(AE63="DATI MANCANTI",AF63="N/D"),"DA COMPLETARE",IF(AND(AE63="OK",AF63="OTTIMO"),"PASSA FORTE",IF(AND(AE63="OK",AF63="OK"),"PASSA","SCARTA"))) | AH63: 2026-10-12 | AI63: yahoo
A64: =IF(AD64="","",RANK(AD64,AD$2:AD$67)) | B64: Juventus FC | C64: JUVE.MI | D64: Sport / Intrattenimento | E64: Consumi | F64: 1.737 | G64: EUR | H64: 1.737 | I64: 724.4 | J64: 724.4 | K64: -0.17 | L64: -0.06018 | M64: =IF(OR(F64="",K64="",K64<=0),"",F64/K64) | N64: 62.035713 | O64: =IF(OR(N64="",M64="",M64<=0),"",N64/M64) | P64: -5.34 | Q64: -3.1157272 | R64: 1.4359304 | S64: 3 | V64: -4.9564385 | W64: -2.9381235 | X64: -1.4526195 | Z64: =IF(OR(Y64="",F64="",F64=0),"",Y64/F64) | AA64: 3159.981 | AB64: -0.015 | AC64: -0.16788345 | AD64: =IF(OR(Q64="",M64="",M64<=0),"",ROUND(40*MAX(0,MIN(N(Q64)/0.3,1))+IF(OR(R64="",N(Q64)<=0),10,20*MAX(0,1-MIN(R64/Q64,1)))+30*MAX(0,MIN((PARAMETRI!$B$5-M64)/MAX(PARAMETRI!$B$5-10,1),1))+IF(AB64="",3,10*MAX(0,MIN(AB64/0.15,1)))+IF(AND(P64<>"",N(P64)<N(Q64)*0.6),-8,0),1)) | AE64: =IF(AND(P64="",Q64=""),"DATI MANCANTI",IF(AND(N(P64)>=PARAMETRI!$B$4,N(Q64)>=PARAMETRI!$B$4),"OK","NO")) | AF64: =IF(M64="","N/D",IF(M64<PARAMETRI!$B$6,"OTTIMO",IF(M64<PARAMETRI!$B$5,"OK","NO"))) | AG64: =IF(OR(AE64="DATI MANCANTI",AF64="N/D"),"DA COMPLETARE",IF(AND(AE64="OK",AF64="OTTIMO"),"PASSA FORTE",IF(AND(AE64="OK",AF64="OK"),"PASSA","SCARTA"))) | AH64: 2026-10-12 | AI64: yahoo
A65: =IF(AD65="","",RANK(AD65,AD$2:AD$67)) | B65: Nexi | C65: NEXI.MI | D65: Pagamenti / Tech | E65: Tecnologia | F65: 4.308 | G65: EUR | H65: 4.308 | I65: 5060.7 | J65: 5060.7 | K65: -2.8 | L65: 0.66339 | M65: =IF(OR(F65="",K65="",K65<=0),"",F65/K65) | N65: 0.74417 | O65: =IF(OR(N65="",M65="",M65<=0),"",N65/M65) | P65: -0.3861 | Q65: -0.13526439 | R65: 0.20252533 | S65: 4 | U65: -0.47846415 | V65: 0.015273459 | W65: -0.089227601 | X65: 0.011360754 | Y65: 0.3 | Z65: =IF(OR(Y65="",F65="",F65=0),"",Y65/F65) | AA65: 86.669 | AB65: 0.016 | AC65: -0.53618106 | AD65: =IF(OR(Q65="",M65="",M65<=0),"",ROUND(40*MAX(0,MIN(N(Q65)/0.3,1))+IF(OR(R65="",N(Q65)<=0),10,20*MAX(0,1-MIN(R65/Q65,1)))+30*MAX(0,MIN((PARAMETRI!$B$5-M65)/MAX(PARAMETRI!$B$5-10,1),1))+IF(AB65="",3,10*MAX(0,MIN(AB65/0.15,1)))+IF(AND(P65<>"",N(P65)<N(Q65)*0.6),-8,0),1)) | AE65: =IF(AND(P65="",Q65=""),"DATI MANCANTI",IF(AND(N(P65)>=PARAMETRI!$B$4,N(Q65)>=PARAMETRI!$B$4),"OK","NO")) | AF65: =IF(M65="","N/D",IF(M65<PARAMETRI!$B$6,"OTTIMO",IF(M65<PARAMETRI!$B$5,"OK","NO"))) | AG65: =IF(OR(AE65="DATI MANCANTI",AF65="N/D"),"DA COMPLETARE",IF(AND(AE65="OK",AF65="OTTIMO"),"PASSA FORTE",IF(AND(AE65="OK",AF65="OK"),"PASSA","SCARTA"))) | AH65: 2026-10-12 | AI65: yahoo
A66: =IF(AD66="","",RANK(AD66,AD$2:AD$67)) | B66: Risanamento | C66: RN.MI | D66: Immobiliare | E66: Immobiliare | F66: 0.0344 | G66: EUR | H66: 0.0344 | I66: 61.9 | J66: 61.9 | K66: -0.01 | M66: =IF(OR(F66="",K66="",K66<=0),"",F66/K66) | O66: =IF(OR(N66="",M66="",M66<=0),"",N66/M66) | P66: -2.12318 | Q66: -2.6314126 | R66: 3.822302 | S66: 4 | V66: -9.1862176 | W66: 0.20234883 | X66: -1.2813885 | Z66: =IF(OR(Y66="",F66="",F66=0),"",Y66/F66) | AB66: 369.333 | AC66: -193.20149 | AD66: =IF(OR(Q66="",M66="",M66<=0),"",ROUND(40*MAX(0,MIN(N(Q66)/0.3,1))+IF(OR(R66="",N(Q66)<=0),10,20*MAX(0,1-MIN(R66/Q66,1)))+30*MAX(0,MIN((PARAMETRI!$B$5-M66)/MAX(PARAMETRI!$B$5-10,1),1))+IF(AB66="",3,10*MAX(0,MIN(AB66/0.15,1)))+IF(AND(P66<>"",N(P66)<N(Q66)*0.6),-8,0),1)) | AE66: =IF(AND(P66="",Q66=""),"DATI MANCANTI",IF(AND(N(P66)>=PARAMETRI!$B$4,N(Q66)>=PARAMETRI!$B$4),"OK","NO")) | AF66: =IF(M66="","N/D",IF(M66<PARAMETRI!$B$6,"OTTIMO",IF(M66<PARAMETRI!$B$5,"OK","NO"))) | AG66: =IF(OR(AE66="DATI MANCANTI",AF66="N/D"),"DA COMPLETARE",IF(AND(AE66="OK",AF66="OTTIMO"),"PASSA FORTE",IF(AND(AE66="OK",AF66="OK"),"PASSA","SCARTA"))) | AH66: 2026-10-12 | AI66: yahoo
A67: =IF(AD67="","",RANK(AD67,AD$2:AD$67)) | B67: Stellantis | C67: STLAM.MI | D67: Auto | E67: Industriale | F67: 3.9695 | G67: EUR | H67: 3.9695 | I67: 11515.3 | J67: 11515.3 | K67: -7.49 | L67: 1.07023 | M67: =IF(OR(F67="",K67="",K67<=0),"",F67/K67) | N67: 0.2048457 | O67: =IF(OR(N67="",M67="",M67<=0),"",N67/M67) | P67: -0.28694 | Q67: 0.027563918 | R67: 0.26560064 | S67: 4 | U67: -0.41769528 | V67: 0.066995544 | W67: 0.22763272 | X67: 0.23332269 | Y67: 0 | Z67: =IF(OR(Y67="",F67="",F67=0),"",Y67/F67) | AA67: 84.387 | AB67: 0.131 | AC67: -0.1268468 | AD67: =IF(OR(Q67="",M67="",M67<=0),"",ROUND(40*MAX(0,MIN(N(Q67)/0.3,1))+IF(OR(R67="",N(Q67)<=0),10,20*MAX(0,1-MIN(R67/Q67,1)))+30*MAX(0,MIN((PARAMETRI!$B$5-M67)/MAX(PARAMETRI!$B$5-10,1),1))+IF(AB67="",3,10*MAX(0,MIN(AB67/0.15,1)))+IF(AND(P67<>"",N(P67)<N(Q67)*0.6),-8,0),1)) | AE67: =IF(AND(P67="",Q67=""),"DATI MANCANTI",IF(AND(N(P67)>=PARAMETRI!$B$4,N(Q67)>=PARAMETRI!$B$4),"OK","NO")) | AF67: =IF(M67="","N/D",IF(M67<PARAMETRI!$B$6,"OTTIMO",IF(M67<PARAMETRI!$B$5,"OK","NO"))) | AG67: =IF(OR(AE67="DATI MANCANTI",AF67="N/D"),"DA COMPLETARE",IF(AND(AE67="OK",AF67="OTTIMO"),"PASSA FORTE",IF(AND(AE67="OK",AF67="OK"),"PASSA","SCARTA"))) | AH67: 2026-10-12 | AI67: yahoo

Sheet GERMANIA
A1: POS. | B1: TITOLO | C1: TICKER | D1: SETTORE | E1: CLASSE | F1: PREZZO | G1: VAL. | H1: PREZZO € | I1: CAP. MLN € | J1: CAP. MLN locale | K1: EPS TTM | L1: EPS ATTESO | M1: P/E | N1: P/B | O1: ROE IMPL. | P1: ROE 1a | Q1: ROE 5a | R1: VARIAB. ROE | S1: ANNI | T1: 2026 | U1: 2025 | V1: 2024 | W1: 2023 | X1: 2022 | Y1: DIVID. | Z1: RENDIM. | AA1: DEBITO/MP | AB1: CRESC. RICAVI | AC1: MARGINE | AD1: PUNTEGGIO | AE1: ESITO ROE | AF1: ESITO P/E | AG1: GIUDIZIO | AH1: RILEVATO | AI1: FONTE | AJ1: NOTE
A2: =IF(AD2="","",RANK(AD2,AD$2:AD$44)) | B2: Munich Re | C2: MUV2.DE | D2: Riassicurazione | E2: Finanziario | F2: 527 | G2: EUR | H2: 527 | I2: 66304.2 | J2: 66304.2 | K2: 54.03 | L2: 51.61599 | M2: =IF(OR(F2="",K2="",K2<=0),"",F2/K2) | N2: 1.9756327 | O2: =IF(OR(N2="",M2="",M2<=0),"",N2/M2) | P2: 0.21299 | Q2: 0.17734574 | R2: 0.014933672 | S2: 4 | U2: 0.1840166 | V2: 0.17391835 | W2: 0.1553457 | X2: 0.19610231 | Y2: 24 | Z2: =IF(OR(Y2="",F2="",F2=0),"",Y2/F2) | AA2: 24.378 | AB2: 0.013 | AC2: 0.11025518 | AD2: =IF(OR(Q2="",M2="",M2<=0),"",ROUND(40*MAX(0,MIN(N(Q2)/0.3,1))+IF(OR(R2="",N(Q2)<=0),10,20*MAX(0,1-MIN(R2/Q2,1)))+30*MAX(0,MIN((PARAMETRI!$B$5-M2)/MAX(PARAMETRI!$B$5-10,1),1))+IF(AB2="",3,10*MAX(0,MIN(AB2/0.15,1)))+IF(AND(P2<>"",N(P2)<N(Q2)*0.6),-8,0),1)) | AE2: =IF(AND(P2="",Q2=""),"DATI MANCANTI",IF(AND(N(P2)>=PARAMETRI!$B$4,N(Q2)>=PARAMETRI!$B$4),"OK","NO")) | AF2: =IF(M2="","N/D",IF(M2<PARAMETRI!$B$6,"OTTIMO",IF(M2<PARAMETRI!$B$5,"OK","NO"))) | AG2: =IF(OR(AE2="DATI MANCANTI",AF2="N/D"),"DA COMPLETARE",IF(AND(AE2="OK",AF2="OTTIMO"),"PASSA FORTE",IF(AND(AE2="OK",AF2="OK"),"PASSA","SCARTA"))) | AH2: 2026-10-12 | AI2: yahoo
A3: =IF(AD3="","",RANK(AD3,AD$2:AD$44)) | B3: Allianz | C3: ALV.DE | D3: Assicurazione | E3: Finanziario | F3: 420.5 | G3: EUR | H3: 420.5 | I3: 159489.9 | J3: 159489.9 | K3: 30.48 | L3: 33.39562 | M3: =IF(OR(F3="",K3="",K3<=0),"",F3/K3) | N3: 2.5281067 | O3: =IF(OR(N3="",M3="",M3<=0),"",N3/M3) | P3: 0.19612 | Q3: 0.15029334 | R3: 0.020775856 | S3: 4 | U3: 0.1717898 | V3: 0.16472871 | W3: 0.1466543 | X3: 0.11800055 | Y3: 17.1 | Z3: =IF(OR(Y3="",F3="",F3=0),"",Y3/F3) | AA3: 50.648 | AB3: 0.121 | AC3: 0.084481632 | AD3: =IF(OR(Q3="",M3="",M3<=0),"",ROUND(40*MAX(0,MIN(N(Q3)/0.3,1))+IF(OR(R3="",N(Q3)<=0),10,20*MAX(0,1-MIN(R3/Q3,1)))+30*MAX(0,MIN((PARAMETRI!$B$5-M3)/MAX(PARAMETRI!$B$5-10,1),1))+IF(AB3="",3,10*MAX(0,MIN(AB3/0.15,1)))+IF(AND(P3<>"",N(P3)<N(Q3)*0.6),-8,0),1)) | AE3: =IF(AND(P3="",Q3=""),"DATI MANCANTI",IF(AND(N(P3)>=PARAMETRI!$B$4,N(Q3)>=PARAMETRI!$B$4),"OK","NO")) | AF3: =IF(M3="","N/D",IF(M3<PARAMETRI!$B$6,"OTTIMO",IF(M3<PARAMETRI!$B$5,"OK","NO"))) | AG3: =IF(OR(AE3="DATI MANCANTI",AF3="N/D"),"DA COMPLETARE",IF(AND(AE3="OK",AF3="OTTIMO"),"PASSA FORTE",IF(AND(AE3="OK",AF3="OK"),"PASSA","SCARTA"))) | AH3: 2026-10-12 | AI3: yahoo
A4: =IF(AD4="","",RANK(AD4,AD$2:AD$44)) | B4: Hannover Rueck | C4: HNR1.DE | D4: Riassicurazione | E4: Finanziario | F4: 267 | G4: EUR | H4: 267 | I4: 32199.4 | J4: 32199.4 | K4: 22.77 | L4: 23.62468 | M4: =IF(OR(F4="",K4="",K4<=0),"",F4/K4) | N4: 2.4272065 | O4: =IF(OR(N4="",M4="",M4<=0),"",N4/M4) | P4: 0.22163 | Q4: 0.16703284 | R4: 0.04749781 | S4: 4 | U4: 0.20431289 | V4: 0.19743948 | W4: 0.18019513 | X4: 0.086183869 | Y4: 12.5 | Z4: =IF(OR(Y4="",F4="",F4=0),"",Y4/F4) | AA4: 28.967 | AB4: -0.233 | AC4: 0.11381142 | AD4: =IF(OR(Q4="",M4="",M4<=0),"",ROUND(40*MAX(0,MIN(N(Q4)/0.3,1))+IF(OR(R4="",N(Q4)<=0),10,20*MAX(0,1-MIN(R4/Q4,1)))+30*MAX(0,MIN((PARAMETRI!$B$5-M4)/MAX(PARAMETRI!$B$5-10,1),1))+IF(AB4="",3,10*MAX(0,MIN(AB4/0.15,1)))+IF(AND(P4<>"",N(P4)<N(Q4)*0.6),-8,0),1)) | AE4: =IF(AND(P4="",Q4=""),"DATI MANCANTI",IF(AND(N(P4)>=PARAMETRI!$B$4,N(Q4)>=PARAMETRI!$B$4),"OK","NO")) | AF4: =IF(M4="","N/D",IF(M4<PARAMETRI!$B$6,"OTTIMO",IF(M4<PARAMETRI!$B$5,"OK","NO"))) | AG4: =IF(OR(AE4="DATI MANCANTI",AF4="N/D"),"DA COMPLETARE",IF(AND(AE4="OK",AF4="OTTIMO"),"PASSA FORTE",IF(AND(AE4="OK",AF4="OK"),"PASSA","SCARTA"))) | AH4: 2026-10-12 | AI4: yahoo
A5: =IF(AD5="","",RANK(AD5,AD$2:AD$44)) | B5: Deutsche Bank | C5: DBK.DE | D5: Banca | E5: Finanziario | F5: 30.29 | G5: EUR | H5: 30.29 | I5: 56914.9 | J5: 56914.9 | K5: 3.29 | L5: 3.84065 | M5: =IF(OR(F5="",K5="",K5<=0),"",F5/K5) | N5: 0.7220501 | O5: =IF(OR(N5="",M5="",M5<=0),"",N5/M5) | P5: 0.08891 | Q5: 0.068758561 | R5: 0.01680391 | S5: 4 | U5: 0.088134688 | V5: 0.043250328 | W5: 0.065321543 | X5: 0.078327686 | Y5: 1 | Z5: =IF(OR(Y5="",F5="",F5=0),"",Y5/F5) | AB5: 0.087 | AC5: 0.18975668 | AD5: =IF(OR(Q5="",M5="",M5<=0),"",ROUND(40*MAX(0,MIN(N(Q5)/0.3,1))+IF(OR(R5="",N(Q5)<=0),10,20*MAX(0,1-MIN(R5/Q5,1)))+30*MAX(0,MIN((PARAMETRI!$B$5-M5)/MAX(PARAMETRI!$B$5-10,1),1))+IF(AB5="",3,10*MAX(0,MIN(AB5/0.15,1)))+IF(AND(P5<>"",N(P5)<N(Q5)*0.6),-8,0),1)) | AE5: =IF(AND(P5="",Q5=""),"DATI MANCANTI",IF(AND(N(P5)>=PARAMETRI!$B$4,N(Q5)>=PARAMETRI!$B$4),"OK","NO")) | AF5: =IF(M5="","N/D",IF(M5<PARAMETRI!$B$6,"OTTIMO",IF(M5<PARAMETRI!$B$5,"OK","NO"))) | AG5: =IF(OR(AE5="DATI MANCANTI",AF5="N/D"),"DA COMPLETARE",IF(AND(AE5="OK",AF5="OTTIMO"),"PASSA FORTE",IF(AND(AE5="OK",AF5="OK"),"PASSA","SCARTA"))) | AH5: 2026-10-12 | AI5: yahoo
A6: =IF(AD6="","",RANK(AD6,AD$2:AD$44)) | B6: Deutsche Telekom | C6: DTE.DE | D6: Telecomunicazioni | E6: Industriale | F6: 24.98 | G6: EUR | H6: 24.98 | I6: 119469.6 | J6: 119469.6 | K6: 1.63 | L6: 2.56026 | M6: =IF(OR(F6="",K6="",K6<=0),"",F6/K6) | N6: 1.9961643 | O6: =IF(OR(N6="",M6="",M6<=0),"",N6/M6) | P6: 0.15063 | Q6: 0.20222489 | R6: 0.064154511 | S6: 4 | U6: 0.15455759 | V6: 0.1770886 | W6: 0.31248134 | X6: 0.16477203 | Y6: 1 | Z6: =IF(OR(Y6="",F6="",F6=0),"",Y6/F6) | AA6: 165.297 | AB6: 0.043 | AC6: 0.073025019 | AD6: =IF(OR(Q6="",M6="",M6<=0),"",ROUND(40*MAX(0,MIN(N(Q6)/0.3,1))+IF(OR(R6="",N(Q6)<=0),10,20*MAX(0,1-MIN(R6/Q6,1)))+30*MAX(0,MIN((PARAMETRI!$B$5-M6)/MAX(PARAMETRI!$B$5-10,1),1))+IF(AB6="",3,10*MAX(0,MIN(AB6/0.15,1)))+IF(AND(P6<>"",N(P6)<N(Q6)*0.6),-8,0),1)) | AE6: =IF(AND(P6="",Q6=""),"DATI MANCANTI",IF(AND(N(P6)>=PARAMETRI!$B$4,N(Q6)>=PARAMETRI!$B$4),"OK","NO")) | AF6: =IF(M6="","N/D",IF(M6<PARAMETRI!$B$6,"OTTIMO",IF(M6<PARAMETRI!$B$5,"OK","NO"))) | AG6: =IF(OR(AE6="DATI MANCANTI",AF6="N/D"),"DA COMPLETARE",IF(AND(AE6="OK",AF6="OTTIMO"),"PASSA FORTE",IF(AND(AE6="OK",AF6="OK"),"PASSA","SCARTA"))) | AH6: 2026-10-12 | AI6: yahoo
A7: =IF(AD7="","",RANK(AD7,AD$2:AD$44)) | B7: Heidelberg Materials | C7: HEI.DE | D7: Cemento | E7: Materiali | F7: 142.9 | G7: EUR | H7: 142.9 | I7: 25122.1 | J7: 25122.1 | K7: 11.5 | L7: 14.38566 | M7: =IF(OR(F7="",K7="",K7<=0),"",F7/K7) | N7: 1.3481895 | O7: =IF(OR(N7="",M7="",M7<=0),"",N7/M7) | P7: 0.11698 | Q7: 0.10251702 | R7: 0.0071003171 | S7: 4 | U7: 0.10685069 | V7: 0.094798783 | W7: 0.11187671 | X7: 0.096541883 | Y7: 3.6 | Z7: =IF(OR(Y7="",F7="",F7=0),"",Y7/F7) | AA7: 50.409 | AB7: 0.017 | AC7: 0.094775446 | AD7: =IF(OR(Q7="",M7="",M7<=0),"",ROUND(40*MAX(0,MIN(N(Q7)/0.3,1))+IF(OR(R7="",N(Q7)<=0),10,20*MAX(0,1-MIN(R7/Q7,1)))+30*MAX(0,MIN((PARAMETRI!$B$5-M7)/MAX(PARAMETRI!$B$5-10,1),1))+IF(AB7="",3,10*MAX(0,MIN(AB7/0.15,1)))+IF(AND(P7<>"",N(P7)<N(Q7)*0.6),-8,0),1)) | AE7: =IF(AND(P7="",Q7=""),"DATI MANCANTI",IF(AND(N(P7)>=PARAMETRI!$B$4,N(Q7)>=PARAMETRI!$B$4),"OK","NO")) | AF7: =IF(M7="","N/D",IF(M7<PARAMETRI!$B$6,"OTTIMO",IF(M7<PARAMETRI!$B$5,"OK","NO"))) | AG7: =IF(OR(AE7="DATI MANCANTI",AF7="N/D"),"DA COMPLETARE",IF(AND(AE7="OK",AF7="OTTIMO"),"PASSA FORTE",IF(AND(AE7="OK",AF7="OK"),"PASSA","SCARTA"))) | AH7: 2026-10-12 | AI7: yahoo
A8: =IF(AD8="","",RANK(AD8,AD$2:AD$44)) | B8: DHL Group | C8: DHL.DE | D8: Logistica | E8: Industriale | F8: 56.74 | G8: EUR | H8: 56.74 | I8: 63505.9 | J8: 63505.9 | K8: 3.29 | L8: 3.88552 | M8: =IF(OR(F8="",K8="",K8<=0),"",F8/K8) | N8: 2.8258379 | O8: =IF(OR(N8="",M8="",M8<=0),"",N8/M8) | P8: 0.18090001 | Q8: 0.17292521 | R8: 0.034415661 | S8: 4 | U8: 0.15751114 | V8: 0.14004119 | W8: 0.16351502 | X8: 0.2306335 | Y8: 1.9 | Z8: =IF(OR(Y8="",F8="",F8=0),"",Y8/F8) | AA8: 122.614 | AB8: 0.128 | AC8: 0.044861504 | AD8: =IF(OR(Q8="",M8="",M8<=0),"",ROUND(40*MAX(0,MIN(N(Q8)/0.3,1))+IF(OR(R8="",N(Q8)<=0),10,20*MAX(0,1-MIN(R8/Q8,1)))+30*MAX(0,MIN((PARAMETRI!$B$5-M8)/MAX(PARAMETRI!$B$5-10,1),1))+IF(AB8="",3,10*MAX(0,MIN(AB8/0.15,1)))+IF(AND(P8<>"",N(P8)<N(Q8)*0.6),-8,0),1)) | AE8: =IF(AND(P8="",Q8=""),"DATI MANCANTI",IF(AND(N(P8)>=PARAMETRI!$B$4,N(Q8)>=PARAMETRI!$B$4),"OK","NO")) | AF8: =IF(M8="","N/D",IF(M8<PARAMETRI!$B$6,"OTTIMO",IF(M8<PARAMETRI!$B$5,"OK","NO"))) | AG8: =IF(OR(AE8="DATI MANCANTI",AF8="N/D"),"DA COMPLETARE",IF(AND(AE8="OK",AF8="OTTIMO"),"PASSA FORTE",IF(AND(AE8="OK",AF8="OK"),"PASSA","SCARTA"))) | AH8: 2026-10-12 | AI8: yahoo
A9: =IF(AD9="","",RANK(AD9,AD$2:AD$44)) | B9: Adidas | C9: ADS.DE | D9: Abbigliamento sportivo | E9: Consumi | F9: 149.6 | G9: EUR | H9: 149.6 | I9: 26189.4 | J9: 26189.4 | K9: 7.96 | L9: 11.60475 | M9: =IF(OR(F9="",K9="",K9<=0),"",F9/K9) | N9: 4.397155 | O9: =IF(OR(N9="",M9="",M9<=0),"",N9/M9) | P9: 0.24324 | Q9: 0.24324 | S9: 0 | U9: 0.23199446 | V9: 0.1395179 | W9: -0.016375546 | X9: 0.12262072 | Y9: 2.8 | Z9: =IF(OR(Y9="",F9="",F9=0),"",Y9/F9) | AA9: 94.127 | AB9: 0.133 | AC9: 0.055660793 | AD9: =IF(OR(Q9="",M9="",M9<=0),"",ROUND(40*MAX(0,MIN(N(Q9)/0.3,1))+IF(OR(R9="",N(Q9)<=0),10,20*MAX(0,1-MIN(R9/Q9,1)))+30*MAX(0,MIN((PARAMETRI!$B$5-M9)/MAX(PARAMETRI!$B$5-10,1),1))+IF(AB9="",3,10*MAX(0,MIN(AB9/0.15,1)))+IF(AND(P9<>"",N(P9)<N(Q9)*0.6),-8,0),1)) | AE9: =IF(AND(P9="",Q9=""),"DATI MANCANTI",IF(AND(N(P9)>=PARAMETRI!$B$4,N(Q9)>=PARAMETRI!$B$4),"OK","NO")) | AF9: =IF(M9="","N/D",IF(M9<PARAMETRI!$B$6,"OTTIMO",IF(M9<PARAMETRI!$B$5,"OK","NO"))) | AG9: =IF(OR(AE9="DATI MANCANTI",AF9="N/D"),"DA COMPLETARE",IF(AND(AE9="OK",AF9="OTTIMO"),"PASSA FORTE",IF(AND(AE9="OK",AF9="OK"),"PASSA","SCARTA"))) | AH9: 2026-10-12 | AI9: yahoo
A10: =IF(AD10="","",RANK(AD10,AD$2:AD$44)) | B10: Deutsche Boerse | C10: DB1.DE | D10: Infrastrutture di mercato | E10: Finanziario | F10: 298.3 | G10: EUR | H10: 298.3 | I10: 53779.8 | J10: 53779.8 | K10: 11.75 | L10: 13.60433 | M10: =IF(OR(F10="",K10="",K10<=0),"",F10/K10) | N10: 5.193064 | O10: =IF(OR(N10="",M10="",M10<=0),"",N10/M10) | P10: 0.20412001 | Q10: 0.17801364 | R10: 0.0018442129 | S10: 4 | U10: 0.17636139 | V10: 0.180856 | W10: 0.1784402 | X10: 0.17639699 | Y10: 4.2 | Z10: =IF(OR(Y10="",F10="",F10=0),"",Y10/F10) | AA10: 57.645 | AB10: 0.117 | AC10: 0.28654655 | AD10: =IF(OR(Q10="",M10="",M10<=0),"",ROUND(40*MAX(0,MIN(N(Q10)/0.3,1))+IF(OR(R10="",N(Q10)<=0),10,20*MAX(0,1-MIN(R10/Q10,1)))+30*MAX(0,MIN((PARAMETRI!$B$5-M10)/MAX(PARAMETRI!$B$5-10,1),1))+IF(AB10="",3,10*MAX(0,MIN(AB10/0.15,1)))+IF(AND(P10<>"",N(P10)<N(Q10)*0.6),-8,0),1)) | AE10: =IF(AND(P10="",Q10=""),"DATI MANCANTI",IF(AND(N(P10)>=PARAMETRI!$B$4,N(Q10)>=PARAMETRI!$B$4),"OK","NO")) | AF10: =IF(M10="","N/D",IF(M10<PARAMETRI!$B$6,"OTTIMO",IF(M10<PARAMETRI!$B$5,"OK","NO"))) | AG10: =IF(OR(AE10="DATI MANCANTI",AF10="N/D"),"DA COMPLETARE",IF(AND(AE10="OK",AF10="OTTIMO"),"PASSA FORTE",IF(AND(AE10="OK",AF10="OK"),"PASSA","SCARTA"))) | AH10: 2026-10-12 | AI10: yahoo
A11: =IF(AD11="","",RANK(AD11,AD$2:AD$44)) | B11: Mercedes-Benz Group | C11: MBG.DE | D11: Auto | E11: Consumi | F11: 39.265 | G11: EUR | H11: 39.265 | I11: 37271.6 | J11: 37271.6 | K11: 5.28 | L11: 6.74821 | M11: =IF(OR(F11="",K11="",K11<=0),"",F11/K11) | N11: 0.39570883 | O11: =IF(OR(N11="",M11="",M11<=0),"",N11/M11) | P11: 0.055960003 | Q11: 0.12262242 | R11: 0.044740882 | S11: 4 | U11: 0.055127229 | V11: 0.11019703 | W11: 0.15539429 | X11: 0.16977112 | Y11: 3.5 | Z11: =IF(OR(Y11="",F11="",F11=0),"",Y11/F11) | AA11: 110.208 | AB11: -0.033 | AC11: 0.038051947 | AD11: =IF(OR(Q11="",M11="",M11<=0),"",ROUND(40*MAX(0,MIN(N(Q11)/0.3,1))+IF(OR(R11="",N(Q11)<=0),10,20*MAX(0,1-MIN(R11/Q11,1)))+30*MAX(0,MIN((PARAMETRI!$B$5-M11)/MAX(PARAMETRI!$B$5-10,1),1))+IF(AB11="",3,10*MAX(0,MIN(AB11/0.15,1)))+IF(AND(P11<>"",N(P11)<N(Q11)*0.6),-8,0),1)) | AE11: =IF(AND(P11="",Q11=""),"DATI MANCANTI",IF(AND(N(P11)>=PARAMETRI!$B$4,N(Q11)>=PARAMETRI!$B$4),"OK","NO")) | AF11: =IF(M11="","N/D",IF(M11<PARAMETRI!$B$6,"OTTIMO",IF(M11<PARAMETRI!$B$5,"OK","NO"))) | AG11: =IF(OR(AE11="DATI MANCANTI",AF11="N/D"),"DA COMPLETARE",IF(AND(AE11="OK",AF11="OTTIMO"),"PASSA FORTE",IF(AND(AE11="OK",AF11="OK"),"PASSA","SCARTA"))) | AH11: 2026-10-12 | AI11: yahoo
A12: =IF(AD12="","",RANK(AD12,AD$2:AD$44)) | B12: Rheinmetall | C12: RHM.DE | D12: Difesa | E12: Industriale | F12: 962.2 | G12: EUR | H12: 962.2 | I12: 44904 | J12: 44904 | K12: 26.11 | L12: 52.99102 | M12: =IF(OR(F12="",K12="",K12<=0),"",F12/K12) | N12: 9.030842 | O12: =IF(OR(N12="",M12="",M12<=0),"",N12/M12) | P12: 0.25688 | Q12: 0.16135379 | R12: 0.014111202 | S12: 4 | U12: 0.13889443 | V12: 0.17703704 | W12: 0.16133896 | X12: 0.16814473 | Y12: 11.5 | Z12: =IF(OR(Y12="",F12="",F12=0),"",Y12/F12) | AA12: 51.63 | AB12: 0.688 | AC12: 0.12179165 | AD12: =IF(OR(Q12="",M12="",M12<=0),"",ROUND(40*MAX(0,MIN(N(Q12)/0.3,1))+IF(OR(R12="",N(Q12)<=0),10,20*MAX(0,1-MIN(R12/Q12,1)))+30*MAX(0,MIN((PARAMETRI!$B$5-M12)/MAX(PARAMETRI!$B$5-10,1),1))+IF(AB12="",3,10*MAX(0,MIN(AB12/0.15,1)))+IF(AND(P12<>"",N(P12)<N(Q12)*0.6),-8,0),1)) | AE12: =IF(AND(P12="",Q12=""),"DATI MANCANTI",IF(AND(N(P12)>=PARAMETRI!$B$4,N(Q12)>=PARAMETRI!$B$4),"OK","NO")) | AF12: =IF(M12="","N/D",IF(M12<PARAMETRI!$B$6,"OTTIMO",IF(M12<PARAMETRI!$B$5,"OK","NO"))) | AG12: =IF(OR(AE12="DATI MANCANTI",AF12="N/D"),"DA COMPLETARE",IF(AND(AE12="OK",AF12="OTTIMO"),"PASSA FORTE",IF(AND(AE12="OK",AF12="OK"),"PASSA","SCARTA"))) | AH12: 2026-10-12 | AI12: yahoo
A13: =IF(AD13="","",RANK(AD13,AD$2:AD$44)) | B13: BMW | C13: BMW.DE | D13: Auto | E13: Consumi | F13: 53.06 | G13: EUR | H13: 53.06 | I13: 31760.4 | J13: 31760.4 | K13: 10.31 | L13: 8.70421 | M13: =IF(OR(F13="",K13="",K13<=0),"",F13/K13) | N13: 0.33326006 | O13: =IF(OR(N13="",M13="",M13<=0),"",N13/M13) | P13: 0.06592 | Q13: 0.12178027 | R13: 0.052455694 | S13: 4 | U13: 0.076219735 | V13: 0.078968748 | W13: 0.12601009 | X13: 0.20592253 | Y13: 4.4 | Z13: =IF(OR(Y13="",F13="",F13=0),"",Y13/F13) | AA13: 119.855 | AB13: -0.079 | AC13: 0.047230111 | AD13: =IF(OR(Q13="",M13="",M13<=0),"",ROUND(40*MAX(0,MIN(N(Q13)/0.3,1))+IF(OR(R13="",N(Q13)<=0),10,20*MAX(0,1-MIN(R13/Q13,1)))+30*MAX(0,MIN((PARAMETRI!$B$5-M13)/MAX(PARAMETRI!$B$5-10,1),1))+IF(AB13="",3,10*MAX(0,MIN(AB13/0.15,1)))+IF(AND(P13<>"",N(P13)<N(Q13)*0.6),-8,0),1)) | AE13: =IF(AND(P13="",Q13=""),"DATI MANCANTI",IF(AND(N(P13)>=PARAMETRI!$B$4,N(Q13)>=PARAMETRI!$B$4),"OK","NO")) | AF13: =IF(M13="","N/D",IF(M13<PARAMETRI!$B$6,"OTTIMO",IF(M13<PARAMETRI!$B$5,"OK","NO"))) | AG13: =IF(OR(AE13="DATI MANCANTI",AF13="N/D"),"DA COMPLETARE",IF(AND(AE13="OK",AF13="OTTIMO"),"PASSA FORTE",IF(AND(AE13="OK",AF13="OK"),"PASSA","SCARTA"))) | AH13: 2026-10-12 | AI13: yahoo
A14: =IF(AD14="","",RANK(AD14,AD$2:AD$44)) | B14: GEA Group | C14: G1A.DE | D14: Impiantistica | E14: Industriale | F14: 68.75 | G14: EUR | H14: 68.75 | I14: 11192.6 | J14: 11192.6 | K14: 2.7 | L14: 3.74645 | M14: =IF(OR(F14="",K14="",K14<=0),"",F14/K14) | N14: 4.4724174 | O14: =IF(OR(N14="",M14="",M14<=0),"",N14/M14) | P14: 0.18450001 | Q14: 0.16687526 | R14: 0.0063399103 | S14: 4 | U14: 0.16877775 | V14: 0.15886257 | W14: 0.16383578 | X14: 0.17602495 | Y14: 1.3 | Z14: =IF(OR(Y14="",F14="",F14=0),"",Y14/F14) | AA14: 10.426 | AB14: 0.1 | AC14: 0.079509683 | AD14: =IF(OR(Q14="",M14="",M14<=0),"",ROUND(40*MAX(0,MIN(N(Q14)/0.3,1))+IF(OR(R14="",N(Q14)<=0),10,20*MAX(0,1-MIN(R14/Q14,1)))+30*MAX(0,MIN((PARAMETRI!$B$5-M14)/MAX(PARAMETRI!$B$5-10,1),1))+IF(AB14="",3,10*MAX(0,MIN(AB14/0.15,1)))+IF(AND(P14<>"",N(P14)<N(Q14)*0.6),-8,0),1)) | AE14: =IF(AND(P14="",Q14=""),"DATI MANCANTI",IF(AND(N(P14)>=PARAMETRI!$B$4,N(Q14)>=PARAMETRI!$B$4),"OK","NO")) | AF14: =IF(M14="","N/D",IF(M14<PARAMETRI!$B$6,"OTTIMO",IF(M14<PARAMETRI!$B$5,"OK","NO"))) | AG14: =IF(OR(AE14="DATI MANCANTI",AF14="N/D"),"DA COMPLETARE",IF(AND(AE14="OK",AF14="OTTIMO"),"PASSA FORTE",IF(AND(AE14="OK",AF14="OK"),"PASSA","SCARTA"))) | AH14: 2026-10-12 | AI14: yahoo
A15: =IF(AD15="","",RANK(AD15,AD$2:AD$44)) | B15: Commerzbank | C15: CBK.DE | D15: Banca | E15: Finanziario | F15: 38.12 | G15: EUR | H15: 38.12 | I15: 41201.9 | J15: 41201.9 | K15: 2.57 | L15: 3.91935 | M15: =IF(OR(F15="",K15="",K15<=0),"",F15/K15) | N15: 1.2201914 | O15: =IF(OR(N15="",M15="",M15<=0),"",N15/M15) | P15: 0.09666 | Q15: 0.068135364 | R15: 0.012220275 | S15: 4 | U15: 0.077596145 | V15: 0.077666241 | W15: 0.069517379 | X15: 0.047761691 | Y15: 1.1 | Z15: =IF(OR(Y15="",F15="",F15=0),"",Y15/F15) | AB15: 0.101 | AC15: 0.22174115 | AD15: =IF(OR(Q15="",M15="",M15<=0),"",ROUND(40*MAX(0,MIN(N(Q15)/0.3,1))+IF(OR(R15="",N(Q15)<=0),10,20*MAX(0,1-MIN(R15/Q15,1)))+30*MAX(0,MIN((PARAMETRI!$B$5-M15)/MAX(PARAMETRI!$B$5-10,1),1))+IF(AB15="",3,10*MAX(0,MIN(AB15/0.15,1)))+IF(AND(P15<>"",N(P15)<N(Q15)*0.6),-8,0),1)) | AE15: =IF(AND(P15="",Q15=""),"DATI MANCANTI",IF(AND(N(P15)>=PARAMETRI!$B$4,N(Q15)>=PARAMETRI!$B$4),"OK","NO")) | AF15: =IF(M15="","N/D",IF(M15<PARAMETRI!$B$6,"OTTIMO",IF(M15<PARAMETRI!$B$5,"OK","NO"))) | AG15: =IF(OR(AE15="DATI MANCANTI",AF15="N/D"),"DA COMPLETARE",IF(AND(AE15="OK",AF15="OTTIMO"),"PASSA FORTE",IF(AND(AE15="OK",AF15="OK"),"PASSA","SCARTA"))) | AH15: 2026-10-12 | AI15: yahoo
A16: =IF(AD16="","",RANK(AD16,AD$2:AD$44)) | B16: Fresenius Medical Care | C16: FME.DE | D16: Dialisi | E16: Salute | F16: 37.9 | G16: EUR | H16: 37.9 | I16: 10178.6 | J16: 10178.6 | K16: 3.33 | L16: 4.26488 | M16: =IF(OR(F16="",K16="",K16<=0),"",F16/K16) | N16: 0.80320436 | O16: =IF(OR(N16="",M16="",M16<=0),"",N16/M16) | P16: 0.08524 | Q16: 0.04879567 | R16: 0.015003185 | S16: 4 | U16: 0.073507089 | V16: 0.036902595 | W16: 0.036636376 | X16: 0.048136621 | Y16: 1.49 | Z16: =IF(OR(Y16="",F16="",F16=0),"",Y16/F16) | AA16: 81.131 | AB16: 0.014 | AC16: 0.047778684 | AD16: =IF(OR(Q16="",M16="",M16<=0),"",ROUND(40*MAX(0,MIN(N(Q16)/0.3,1))+IF(OR(R16="",N(Q16)<=0),10,20*MAX(0,1-MIN(R16/Q16,1)))+30*MAX(0,MIN((PARAMETRI!$B$5-M16)/MAX(PARAMETRI!$B$5-10,1),1))+IF(AB16="",3,10*MAX(0,MIN(AB16/0.15,1)))+IF(AND(P16<>"",N(P16)<N(Q16)*0.6),-8,0),1)) | AE16: =IF(AND(P16="",Q16=""),"DATI MANCANTI",IF(AND(N(P16)>=PARAMETRI!$B$4,N(Q16)>=PARAMETRI!$B$4),"OK","NO")) | AF16: =IF(M16="","N/D",IF(M16<PARAMETRI!$B$6,"OTTIMO",IF(M16<PARAMETRI!$B$5,"OK","NO"))) | AG16: =IF(OR(AE16="DATI MANCANTI",AF16="N/D"),"DA COMPLETARE",IF(AND(AE16="OK",AF16="OTTIMO"),"PASSA FORTE",IF(AND(AE16="OK",AF16="OK"),"PASSA","SCARTA"))) | AH16: 2026-10-12 | AI16: yahoo
A17: =IF(AD17="","",RANK(AD17,AD$2:AD$44)) | B17: Volkswagen VZ | C17: VOW3.DE | D17: Auto | E17: Consumi | F17: 68.4 | G17: EUR | H17: 68.4 | I17: 34288.6 | J17: 34288.6 | K17: 10.18 | L17: 21.41173 | M17: =IF(OR(F17="",K17="",K17<=0),"",F17/K17) | N17: 0.1955515 | O17: =IF(OR(N17="",M17="",M17<=0),"",N17/M17) | P17: 0.027609998 | Q17: 0.072278503 | R17: 0.023220451 | S17: 4 | U17: 0.03889482 | V17: 0.062267546 | W17: 0.094485849 | X17: 0.093465799 | Y17: 5.26 | Z17: =IF(OR(Y17="",F17="",F17=0),"",Y17/F17) | AA17: 138.745 | AB17: 0.02 | AC17: 0.016283902 | AD17: =IF(OR(Q17="",M17="",M17<=0),"",ROUND(40*MAX(0,MIN(N(Q17)/0.3,1))+IF(OR(R17="",N(Q17)<=0),10,20*MAX(0,1-MIN(R17/Q17,1)))+30*MAX(0,MIN((PARAMETRI!$B$5-M17)/MAX(PARAMETRI!$B$5-10,1),1))+IF(AB17="",3,10*MAX(0,MIN(AB17/0.15,1)))+IF(AND(P17<>"",N(P17)<N(Q17)*0.6),-8,0),1)) | AE17: =IF(AND(P17="",Q17=""),"DATI MANCANTI",IF(AND(N(P17)>=PARAMETRI!$B$4,N(Q17)>=PARAMETRI!$B$4),"OK","NO")) | AF17: =IF(M17="","N/D",IF(M17<PARAMETRI!$B$6,"OTTIMO",IF(M17<PARAMETRI!$B$5,"OK","NO"))) | AG17: =IF(OR(AE17="DATI MANCANTI",AF17="N/D"),"DA COMPLETARE",IF(AND(AE17="OK",AF17="OTTIMO"),"PASSA FORTE",IF(AND(AE17="OK",AF17="OK"),"PASSA","SCARTA"))) | AH17: 2026-10-12 | AI17: yahoo
A18: =IF(AD18="","",RANK(AD18,AD$2:AD$44)) | B18: RWE | C18: RWE.DE | D18: Utility / Generazione | E18: Utility | F18: 59.26 | G18: EUR | H18: 59.26 | I18: 46221.9 | J18: 46221.9 | K18: 4.51 | L18: 3.3403 | M18: =IF(OR(F18="",K18="",K18<=0),"",F18/K18) | N18: 1.0628452 | O18: =IF(OR(N18="",M18="",M18<=0),"",N18/M18) | P18: 0.08547 | Q18: 0.099913277 | R18: 0.041227712 | S18: 4 | U18: 0.091067741 | V18: 0.16276269 | W18: 0.047294977 | X18: 0.098527705 | Y18: 1.2 | Z18: =IF(OR(Y18="",F18="",F18=0),"",Y18/F18) | AA18: 50.366 | AB18: -0.091 | AC18: 0.18345813 | AD18: =IF(OR(Q18="",M18="",M18<=0),"",ROUND(40*MAX(0,MIN(N(Q18)/0.3,1))+IF(OR(R18="",N(Q18)<=0),10,20*MAX(0,1-MIN(R18/Q18,1)))+30*MAX(0,MIN((PARAMETRI!$B$5-M18)/MAX(PARAMETRI!$B$5-10,1),1))+IF(AB18="",3,10*MAX(0,MIN(AB18/0.15,1)))+IF(AND(P18<>"",N(P18)<N(Q18)*0.6),-8,0),1)) | AE18: =IF(AND(P18="",Q18=""),"DATI MANCANTI",IF(AND(N(P18)>=PARAMETRI!$B$4,N(Q18)>=PARAMETRI!$B$4),"OK","NO")) | AF18: =IF(M18="","N/D",IF(M18<PARAMETRI!$B$6,"OTTIMO",IF(M18<PARAMETRI!$B$5,"OK","NO"))) | AG18: =IF(OR(AE18="DATI MANCANTI",AF18="N/D"),"DA COMPLETARE",IF(AND(AE18="OK",AF18="OTTIMO"),"PASSA FORTE",IF(AND(AE18="OK",AF18="OK"),"PASSA","SCARTA"))) | AH18: 2026-10-12 | AI18: yahoo
A19: =IF(AD19="","",RANK(AD19,AD$2:AD$44)) | B19: E.ON | C19: EOAN.DE | D19: Utility / Reti | E19: Utility | F19: 17.335 | G19: EUR | H19: 17.335 | I19: 45318.6 | J19: 45318.6 | K19: 1.29 | L19: 1.24564 | M19: =IF(OR(F19="",K19="",K19<=0),"",F19/K19) | N19: 2.1353781 | O19: =IF(OR(N19="",M19="",M19<=0),"",N19/M19) | P19: 0.15546 | Q19: 0.12390448 | R19: 0.080248876 | S19: 4 | U19: 0.090031153 | V19: 0.25396558 | W19: 0.036630296 | X19: 0.11499089 | Y19: 0.57 | Z19: =IF(OR(Y19="",F19="",F19=0),"",Y19/F19) | AA19: 152.987 | AB19: -0.005 | AC19: 0.042856779 | AD19: =IF(OR(Q19="",M19="",M19<=0),"",ROUND(40*MAX(0,MIN(N(Q19)/0.3,1))+IF(OR(R19="",N(Q19)<=0),10,20*MAX(0,1-MIN(R19/Q19,1)))+30*MAX(0,MIN((PARAMETRI!$B$5-M19)/MAX(PARAMETRI!$B$5-10,1),1))+IF(AB19="",3,10*MAX(0,MIN(AB19/0.15,1)))+IF(AND(P19<>"",N(P19)<N(Q19)*0.6),-8,0),1)) | AE19: =IF(AND(P19="",Q19=""),"DATI MANCANTI",IF(AND(N(P19)>=PARAMETRI!$B$4,N(Q19)>=PARAMETRI!$B$4),"OK","NO")) | AF19: =IF(M19="","N/D",IF(M19<PARAMETRI!$B$6,"OTTIMO",IF(M19<PARAMETRI!$B$5,"OK","NO"))) | AG19: =IF(OR(AE19="DATI MANCANTI",AF19="N/D"),"DA COMPLETARE",IF(AND(AE19="OK",AF19="OTTIMO"),"PASSA FORTE",IF(AND(AE19="OK",AF19="OK"),"PASSA","SCARTA"))) | AH19: 2026-10-12 | AI19: yahoo
A20: =IF(AD20="","",RANK(AD20,AD$2:AD$44)) | B20: Vonovia | C20: VNA.DE | D20: Immobiliare residenziale | E20: Immobiliare | F20: 16.395 | G20: EUR | H20: 16.395 | I20: 13910.1 | J20: 13910.1 | K20: 4.39 | L20: 1.83186 | M20: =IF(OR(F20="",K20="",K20<=0),"",F20/K20) | N20: 0.51039785 | O20: =IF(OR(N20="",M20="",M20<=0),"",N20/M20) | P20: 0.14558 | Q20: -0.041765652 | R20: 0.13518569 | S20: 4 | U20: 0.13554645 | V20: -0.037338934 | W20: -0.24472211 | X20: -0.020548011 | Y20: 1.25 | Z20: =IF(OR(Y20="",F20="",F20=0),"",Y20/F20) | AA20: 135.1 | AB20: 0.016 | AC20: 0.71512174 | AD20: =IF(OR(Q20="",M20="",M20<=0),"",ROUND(40*MAX(0,MIN(N(Q20)/0.3,1))+IF(OR(R20="",N(Q20)<=0),10,20*MAX(0,1-MIN(R20/Q20,1)))+30*MAX(0,MIN((PARAMETRI!$B$5-M20)/MAX(PARAMETRI!$B$5-10,1),1))+IF(AB20="",3,10*MAX(0,MIN(AB20/0.15,1)))+IF(AND(P20<>"",N(P20)<N(Q20)*0.6),-8,0),1)) | AE20: =IF(AND(P20="",Q20=""),"DATI MANCANTI",IF(AND(N(P20)>=PARAMETRI!$B$4,N(Q20)>=PARAMETRI!$B$4),"OK","NO")) | AF20: =IF(M20="","N/D",IF(M20<PARAMETRI!$B$6,"OTTIMO",IF(M20<PARAMETRI!$B$5,"OK","NO"))) | AG20: =IF(OR(AE20="DATI MANCANTI",AF20="N/D"),"DA COMPLETARE",IF(AND(AE20="OK",AF20="OTTIMO"),"PASSA FORTE",IF(AND(AE20="OK",AF20="OK"),"PASSA","SCARTA"))) | AH20: 2026-10-12 | AI20: yahoo
A21: =IF(AD21="","",RANK(AD21,AD$2:AD$44)) | B21: Henkel VZ | C21: HEN3.DE | D21: Beni per la casa | E21: Consumi | F21: 75.32 | G21: EUR | H21: 75.32 | I21: 30493.4 | J21: 30493.4 | K21: 4.71 | L21: 5.88165 | M21: =IF(OR(F21="",K21="",K21<=0),"",F21/K21) | N21: 1.4557685 | O21: =IF(OR(N21="",M21="",M21<=0),"",N21/M21) | P21: 0.09395 | Q21: 0.080124375 | R21: 0.015938534 | S21: 4 | U21: 0.099297355 | V21: 0.092352292 | W21: 0.066158016 | X21: 0.062689837 | Y21: 2.07 | Z21: =IF(OR(Y21="",F21="",F21=0),"",Y21/F21) | AA21: 32.159 | AB21: -0.005 | AC21: 0.093339836 | AD21: =IF(OR(Q21="",M21="",M21<=0),"",ROUND(40*MAX(0,MIN(N(Q21)/0.3,1))+IF(OR(R21="",N(Q21)<=0),10,20*MAX(0,1-MIN(R21/Q21,1)))+30*MAX(0,MIN((PARAMETRI!$B$5-M21)/MAX(PARAMETRI!$B$5-10,1),1))+IF(AB21="",3,10*MAX(0,MIN(AB21/0.15,1)))+IF(AND(P21<>"",N(P21)<N(Q21)*0.6),-8,0),1)) | AE21: =IF(AND(P21="",Q21=""),"DATI MANCANTI",IF(AND(N(P21)>=PARAMETRI!$B$4,N(Q21)>=PARAMETRI!$B$4),"OK","NO")) | AF21: =IF(M21="","N/D",IF(M21<PARAMETRI!$B$6,"OTTIMO",IF(M21<PARAMETRI!$B$5,"OK","NO"))) | AG21: =IF(OR(AE21="DATI MANCANTI",AF21="N/D"),"DA COMPLETARE",IF(AND(AE21="OK",AF21="OTTIMO"),"PASSA FORTE",IF(AND(AE21="OK",AF21="OK"),"PASSA","SCARTA"))) | AH21: 2026-10-12 | AI21: yahoo
A22: =IF(AD22="","",RANK(AD22,AD$2:AD$44)) | B22: Siemens | C22: SIE.DE | D22: Conglomerata industriale | E22: Industriale | F22: 275.75 | G22: EUR | H22: 275.75 | I22: 211076.4 | J22: 211076.4 | K22: 10.03 | L22: 12.90652 | M22: =IF(OR(F22="",K22="",K22<=0),"",F22/K22) | N22: 3.1269138 | O22: =IF(OR(N22="",M22="",M22<=0),"",N22/M22) | P22: 0.12465999 | Q22: 0.1397455 | R22: 0.036962433 | S22: 4 | U22: 0.15455305 | V22: 0.1619265 | W22: 0.16635972 | X22: 0.076142755 | Y22: 5.35 | Z22: =IF(OR(Y22="",F22="",F22=0),"",Y22/F22) | AA22: 66.425 | AB22: 0.073 | AC22: 0.09972882 | AD22: =IF(OR(Q22="",M22="",M22<=0),"",ROUND(40*MAX(0,MIN(N(Q22)/0.3,1))+IF(OR(R22="",N(Q22)<=0),10,20*MAX(0,1-MIN(R22/Q22,1)))+30*MAX(0,MIN((PARAMETRI!$B$5-M22)/MAX(PARAMETRI!$B$5-10,1),1))+IF(AB22="",3,10*MAX(0,MIN(AB22/0.15,1)))+IF(AND(P22<>"",N(P22)<N(Q22)*0.6),-8,0),1)) | AE22: =IF(AND(P22="",Q22=""),"DATI MANCANTI",IF(AND(N(P22)>=PARAMETRI!$B$4,N(Q22)>=PARAMETRI!$B$4),"OK","NO")) | AF22: =IF(M22="","N/D",IF(M22<PARAMETRI!$B$6,"OTTIMO",IF(M22<PARAMETRI!$B$5,"OK","NO"))) | AG22: =IF(OR(AE22="DATI MANCANTI",AF22="N/D"),"DA COMPLETARE",IF(AND(AE22="OK",AF22="OTTIMO"),"PASSA FORTE",IF(AND(AE22="OK",AF22="OK"),"PASSA","SCARTA"))) | AH22: 2026-10-12 | AI22: yahoo
A23: =IF(AD23="","",RANK(AD23,AD$2:AD$44)) | B23: Brenntag | C23: BNR.DE | D23: Distribuzione chimica | E23: Industriale | F23: 61.84 | G23: EUR | H23: 61.84 | I23: 8928.8 | J23: 8928.8 | K23: 2.54 | L23: 4.17161 | M23: =IF(OR(F23="",K23="",K23<=0),"",F23/K23) | N23: 2.013742 | O23: =IF(OR(N23="",M23="",M23<=0),"",N23/M23) | P23: 0.085310005 | Q23: 0.13186131 | R23: 0.048682458 | S23: 4 | U23: 0.061333766 | V23: 0.11344067 | W23: 0.16607429 | X23: 0.18659653 | Y23: 1.9 | Z23: =IF(OR(Y23="",F23="",F23=0),"",Y23/F23) | AA23: 80.702 | AB23: 0.102 | AC23: 0.024031902 | AD23: =IF(OR(Q23="",M23="",M23<=0),"",ROUND(40*MAX(0,MIN(N(Q23)/0.3,1))+IF(OR(R23="",N(Q23)<=0),10,20*MAX(0,1-MIN(R23/Q23,1)))+30*MAX(0,MIN((PARAMETRI!$B$5-M23)/MAX(PARAMETRI!$B$5-10,1),1))+IF(AB23="",3,10*MAX(0,MIN(AB23/0.15,1)))+IF(AND(P23<>"",N(P23)<N(Q23)*0.6),-8,0),1)) | AE23: =IF(AND(P23="",Q23=""),"DATI MANCANTI",IF(AND(N(P23)>=PARAMETRI!$B$4,N(Q23)>=PARAMETRI!$B$4),"OK","NO")) | AF23: =IF(M23="","N/D",IF(M23<PARAMETRI!$B$6,"OTTIMO",IF(M23<PARAMETRI!$B$5,"OK","NO"))) | AG23: =IF(OR(AE23="DATI MANCANTI",AF23="N/D"),"DA COMPLETARE",IF(AND(AE23="OK",AF23="OTTIMO"),"PASSA FORTE",IF(AND(AE23="OK",AF23="OK"),"PASSA","SCARTA"))) | AH23: 2026-10-12 | AI23: yahoo
A24: =IF(AD24="","",RANK(AD24,AD$2:AD$44)) | B24: Beiersdorf | C24: BEI.DE | D24: Cura della persona | E24: Consumi | F24: 79.24 | G24: EUR | H24: 79.24 | I24: 17315.8 | J24: 17315.8 | K24: 4.3 | L24: 3.99155 | M24: =IF(OR(F24="",K24="",K24<=0),"",F24/K24) | N24: 1.9199922 | O24: =IF(OR(N24="",M24="",M24<=0),"",N24/M24) | P24: 0.10887 | Q24: 0.10055141 | R24: 0.0084201392 | S24: 4 | U24: 0.10917335 | V24: 0.10761062 | W24: 0.088440279 | X24: 0.096981374 | Y24: 1 | Z24: =IF(OR(Y24="",F24="",F24=0),"",Y24/F24) | AA24: 1.221 | AB24: -0.045 | AC24: 0.095209095 | AD24: =IF(OR(Q24="",M24="",M24<=0),"",ROUND(40*MAX(0,MIN(N(Q24)/0.3,1))+IF(OR(R24="",N(Q24)<=0),10,20*MAX(0,1-MIN(R24/Q24,1)))+30*MAX(0,MIN((PARAMETRI!$B$5-M24)/MAX(PARAMETRI!$B$5-10,1),1))+IF(AB24="",3,10*MAX(0,MIN(AB24/0.15,1)))+IF(AND(P24<>"",N(P24)<N(Q24)*0.6),-8,0),1)) | AE24: =IF(AND(P24="",Q24=""),"DATI MANCANTI",IF(AND(N(P24)>=PARAMETRI!$B$4,N(Q24)>=PARAMETRI!$B$4),"OK","NO")) | AF24: =IF(M24="","N/D",IF(M24<PARAMETRI!$B$6,"OTTIMO",IF(M24<PARAMETRI!$B$5,"OK","NO"))) | AG24: =IF(OR(AE24="DATI MANCANTI",AF24="N/D"),"DA COMPLETARE",IF(AND(AE24="OK",AF24="OTTIMO"),"PASSA FORTE",IF(AND(AE24="OK",AF24="OK"),"PASSA","SCARTA"))) | AH24: 2026-10-12 | AI24: yahoo
A25: =IF(AD25="","",RANK(AD25,AD$2:AD$44)) | B25: Infineon Technologies | C25: IFX.DE | D25: Semiconduttori | E25: Tecnologia | F25: 57.22 | G25: EUR | H25: 57.22 | I25: 74357.4 | J25: 74357.4 | K25: 0.89 | L25: 2.8557 | M25: =IF(OR(F25="",K25="",K25<=0),"",F25/K25) | N25: 4.282293 | O25: =IF(OR(N25="",M25="",M25<=0),"",N25/M25) | P25: 0.07019 | Q25: 0.11623686 | R25: 0.05085412 | S25: 4 | U25: 0.0595273 | V25: 0.075556072 | W25: 0.18405304 | X25: 0.14581103 | Y25: 0.35 | Z25: =IF(OR(Y25="",F25="",F25=0),"",Y25/F25) | AA25: 40.183 | AB25: 0.126 | AC25: 0.082117037 | AD25: =IF(OR(Q25="",M25="",M25<=0),"",ROUND(40*MAX(0,MIN(N(Q25)/0.3,1))+IF(OR(R25="",N(Q25)<=0),10,20*MAX(0,1-MIN(R25/Q25,1)))+30*MAX(0,MIN((PARAMETRI!$B$5-M25)/MAX(PARAMETRI!$B$5-10,1),1))+IF(AB25="",3,10*MAX(0,MIN(AB25/0.15,1)))+IF(AND(P25<>"",N(P25)<N(Q25)*0.6),-8,0),1)) | AE25: =IF(AND(P25="",Q25=""),"DATI MANCANTI",IF(AND(N(P25)>=PARAMETRI!$B$4,N(Q25)>=PARAMETRI!$B$4),"OK","NO")) | AF25: =IF(M25="","N/D",IF(M25<PARAMETRI!$B$6,"OTTIMO",IF(M25<PARAMETRI!$B$5,"OK","NO"))) | AG25: =IF(OR(AE25="DATI MANCANTI",AF25="N/D"),"DA COMPLETARE",IF(AND(AE25="OK",AF25="OTTIMO"),"PASSA FORTE",IF(AND(AE25="OK",AF25="OK"),"PASSA","SCARTA"))) | AH25: 2026-10-12 | AI25: yahoo
A26: =IF(AD26="","",RANK(AD26,AD$2:AD$44)) | B26: Merck KGaA | C26: MRK.DE | D26: Farmaceutica | E26: Salute | F26: 138.65 | G26: EUR | H26: 138.65 | I26: 60282 | J26: 60282 | K26: 5.36 | L26: 8.9146 | M26: =IF(OR(F26="",K26="",K26<=0),"",F26/K26) | N26: 1.9926702 | O26: =IF(OR(N26="",M26="",M26<=0),"",N26/M26) | P26: 0.08134 | Q26: 0.10454436 | R26: 0.014833097 | S26: 4 | U26: 0.091214326 | V26: 0.092832787 | W26: 0.10584708 | X26: 0.12828326 | Y26: 2.2 | Z26: =IF(OR(Y26="",F26="",F26=0),"",Y26/F26) | AA26: 40.618 | AB26: 0.034 | AC26: 0.11231162 | AD26: =IF(OR(Q26="",M26="",M26<=0),"",ROUND(40*MAX(0,MIN(N(Q26)/0.3,1))+IF(OR(R26="",N(Q26)<=0),10,20*MAX(0,1-MIN(R26/Q26,1)))+30*MAX(0,MIN((PARAMETRI!$B$5-M26)/MAX(PARAMETRI!$B$5-10,1),1))+IF(AB26="",3,10*MAX(0,MIN(AB26/0.15,1)))+IF(AND(P26<>"",N(P26)<N(Q26)*0.6),-8,0),1)) | AE26: =IF(AND(P26="",Q26=""),"DATI MANCANTI",IF(AND(N(P26)>=PARAMETRI!$B$4,N(Q26)>=PARAMETRI!$B$4),"OK","NO")) | AF26: =IF(M26="","N/D",IF(M26<PARAMETRI!$B$6,"OTTIMO",IF(M26<PARAMETRI!$B$5,"OK","NO"))) | AG26: =IF(OR(AE26="DATI MANCANTI",AF26="N/D"),"DA COMPLETARE",IF(AND(AE26="OK",AF26="OTTIMO"),"PASSA FORTE",IF(AND(AE26="OK",AF26="OK"),"PASSA","SCARTA"))) | AH26: 2026-10-12 | AI26: yahoo
A27: =IF(AD27="","",RANK(AD27,AD$2:AD$44)) | B27: Siemens Healthineers | C27: SHL.DE | D27: Dispositivi medicali | E27: Salute | F27: 39.63 | G27: EUR | H27: 39.63 | I27: 44353.9 | J27: 44353.9 | K27: 2 | L27: 2.37895 | M27: =IF(OR(F27="",K27="",K27<=0),"",F27/K27) | N27: 2.313215 | O27: =IF(OR(N27="",M27="",M27<=0),"",N27/M27) | P27: 0.12147 | Q27: 0.097636474 | R27: 0.010155796 | S27: 3 | V27: 0.10670916 | W27: 0.083457773 | X27: 0.10274249 | Y27: 1 | Z27: =IF(OR(Y27="",F27="",F27=0),"",Y27/F27) | AA27: 78.296 | AB27: 0.018 | AC27: 0.098958098 | AD27: =IF(OR(Q27="",M27="",M27<=0),"",ROUND(40*MAX(0,MIN(N(Q27)/0.3,1))+IF(OR(R27="",N(Q27)<=0),10,20*MAX(0,1-MIN(R27/Q27,1)))+30*MAX(0,MIN((PARAMETRI!$B$5-M27)/MAX(PARAMETRI!$B$5-10,1),1))+IF(AB27="",3,10*MAX(0,MIN(AB27/0.15,1)))+IF(AND(P27<>"",N(P27)<N(Q27)*0.6),-8,0),1)) | AE27: =IF(AND(P27="",Q27=""),"DATI MANCANTI",IF(AND(N(P27)>=PARAMETRI!$B$4,N(Q27)>=PARAMETRI!$B$4),"OK","NO")) | AF27: =IF(M27="","N/D",IF(M27<PARAMETRI!$B$6,"OTTIMO",IF(M27<PARAMETRI!$B$5,"OK","NO"))) | AG27: =IF(OR(AE27="DATI MANCANTI",AF27="N/D"),"DA COMPLETARE",IF(AND(AE27="OK",AF27="OTTIMO"),"PASSA FORTE",IF(AND(AE27="OK",AF27="OK"),"PASSA","SCARTA"))) | AH27: 2026-10-12 | AI27: yahoo
A28: =IF(AD28="","",RANK(AD28,AD$2:AD$44)) | B28: SAP | C28: SAP.DE | D28: Software | E28: Tecnologia | F28: 194.46 | G28: EUR | H28: 194.46 | I28: 224446.6 | J28: 224446.6 | K28: 6.82 | L28: 8.37308 | M28: =IF(OR(F28="",K28="",K28<=0),"",F28/K28) | N28: 5.016381 | O28: =IF(OR(N28="",M28="",M28<=0),"",N28/M28) | P28: 0.18320999 | Q28: 0.10711194 | R28: 0.044988325 | S28: 4 | U28: 0.16061095 | V28: 0.068753026 | W28: 0.14224807 | X28: 0.056835714 | Y28: 2.5 | Z28: =IF(OR(Y28="",F28="",F28=0),"",Y28/F28) | AA28: 21.966 | AB28: 0.094 | AC28: 0.21184782 | AD28: =IF(OR(Q28="",M28="",M28<=0),"",ROUND(40*MAX(0,MIN(N(Q28)/0.3,1))+IF(OR(R28="",N(Q28)<=0),10,20*MAX(0,1-MIN(R28/Q28,1)))+30*MAX(0,MIN((PARAMETRI!$B$5-M28)/MAX(PARAMETRI!$B$5-10,1),1))+IF(AB28="",3,10*MAX(0,MIN(AB28/0.15,1)))+IF(AND(P28<>"",N(P28)<N(Q28)*0.6),-8,0),1)) | AE28: =IF(AND(P28="",Q28=""),"DATI MANCANTI",IF(AND(N(P28)>=PARAMETRI!$B$4,N(Q28)>=PARAMETRI!$B$4),"OK","NO")) | AF28: =IF(M28="","N/D",IF(M28<PARAMETRI!$B$6,"OTTIMO",IF(M28<PARAMETRI!$B$5,"OK","NO"))) | AG28: =IF(OR(AE28="DATI MANCANTI",AF28="N/D"),"DA COMPLETARE",IF(AND(AE28="OK",AF28="OTTIMO"),"PASSA FORTE",IF(AND(AE28="OK",AF28="OK"),"PASSA","SCARTA"))) | AH28: 2026-10-12 | AI28: yahoo
A29: =IF(AD29="","",RANK(AD29,AD$2:AD$44)) | B29: MTU Aero Engines | C29: MTX.DE | D29: Aerospazio | E29: Industriale | F29: 350.7 | G29: EUR | H29: 350.7 | I29: 18892.4 | J29: 18892.4 | K29: 17.14 | L29: 20.57896 | M29: =IF(OR(F29="",K29="",K29<=0),"",F29/K29) | N29: 4.158564 | O29: =IF(OR(N29="",M29="",M29<=0),"",N29/M29) | P29: 0.22635001 | Q29: 0.12430176 | R29: 0.10278901 | S29: 4 | U29: 0.23551229 | V29: 0.1882248 | W29: -0.035626965 | X29: 0.1090969 | Y29: 3.6 | Z29: =IF(OR(Y29="",F29="",F29=0),"",Y29/F29) | AA29: 55.565 | AB29: 0.167 | AC29: 0.10749743 | AD29: =IF(OR(Q29="",M29="",M29<=0),"",ROUND(40*MAX(0,MIN(N(Q29)/0.3,1))+IF(OR(R29="",N(Q29)<=0),10,20*MAX(0,1-MIN(R29/Q29,1)))+30*MAX(0,MIN((PARAMETRI!$B$5-M29)/MAX(PARAMETRI!$B$5-10,1),1))+IF(AB29="",3,10*MAX(0,MIN(AB29/0.15,1)))+IF(AND(P29<>"",N(P29)<N(Q29)*0.6),-8,0),1)) | AE29: =IF(AND(P29="",Q29=""),"DATI MANCANTI",IF(AND(N(P29)>=PARAMETRI!$B$4,N(Q29)>=PARAMETRI!$B$4),"OK","NO")) | AF29: =IF(M29="","N/D",IF(M29<PARAMETRI!$B$6,"OTTIMO",IF(M29<PARAMETRI!$B$5,"OK","NO"))) | AG29: =IF(OR(AE29="DATI MANCANTI",AF29="N/D"),"DA COMPLETARE",IF(AND(AE29="OK",AF29="OTTIMO"),"PASSA FORTE",IF(AND(AE29="OK",AF29="OK"),"PASSA","SCARTA"))) | AH29: 2026-10-12 | AI29: yahoo
A30: =IF(AD30="","",RANK(AD30,AD$2:AD$44)) | B30: Daimler Truck | C30: DTG.DE | D30: Veicoli industriali | E30: Industriale | F30: 41 | G30: EUR | H30: 41 | I30: 31168.7 | J30: 31168.7 | K30: 1.46 | L30: 4.77244 | M30: =IF(OR(F30="",K30="",K30<=0),"",F30/K30) | N30: 1.3809363 | O30: =IF(OR(N30="",M30="",M30<=0),"",N30/M30) | P30: 0.05047 | Q30: 0.13241014 | R30: 0.02947709 | S30: 4 | U30: 0.09140683 | V30: 0.13060122 | W30: 0.17472807 | X30: 0.13290445 | Y30: 1.9 | Z30: =IF(OR(Y30="",F30="",F30=0),"",Y30/F30) | AA30: 127.015 | AB30: 0.053 | AC30: 0.023676697 | AD30: =IF(OR(Q30="",M30="",M30<=0),"",ROUND(40*MAX(0,MIN(N(Q30)/0.3,1))+IF(OR(R30="",N(Q30)<=0),10,20*MAX(0,1-MIN(R30/Q30,1)))+30*MAX(0,MIN((PARAMETRI!$B$5-M30)/MAX(PARAMETRI!$B$5-10,1),1))+IF(AB30="",3,10*MAX(0,MIN(AB30/0.15,1)))+IF(AND(P30<>"",N(P30)<N(Q30)*0.6),-8,0),1)) | AE30: =IF(AND(P30="",Q30=""),"DATI MANCANTI",IF(AND(N(P30)>=PARAMETRI!$B$4,N(Q30)>=PARAMETRI!$B$4),"OK","NO")) | AF30: =IF(M30="","N/D",IF(M30<PARAMETRI!$B$6,"OTTIMO",IF(M30<PARAMETRI!$B$5,"OK","NO"))) | AG30: =IF(OR(AE30="DATI MANCANTI",AF30="N/D"),"DA COMPLETARE",IF(AND(AE30="OK",AF30="OTTIMO"),"PASSA FORTE",IF(AND(AE30="OK",AF30="OK"),"PASSA","SCARTA"))) | AH30: 2026-10-12 | AI30: yahoo
A31: =IF(AD31="","",RANK(AD31,AD$2:AD$44)) | B31: Symrise | C31: SY1.DE | D31: Aromi e fragranze | E31: Materiali | F31: 93.26 | G31: EUR | H31: 93.26 | I31: 12793.4 | J31: 12793.4 | K31: 1.77 | L31: 4.3862 | M31: =IF(OR(F31="",K31="",K31<=0),"",F31/K31) | N31: 3.426409 | O31: =IF(OR(N31="",M31="",M31<=0),"",N31/M31) | P31: 0.06708 | Q31: 0.089939743 | R31: 0.019833058 | S31: 4 | U31: 0.067031703 | V31: 0.12012117 | W31: 0.09376136 | X31: 0.078844739 | Y31: 1.25 | Z31: =IF(OR(Y31="",F31="",F31=0),"",Y31/F31) | AA31: 60.613 | AB31: -0.006 | AC31: 0.049922474 | AD31: =IF(OR(Q31="",M31="",M31<=0),"",ROUND(40*MAX(0,MIN(N(Q31)/0.3,1))+IF(OR(R31="",N(Q31)<=0),10,20*MAX(0,1-MIN(R31/Q31,1)))+30*MAX(0,MIN((PARAMETRI!$B$5-M31)/MAX(PARAMETRI!$B$5-10,1),1))+IF(AB31="",3,10*MAX(0,MIN(AB31/0.15,1)))+IF(AND(P31<>"",N(P31)<N(Q31)*0.6),-8,0),1)) | AE31: =IF(AND(P31="",Q31=""),"DATI MANCANTI",IF(AND(N(P31)>=PARAMETRI!$B$4,N(Q31)>=PARAMETRI!$B$4),"OK","NO")) | AF31: =IF(M31="","N/D",IF(M31<PARAMETRI!$B$6,"OTTIMO",IF(M31<PARAMETRI!$B$5,"OK","NO"))) | AG31: =IF(OR(AE31="DATI MANCANTI",AF31="N/D"),"DA COMPLETARE",IF(AND(AE31="OK",AF31="OTTIMO"),"PASSA FORTE",IF(AND(AE31="OK",AF31="OK"),"PASSA","SCARTA"))) | AH31: 2026-10-12 | AI31: yahoo
A32: =IF(AD32="","",RANK(AD32,AD$2:AD$44)) | B32: Zalando | C32: ZAL.DE | D32: E-commerce | E32: Consumi | F32: 24.14 | G32: EUR | H32: 24.14 | I32: 5895.5 | J32: 5895.5 | K32: 0.39 | L32: 1.85536 | M32: =IF(OR(F32="",K32="",K32<=0),"",F32/K32) | N32: 2.3427794 | O32: =IF(OR(N32="",M32="",M32<=0),"",N32/M32) | P32: 0.0345 | Q32: 0.053236328 | R32: 0.033967399 | S32: 4 | U32: 0.076120037 | V32: 0.094210783 | W32: 0.034975349 | X32: 0.0076391415 | Z32: =IF(OR(Y32="",F32="",F32=0),"",Y32/F32) | AA32: 53.379 | AB32: 0.208 | AC32: 0.007678476 | AD32: =IF(OR(Q32="",M32="",M32<=0),"",ROUND(40*MAX(0,MIN(N(Q32)/0.3,1))+IF(OR(R32="",N(Q32)<=0),10,20*MAX(0,1-MIN(R32/Q32,1)))+30*MAX(0,MIN((PARAMETRI!$B$5-M32)/MAX(PARAMETRI!$B$5-10,1),1))+IF(AB32="",3,10*MAX(0,MIN(AB32/0.15,1)))+IF(AND(P32<>"",N(P32)<N(Q32)*0.6),-8,0),1)) | AE32: =IF(AND(P32="",Q32=""),"DATI MANCANTI",IF(AND(N(P32)>=PARAMETRI!$B$4,N(Q32)>=PARAMETRI!$B$4),"OK","NO")) | AF32: =IF(M32="","N/D",IF(M32<PARAMETRI!$B$6,"OTTIMO",IF(M32<PARAMETRI!$B$5,"OK","NO"))) | AG32: =IF(OR(AE32="DATI MANCANTI",AF32="N/D"),"DA COMPLETARE",IF(AND(AE32="OK",AF32="OTTIMO"),"PASSA FORTE",IF(AND(AE32="OK",AF32="OK"),"PASSA","SCARTA"))) | AH32: 2026-10-12 | AI32: yahoo
A33: =IF(AD33="","",RANK(AD33,AD$2:AD$44)) | B33: Porsche AG | C33: P911.DE | D33: Auto di lusso | E33: Consumi | F33: 42.2 | G33: EUR | H33: 42.2 | I33: 38444.2 | J33: 38444.2 | K33: 0.9 | L33: 1.89195 | M33: =IF(OR(F33="",K33="",K33<=0),"",F33/K33) | N33: 1.6821462 | O33: =IF(OR(N33="",M33="",M33<=0),"",N33/M33) | P33: 0.02861 | Q33: 0.17598568 | R33: 0.10280249 | S33: 4 | U33: 0.018746466 | V33: 0.15588248 | W33: 0.23801172 | X33: 0.29130205 | Y33: 1.01 | Z33: =IF(OR(Y33="",F33="",F33=0),"",Y33/F33) | AA33: 50.953 | AB33: -0.051 | AC33: 0.023242349 | AD33: =IF(OR(Q33="",M33="",M33<=0),"",ROUND(40*MAX(0,MIN(N(Q33)/0.3,1))+IF(OR(R33="",N(Q33)<=0),10,20*MAX(0,1-MIN(R33/Q33,1)))+30*MAX(0,MIN((PARAMETRI!$B$5-M33)/MAX(PARAMETRI!$B$5-10,1),1))+IF(AB33="",3,10*MAX(0,MIN(AB33/0.15,1)))+IF(AND(P33<>"",N(P33)<N(Q33)*0.6),-8,0),1)) | AE33: =IF(AND(P33="",Q33=""),"DATI MANCANTI",IF(AND(N(P33)>=PARAMETRI!$B$4,N(Q33)>=PARAMETRI!$B$4),"OK","NO")) | AF33: =IF(M33="","N/D",IF(M33<PARAMETRI!$B$6,"OTTIMO",IF(M33<PARAMETRI!$B$5,"OK","NO"))) | AG33: =IF(OR(AE33="DATI MANCANTI",AF33="N/D"),"DA COMPLETARE",IF(AND(AE33="OK",AF33="OTTIMO"),"PASSA FORTE",IF(AND(AE33="OK",AF33="OK"),"PASSA","SCARTA"))) | AH33: 2026-10-12 | AI33: yahoo
A34: =IF(AD34="","",RANK(AD34,AD$2:AD$44)) | B34: Qiagen | C34: QIA.DE | D34: Diagnostica | E34: Salute | F34: 40.535 | G34: EUR | H34: 40.535 | I34: 8370.3 | J34: 8370.3 | K34: 1.66 | L34: 2.27313 | M34: =IF(OR(F34="",K34="",K34<=0),"",F34/K34) | N34: 2.8058667 | O34: =IF(OR(N34="",M34="",M34<=0),"",N34/M34) | P34: 0.11928 | Q34: 0.086901212 | R34: 0.038492072 | S34: 4 | U34: 0.11245704 | V34: 0.023432312 | W34: 0.089633444 | X34: 0.12208206 | Y34: 0.31 | Z34: =IF(OR(Y34="",F34="",F34=0),"",Y34/F34) | AA34: 49.25 | AB34: 0.003 | AC34: 0.19584507 | AD34: =IF(OR(Q34="",M34="",M34<=0),"",ROUND(40*MAX(0,MIN(N(Q34)/0.3,1))+IF(OR(R34="",N(Q34)<=0),10,20*MAX(0,1-MIN(R34/Q34,1)))+30*MAX(0,MIN((PARAMETRI!$B$5-M34)/MAX(PARAMETRI!$B$5-10,1),1))+IF(AB34="",3,10*MAX(0,MIN(AB34/0.15,1)))+IF(AND(P34<>"",N(P34)<N(Q34)*0.6),-8,0),1)) | AE34: =IF(AND(P34="",Q34=""),"DATI MANCANTI",IF(AND(N(P34)>=PARAMETRI!$B$4,N(Q34)>=PARAMETRI!$B$4),"OK","NO")) | AF34: =IF(M34="","N/D",IF(M34<PARAMETRI!$B$6,"OTTIMO",IF(M34<PARAMETRI!$B$5,"OK","NO"))) | AG34: =IF(OR(AE34="DATI MANCANTI",AF34="N/D"),"DA COMPLETARE",IF(AND(AE34="OK",AF34="OTTIMO"),"PASSA FORTE",IF(AND(AE34="OK",AF34="OK"),"PASSA","SCARTA"))) | AH34: 2026-10-12 | AI34: yahoo
A35: =IF(AD35="","",RANK(AD35,AD$2:AD$44)) | B35: Fresenius | C35: FRE.DE | D35: Servizi sanitari | E35: Salute | F35: 43 | G35: EUR | H35: 43 | I35: 24219.2 | J35: 24219.2 | K35: 2.71 | L35: 3.95467 | M35: =IF(OR(F35="",K35="",K35<=0),"",F35/K35) | N35: 1.2294496 | O35: =IF(OR(N35="",M35="",M35<=0),"",N35/M35) | P35: 0.08287 | Q35: 0.031551693 | R35: 0.040220102 | S35: 4 | U35: 0.066164154 | V35: 0.024101934 | W35: -0.031264803 | X35: 0.067205486 | Y35: 1.05 | Z35: =IF(OR(Y35="",F35="",F35=0),"",Y35/F35) | AA35: 55.978 | AB35: 0.052 | AC35: 0.068333846 | AD35: =IF(OR(Q35="",M35="",M35<=0),"",ROUND(40*MAX(0,MIN(N(Q35)/0.3,1))+IF(OR(R35="",N(Q35)<=0),10,20*MAX(0,1-MIN(R35/Q35,1)))+30*MAX(0,MIN((PARAMETRI!$B$5-M35)/MAX(PARAMETRI!$B$5-10,1),1))+IF(AB35="",3,10*MAX(0,MIN(AB35/0.15,1)))+IF(AND(P35<>"",N(P35)<N(Q35)*0.6),-8,0),1)) | AE35: =IF(AND(P35="",Q35=""),"DATI MANCANTI",IF(AND(N(P35)>=PARAMETRI!$B$4,N(Q35)>=PARAMETRI!$B$4),"OK","NO")) | AF35: =IF(M35="","N/D",IF(M35<PARAMETRI!$B$6,"OTTIMO",IF(M35<PARAMETRI!$B$5,"OK","NO"))) | AG35: =IF(OR(AE35="DATI MANCANTI",AF35="N/D"),"DA COMPLETARE",IF(AND(AE35="OK",AF35="OTTIMO"),"PASSA FORTE",IF(AND(AE35="OK",AF35="OK"),"PASSA","SCARTA"))) | AH35: 2026-10-12 | AI35: yahoo
A36: =IF(AD36="","",RANK(AD36,AD$2:AD$44)) | B36: Siemens Energy | C36: ENR.DE | D36: Elettrificazione / Energia | E36: Industriale | F36: 146.78 | G36: EUR | H36: 146.78 | I36: 124887.6 | J36: 124887.6 | K36: 3.14 | L36: 6.24953 | M36: =IF(OR(F36="",K36="",K36<=0),"",F36/K36) | N36: 11.642737 | O36: =IF(OR(N36="",M36="",M36<=0),"",N36/M36) | P36: 0.27749002 | Q36: -0.073131666 | R36: 0.27353797 | S36: 4 | U36: 0.13726823 | V36: 0.13046832 | W36: -0.53298836 | X36: -0.027274851 | Y36: 0.7 | Z36: =IF(OR(Y36="",F36="",F36=0),"",Y36/F36) | AA36: 26.488 | AB36: 0.175 | AC36: 0.068889628 | AD36: =IF(OR(Q36="",M36="",M36<=0),"",ROUND(40*MAX(0,MIN(N(Q36)/0.3,1))+IF(OR(R36="",N(Q36)<=0),10,20*MAX(0,1-MIN(R36/Q36,1)))+30*MAX(0,MIN((PARAMETRI!$B$5-M36)/MAX(PARAMETRI!$B$5-10,1),1))+IF(AB36="",3,10*MAX(0,MIN(AB36/0.15,1)))+IF(AND(P36<>"",N(P36)<N(Q36)*0.6),-8,0),1)) | AE36: =IF(AND(P36="",Q36=""),"DATI MANCANTI",IF(AND(N(P36)>=PARAMETRI!$B$4,N(Q36)>=PARAMETRI!$B$4),"OK","NO")) | AF36: =IF(M36="","N/D",IF(M36<PARAMETRI!$B$6,"OTTIMO",IF(M36<PARAMETRI!$B$5,"OK","NO"))) | AG36: =IF(OR(AE36="DATI MANCANTI",AF36="N/D"),"DA COMPLETARE",IF(AND(AE36="OK",AF36="OTTIMO"),"PASSA FORTE",IF(AND(AE36="OK",AF36="OK"),"PASSA","SCARTA"))) | AH36: 2026-10-12 | AI36: yahoo
A37: =IF(AD37="","",RANK(AD37,AD$2:AD$44)) | B37: Porsche Automobil Holding | C37: PAH3.DE | D37: Holding | E37: Finanziario | F37: 25.17 | G37: EUR | H37: 25.17 | I37: 7708.3 | J37: 7708.3 | K37: 0.31 | L37: 13.85479 | M37: =IF(OR(F37="",K37="",K37<=0),"",F37/K37) | N37: 0.21576259 | O37: =IF(OR(N37="",M37="",M37<=0),"",N37/M37) | P37: 0.0027 | Q37: -0.075656646 | R37: 0.28577594 | S37: 4 | U37: 0.070100748 | V37: -0.57015495 | W37: 0.0920938 | X37: 0.10533382 | Y37: 1.51 | Z37: =IF(OR(Y37="",F37="",F37=0),"",Y37/F37) | AA37: 19.333 | AC37: 0.034633613 | AD37: =IF(OR(Q37="",M37="",M37<=0),"",ROUND(40*MAX(0,MIN(N(Q37)/0.3,1))+IF(OR(R37="",N(Q37)<=0),10,20*MAX(0,1-MIN(R37/Q37,1)))+30*MAX(0,MIN((PARAMETRI!$B$5-M37)/MAX(PARAMETRI!$B$5-10,1),1))+IF(AB37="",3,10*MAX(0,MIN(AB37/0.15,1)))+IF(AND(P37<>"",N(P37)<N(Q37)*0.6),-8,0),1)) | AE37: =IF(AND(P37="",Q37=""),"DATI MANCANTI",IF(AND(N(P37)>=PARAMETRI!$B$4,N(Q37)>=PARAMETRI!$B$4),"OK","NO")) | AF37: =IF(M37="","N/D",IF(M37<PARAMETRI!$B$6,"OTTIMO",IF(M37<PARAMETRI!$B$5,"OK","NO"))) | AG37: =IF(OR(AE37="DATI MANCANTI",AF37="N/D"),"DA COMPLETARE",IF(AND(AE37="OK",AF37="OTTIMO"),"PASSA FORTE",IF(AND(AE37="OK",AF37="OK"),"PASSA","SCARTA"))) | AH37: 2026-10-12 | AI37: yahoo
A38: =IF(AD38="","",RANK(AD38,AD$2:AD$44)) | B38: Sartorius VZ | C38: SRT3.DE | D38: Strumentazione life science | E38: Salute | F38: 253 | G38: EUR | H38: 253 | I38: 17470.2 | J38: 17470.2 | K38: 2.83 | L38: 6.33119 | M38: =IF(OR(F38="",K38="",K38<=0),"",F38/K38) | N38: 6.454246 | O38: =IF(OR(N38="",M38="",M38<=0),"",N38/M38) | P38: 0.07179 | Q38: 0.13195639 | R38: 0.1230555 | S38: 4 | U38: 0.057226245 | V38: 0.030381944 | W38: 0.099429345 | X38: 0.34078802 | Y38: 0.74 | Z38: =IF(OR(Y38="",F38="",F38=0),"",Y38/F38) | AA38: 101.366 | AB38: 0.031 | AC38: 0.055425228 | AD38: =IF(OR(Q38="",M38="",M38<=0),"",ROUND(40*MAX(0,MIN(N(Q38)/0.3,1))+IF(OR(R38="",N(Q38)<=0),10,20*MAX(0,1-MIN(R38/Q38,1)))+30*MAX(0,MIN((PARAMETRI!$B$5-M38)/MAX(PARAMETRI!$B$5-10,1),1))+IF(AB38="",3,10*MAX(0,MIN(AB38/0.15,1)))+IF(AND(P38<>"",N(P38)<N(Q38)*0.6),-8,0),1)) | AE38: =IF(AND(P38="",Q38=""),"DATI MANCANTI",IF(AND(N(P38)>=PARAMETRI!$B$4,N(Q38)>=PARAMETRI!$B$4),"OK","NO")) | AF38: =IF(M38="","N/D",IF(M38<PARAMETRI!$B$6,"OTTIMO",IF(M38<PARAMETRI!$B$5,"OK","NO"))) | AG38: =IF(OR(AE38="DATI MANCANTI",AF38="N/D"),"DA COMPLETARE",IF(AND(AE38="OK",AF38="OTTIMO"),"PASSA FORTE",IF(AND(AE38="OK",AF38="OK"),"PASSA","SCARTA"))) | AH38: 2026-10-12 | AI38: yahoo
A39: =IF(AD39="","",RANK(AD39,AD$2:AD$44)) | B39: BASF | C39: BAS.DE | D39: Chimica di base | E39: Materiali | F39: 51.27 | G39: EUR | H39: 51.27 | I39: 45339.4 | J39: 45339.4 | K39: 2.42 | L39: 2.96074 | M39: =IF(OR(F39="",K39="",K39<=0),"",F39/K39) | N39: 1.2241536 | O39: =IF(OR(N39="",M39="",M39<=0),"",N39/M39) | P39: 0.061160002 | Q39: 0.018942383 | R39: 0.025321965 | S39: 4 | U39: 0.048773875 | V39: 0.036461698 | W39: 0.0063780934 | X39: -0.015844136 | Y39: 2.25 | Z39: =IF(OR(Y39="",F39="",F39=0),"",Y39/F39) | AA39: 71.358 | AB39: 0.164 | AC39: 0.03505096 | AD39: =IF(OR(Q39="",M39="",M39<=0),"",ROUND(40*MAX(0,MIN(N(Q39)/0.3,1))+IF(OR(R39="",N(Q39)<=0),10,20*MAX(0,1-MIN(R39/Q39,1)))+30*MAX(0,MIN((PARAMETRI!$B$5-M39)/MAX(PARAMETRI!$B$5-10,1),1))+IF(AB39="",3,10*MAX(0,MIN(AB39/0.15,1)))+IF(AND(P39<>"",N(P39)<N(Q39)*0.6),-8,0),1)) | AE39: =IF(AND(P39="",Q39=""),"DATI MANCANTI",IF(AND(N(P39)>=PARAMETRI!$B$4,N(Q39)>=PARAMETRI!$B$4),"OK","NO")) | AF39: =IF(M39="","N/D",IF(M39<PARAMETRI!$B$6,"OTTIMO",IF(M39<PARAMETRI!$B$5,"OK","NO"))) | AG39: =IF(OR(AE39="DATI MANCANTI",AF39="N/D"),"DA COMPLETARE",IF(AND(AE39="OK",AF39="OTTIMO"),"PASSA FORTE",IF(AND(AE39="OK",AF39="OK"),"PASSA","SCARTA"))) | AH39: 2026-10-12 | AI39: yahoo
A40: =IF(AD40="","",RANK(AD40,AD$2:AD$44)) | B40: Bayer | C40: BAYN.DE | D40: Farmaceutica / Agrochimica | E40: Salute | F40: 43.83 | G40: EUR | H40: 43.83 | I40: 43059.7 | J40: 43059.7 | K40: -1.75 | L40: 4.83607 | M40: =IF(OR(F40="",K40="",K40<=0),"",F40/K40) | N40: 1.4555175 | O40: =IF(OR(N40="",M40="",M40<=0),"",N40/M40) | P40: -0.056900002 | Q40: -0.050445165 | R40: 0.093696821 | S40: 4 | U40: -0.13951517 | V40: -0.079979942 | W40: -0.089318796 | X40: 0.10703324 | Y40: 0.11 | Z40: =IF(OR(Y40="",F40="",F40=0),"",Y40/F40) | AA40: 129.362 | AB40: 0.012 | AC40: -0.038134942 | AD40: =IF(OR(Q40="",M40="",M40<=0),"",ROUND(40*MAX(0,MIN(N(Q40)/0.3,1))+IF(OR(R40="",N(Q40)<=0),10,20*MAX(0,1-MIN(R40/Q40,1)))+30*MAX(0,MIN((PARAMETRI!$B$5-M40)/MAX(PARAMETRI!$B$5-10,1),1))+IF(AB40="",3,10*MAX(0,MIN(AB40/0.15,1)))+IF(AND(P40<>"",N(P40)<N(Q40)*0.6),-8,0),1)) | AE40: =IF(AND(P40="",Q40=""),"DATI MANCANTI",IF(AND(N(P40)>=PARAMETRI!$B$4,N(Q40)>=PARAMETRI!$B$4),"OK","NO")) | AF40: =IF(M40="","N/D",IF(M40<PARAMETRI!$B$6,"OTTIMO",IF(M40<PARAMETRI!$B$5,"OK","NO"))) | AG40: =IF(OR(AE40="DATI MANCANTI",AF40="N/D"),"DA COMPLETARE",IF(AND(AE40="OK",AF40="OTTIMO"),"PASSA FORTE",IF(AND(AE40="OK",AF40="OK"),"PASSA","SCARTA"))) | AH40: 2026-10-12 | AI40: yahoo
A41: =IF(AD41="","",RANK(AD41,AD$2:AD$44)) | B41: Continental | C41: CON.DE | D41: Componentistica auto | E41: Industriale | F41: 68.6 | G41: EUR | H41: 68.6 | I41: 13720.4 | J41: 13720.4 | K41: -2.31 | L41: 6.564 | M41: =IF(OR(F41="",K41="",K41<=0),"",F41/K41) | N41: 3.2651117 | O41: =IF(OR(N41="",M41="",M41<=0),"",N41/M41) | P41: -0.08303001 | Q41: 0.032249145 | R41: 0.053369638 | S41: 4 | U41: -0.041942044 | V41: 0.081388057 | W41: 0.08452764 | X41: 0.0050229275 | Y41: 2.7 | Z41: =IF(OR(Y41="",F41="",F41=0),"",Y41/F41) | AA41: 156.749 | AB41: -0.113 | AC41: -0.021294979 | AD41: =IF(OR(Q41="",M41="",M41<=0),"",ROUND(40*MAX(0,MIN(N(Q41)/0.3,1))+IF(OR(R41="",N(Q41)<=0),10,20*MAX(0,1-MIN(R41/Q41,1)))+30*MAX(0,MIN((PARAMETRI!$B$5-M41)/MAX(PARAMETRI!$B$5-10,1),1))+IF(AB41="",3,10*MAX(0,MIN(AB41/0.15,1)))+IF(AND(P41<>"",N(P41)<N(Q41)*0.6),-8,0),1)) | AE41: =IF(AND(P41="",Q41=""),"DATI MANCANTI",IF(AND(N(P41)>=PARAMETRI!$B$4,N(Q41)>=PARAMETRI!$B$4),"OK","NO")) | AF41: =IF(M41="","N/D",IF(M41<PARAMETRI!$B$6,"OTTIMO",IF(M41<PARAMETRI!$B$5,"OK","NO"))) | AG41: =IF(OR(AE41="DATI MANCANTI",AF41="N/D"),"DA COMPLETARE",IF(AND(AE41="OK",AF41="OTTIMO"),"PASSA FORTE",IF(AND(AE41="OK",AF41="OK"),"PASSA","SCARTA"))) | AH41: 2026-10-12 | AI41: yahoo
A42: =IF(AD42="","",RANK(AD42,AD$2:AD$44)) | B42: Covestro | C42: 1COV.DE | D42: Chimica specialistica | E42: Materiali | F42: 59.98 | G42: EUR | H42: 59.98 | I42: 11320.6 | J42: 11320.6 | K42: -2.43 | L42: 0.96744 | M42: =IF(OR(F42="",K42="",K42<=0),"",F42/K42) | N42: 1.700933 | O42: =IF(OR(N42="",M42="",M42<=0),"",N42/M42) | P42: -0.0444 | Q42: -0.050102326 | R42: 0.024495957 | S42: 4 | U42: -0.092026293 | V42: -0.039951938 | W42: -0.030045524 | X42: -0.038385549 | Z42: =IF(OR(Y42="",F42="",F42=0),"",Y42/F42) | AA42: 38.504 | AB42: -0.004 | AC42: -0.023566682 | AD42: =IF(OR(Q42="",M42="",M42<=0),"",ROUND(40*MAX(0,MIN(N(Q42)/0.3,1))+IF(OR(R42="",N(Q42)<=0),10,20*MAX(0,1-MIN(R42/Q42,1)))+30*MAX(0,MIN((PARAMETRI!$B$5-M42)/MAX(PARAMETRI!$B$5-10,1),1))+IF(AB42="",3,10*MAX(0,MIN(AB42/0.15,1)))+IF(AND(P42<>"",N(P42)<N(Q42)*0.6),-8,0),1)) | AE42: =IF(AND(P42="",Q42=""),"DATI MANCANTI",IF(AND(N(P42)>=PARAMETRI!$B$4,N(Q42)>=PARAMETRI!$B$4),"OK","NO")) | AF42: =IF(M42="","N/D",IF(M42<PARAMETRI!$B$6,"OTTIMO",IF(M42<PARAMETRI!$B$5,"OK","NO"))) | AG42: =IF(OR(AE42="DATI MANCANTI",AF42="N/D"),"DA COMPLETARE",IF(AND(AE42="OK",AF42="OTTIMO"),"PASSA FORTE",IF(AND(AE42="OK",AF42="OK"),"PASSA","SCARTA"))) | AH42: 2026-10-12 | AI42: yahoo
A43: =IF(AD43="","",RANK(AD43,AD$2:AD$44)) | B43: Linde plc (Xetra) | C43: LIN.DE | D43: Gas industriali | E43: Materiali | F43: 438.4 | G43: EUR | H43: 438.4 | I43: 202093.7 | J43: 202093.7 | M43: =IF(OR(F43="",K43="",K43<=0),"",F43/K43) | N43: 6.0052595 | O43: =IF(OR(N43="",M43="",M43<=0),"",N43/M43) | P43: 0.18036345 | Q43: 0.15309482 | R43: 0.029885241 | S43: 4 | U43: 0.18036345 | V43: 0.1723459 | W43: 0.15606747 | X43: 0.10360248 | Z43: =IF(OR(Y43="",F43="",F43=0),"",Y43/F43) | AD43: =IF(OR(Q43="",M43="",M43<=0),"",ROUND(40*MAX(0,MIN(N(Q43)/0.3,1))+IF(OR(R43="",N(Q43)<=0),10,20*MAX(0,1-MIN(R43/Q43,1)))+30*MAX(0,MIN((PARAMETRI!$B$5-M43)/MAX(PARAMETRI!$B$5-10,1),1))+IF(AB43="",3,10*MAX(0,MIN(AB43/0.15,1)))+IF(AND(P43<>"",N(P43)<N(Q43)*0.6),-8,0),1)) | AE43: =IF(AND(P43="",Q43=""),"DATI MANCANTI",IF(AND(N(P43)>=PARAMETRI!$B$4,N(Q43)>=PARAMETRI!$B$4),"OK","NO")) | AF43: =IF(M43="","N/D",IF(M43<PARAMETRI!$B$6,"OTTIMO",IF(M43<PARAMETRI!$B$5,"OK","NO"))) | AG43: =IF(OR(AE43="DATI MANCANTI",AF43="N/D"),"DA COMPLETARE",IF(AND(AE43="OK",AF43="OTTIMO"),"PASSA FORTE",IF(AND(AE43="OK",AF43="OK"),"PASSA","SCARTA"))) | AH43: 2026-10-12 | AI43: yahoo
A44: =IF(AD44="","",RANK(AD44,AD$2:AD$44)) | B44: Puma | C44: PUM.DE | D44: Abbigliamento sportivo | E44: Consumi | F44: 23.18 | G44: EUR | H44: 23.18 | I44: 3412.3 | J44: 3412.3 | K44: -3.01 | L44: 0.2658 | M44: =IF(OR(F44="",K44="",K44<=0),"",F44/K44) | N44: 1.8666452 | O44: =IF(OR(N44="",M44="",M44<=0),"",N44/M44) | P44: -0.22574 | Q44: -0.0011398213 | R44: 0.21154296 | S44: 4 | U44: -0.36657391 | V44: 0.099586236 | W44: 0.11940941 | X44: 0.14301897 | Y44: 0.61 | Z44: =IF(OR(Y44="",F44="",F44=0),"",Y44/F44) | AA44: 145.367 | AB44: -0.097 | AC44: -0.062374935 | AD44: =IF(OR(Q44="",M44="",M44<=0),"",ROUND(40*MAX(0,MIN(N(Q44)/0.3,1))+IF(OR(R44="",N(Q44)<=0),10,20*MAX(0,1-MIN(R44/Q44,1)))+30*MAX(0,MIN((PARAMETRI!$B$5-M44)/MAX(PARAMETRI!$B$5-10,1),1))+IF(AB44="",3,10*MAX(0,MIN(AB44/0.15,1)))+IF(AND(P44<>"",N(P44)<N(Q44)*0.6),-8,0),1)) | AE44: =IF(AND(P44="",Q44=""),"DATI MANCANTI",IF(AND(N(P44)>=PARAMETRI!$B$4,N(Q44)>=PARAMETRI!$B$4),"OK","NO")) | AF44: =IF(M44="","N/D",IF(M44<PARAMETRI!$B$6,"OTTIMO",IF(M44<PARAMETRI!$B$5,"OK","NO"))) | AG44: =IF(OR(AE44="DATI MANCANTI",AF44="N/D"),"DA COMPLETARE",IF(AND(AE44="OK",AF44="OTTIMO"),"PASSA FORTE",IF(AND(AE44="OK",AF44="OK"),"PASSA","SCARTA"))) | AH44: 2026-10-12 | AI44: yahoo

Sheet FRANCIA
A1: POS. | B1: TITOLO | C1: TICKER | D1: SETTORE | E1: CLASSE | F1: PREZZO | G1: VAL. | H1: PREZZO € | I1: CAP. MLN € | J1: CAP. MLN locale | K1: EPS TTM | L1: EPS ATTESO | M1: P/E | N1: P/B | O1: ROE IMPL. | P1: ROE 1a | Q1: ROE 5a | R1: VARIAB. ROE | S1: ANNI | T1: 2026 | U1: 2025 | V1: 2024 | W1: 2023 | X1: 2022 | Y1: DIVID. | Z1: RENDIM. | AA1: DEBITO/MP | AB1: CRESC. RICAVI | AC1: MARGINE | AD1: PUNTEGGIO | AE1: ESITO ROE | AF1: ESITO P/E | AG1: GIUDIZIO | AH1: RILEVATO | AI1: FONTE | AJ1: NOTE
A2: =IF(AD2="","",RANK(AD2,AD$2:AD$36)) | B2: TotalEnergies | C2: TTE.PA | D2: Petrolio integrato | E2: Energia | F2: 78.98 | G2: EUR | H2: 78.98 | I2: 174346.4 | J2: 174346.4 | K2: 6.85 | L2: 9.741713 | M2: =IF(OR(F2="",K2="",K2<=0),"",F2/K2) | N2: 1.5398453 | O2: =IF(OR(N2="",M2="",M2<=0),"",N2/M2) | P2: 0.14479999 | Q2: 0.15371096 | R2: 0.030512074 | S2: 4 | U2: 0.11426408 | V2: 0.13370327 | W2: 0.18315589 | X2: 0.1837206 | Y2: 3.6 | Z2: =IF(OR(Y2="",F2="",F2=0),"",Y2/F2) | AA2: 48.045 | AB2: 0.278 | AC2: 0.097820607 | AD2: =IF(OR(Q2="",M2="",M2<=0),"",ROUND(40*MAX(0,MIN(N(Q2)/0.3,1))+IF(OR(R2="",N(Q2)<=0),10,20*MAX(0,1-MIN(R2/Q2,1)))+30*MAX(0,MIN((PARAMETRI!$B$5-M2)/MAX(PARAMETRI!$B$5-10,1),1))+IF(AB2="",3,10*MAX(0,MIN(AB2/0.15,1)))+IF(AND(P2<>"",N(P2)<N(Q2)*0.6),-8,0),1)) | AE2: =IF(AND(P2="",Q2=""),"DATI MANCANTI",IF(AND(N(P2)>=PARAMETRI!$B$4,N(Q2)>=PARAMETRI!$B$4),"OK","NO")) | AF2: =IF(M2="","N/D",IF(M2<PARAMETRI!$B$6,"OTTIMO",IF(M2<PARAMETRI!$B$5,"OK","NO"))) | AG2: =IF(OR(AE2="DATI MANCANTI",AF2="N/D"),"DA COMPLETARE",IF(AND(AE2="OK",AF2="OTTIMO"),"PASSA FORTE",IF(AND(AE2="OK",AF2="OK"),"PASSA","SCARTA"))) | AH2: 2026-10-12 | AI2: yahoo
A3: =IF(AD3="","",RANK(AD3,AD$2:AD$36)) | B3: BNP Paribas | C3: BNP.PA | D3: Banca | E3: Finanziario | F3: 90.09 | G3: EUR | H3: 90.09 | I3: 98738.6 | J3: 98738.6 | K3: 11.23 | L3: 13.26063 | M3: =IF(OR(F3="",K3="",K3<=0),"",F3/K3) | N3: 0.822139 | O3: =IF(OR(N3="",M3="",M3<=0),"",N3/M3) | P3: 0.10477 | Q3: 0.089634268 | R3: 0.0057952317 | S3: 4 | U3: 0.097400269 | V3: 0.091214872 | W3: 0.088692602 | X3: 0.081229328 | Y3: 6.46 | Z3: =IF(OR(Y3="",F3="",F3=0),"",Y3/F3) | AB3: 0.169 | AC3: 0.18555607 | AD3: =IF(OR(Q3="",M3="",M3<=0),"",ROUND(40*MAX(0,MIN(N(Q3)/0.3,1))+IF(OR(R3="",N(Q3)<=0),10,20*MAX(0,1-MIN(R3/Q3,1)))+30*MAX(0,MIN((PARAMETRI!$B$5-M3)/MAX(PARAMETRI!$B$5-10,1),1))+IF(AB3="",3,10*MAX(0,MIN(AB3/0.15,1)))+IF(AND(P3<>"",N(P3)<N(Q3)*0.6),-8,0),1)) | AE3: =IF(AND(P3="",Q3=""),"DATI MANCANTI",IF(AND(N(P3)>=PARAMETRI!$B$4,N(Q3)>=PARAMETRI!$B$4),"OK","NO")) | AF3: =IF(M3="","N/D",IF(M3<PARAMETRI!$B$6,"OTTIMO",IF(M3<PARAMETRI!$B$5,"OK","NO"))) | AG3: =IF(OR(AE3="DATI MANCANTI",AF3="N/D"),"DA COMPLETARE",IF(AND(AE3="OK",AF3="OTTIMO"),"PASSA FORTE",IF(AND(AE3="OK",AF3="OK"),"PASSA","SCARTA"))) | AH3: 2026-10-12 | AI3: yahoo
A4: =IF(AD4="","",RANK(AD4,AD$2:AD$36)) | B4: Vinci | C4: DG.PA | D4: Costruzioni / Concessioni | E4: Industriale | F4: 107.6 | G4: EUR | H4: 107.6 | I4: 59346.7 | J4: 59346.7 | K4: 9.01 | L4: 10.05592 | M4: =IF(OR(F4="",K4="",K4<=0),"",F4/K4) | N4: 1.9492047 | O4: =IF(OR(N4="",M4="",M4<=0),"",N4/M4) | P4: 0.16318001 | Q4: 0.16331754 | R4: 0.0028365959 | S4: 4 | U4: 0.15943678 | V4: 0.16238688 | W4: 0.16725358 | X4: 0.16419291 | Y4: 5 | Z4: =IF(OR(Y4="",F4="",F4=0),"",Y4/F4) | AA4: 120.742 | AB4: 0.023 | AC4: 0.067171279 | AD4: =IF(OR(Q4="",M4="",M4<=0),"",ROUND(40*MAX(0,MIN(N(Q4)/0.3,1))+IF(OR(R4="",N(Q4)<=0),10,20*MAX(0,1-MIN(R4/Q4,1)))+30*MAX(0,MIN((PARAMETRI!$B$5-M4)/MAX(PARAMETRI!$B$5-10,1),1))+IF(AB4="",3,10*MAX(0,MIN(AB4/0.15,1)))+IF(AND(P4<>"",N(P4)<N(Q4)*0.6),-8,0),1)) | AE4: =IF(AND(P4="",Q4=""),"DATI MANCANTI",IF(AND(N(P4)>=PARAMETRI!$B$4,N(Q4)>=PARAMETRI!$B$4),"OK","NO")) | AF4: =IF(M4="","N/D",IF(M4<PARAMETRI!$B$6,"OTTIMO",IF(M4<PARAMETRI!$B$5,"OK","NO"))) | AG4: =IF(OR(AE4="DATI MANCANTI",AF4="N/D"),"DA COMPLETARE",IF(AND(AE4="OK",AF4="OTTIMO"),"PASSA FORTE",IF(AND(AE4="OK",AF4="OK"),"PASSA","SCARTA"))) | AH4: 2026-10-12 | AI4: yahoo
A5: =IF(AD5="","",RANK(AD5,AD$2:AD$36)) | B5: AXA | C5: CS.PA | D5: Assicurazione | E5: Finanziario | F5: 41.81 | G5: EUR | H5: 41.81 | I5: 87423.1 | J5: 87423.1 | K5: 3.71 | L5: 4.47795 | M5: =IF(OR(F5="",K5="",K5<=0),"",F5/K5) | N5: 1.892626 | O5: =IF(OR(N5="",M5="",M5<=0),"",N5/M5) | P5: 0.14881 | Q5: 0.15511047 | R5: 0.035082911 | S5: 4 | U5: 0.20769117 | V5: 0.15790001 | W5: 0.14500091 | X5: 0.1098498 | Y5: 2.32 | Z5: =IF(OR(Y5="",F5="",F5=0),"",Y5/F5) | AA5: 119.437 | AB5: 0.045 | AC5: 0.072258675 | AD5: =IF(OR(Q5="",M5="",M5<=0),"",ROUND(40*MAX(0,MIN(N(Q5)/0.3,1))+IF(OR(R5="",N(Q5)<=0),10,20*MAX(0,1-MIN(R5/Q5,1)))+30*MAX(0,MIN((PARAMETRI!$B$5-M5)/MAX(PARAMETRI!$B$5-10,1),1))+IF(AB5="",3,10*MAX(0,MIN(AB5/0.15,1)))+IF(AND(P5<>"",N(P5)<N(Q5)*0.6),-8,0),1)) | AE5: =IF(AND(P5="",Q5=""),"DATI MANCANTI",IF(AND(N(P5)>=PARAMETRI!$B$4,N(Q5)>=PARAMETRI!$B$4),"OK","NO")) | AF5: =IF(M5="","N/D",IF(M5<PARAMETRI!$B$6,"OTTIMO",IF(M5<PARAMETRI!$B$5,"OK","NO"))) | AG5: =IF(OR(AE5="DATI MANCANTI",AF5="N/D"),"DA COMPLETARE",IF(AND(AE5="OK",AF5="OTTIMO"),"PASSA FORTE",IF(AND(AE5="OK",AF5="OK"),"PASSA","SCARTA"))) | AH5: 2026-10-12 | AI5: yahoo
A6: =IF(AD6="","",RANK(AD6,AD$2:AD$36)) | B6: Teleperformance | C6: TEP.PA | D6: Servizi esternalizzati | E6: Industriale | F6: 70.78 | G6: EUR | H6: 70.78 | I6: 4114.7 | J6: 4114.7 | K6: 7.91 | L6: 14.20672 | M6: =IF(OR(F6="",K6="",K6<=0),"",F6/K6) | N6: 0.9813246 | O6: =IF(OR(N6="",M6="",M6<=0),"",N6/M6) | P6: 0.11395001 | Q6: 0.1379143 | R6: 0.023488341 | S6: 4 | U6: 0.12130827 | V6: 0.11479368 | W6: 0.14035088 | X6: 0.17520436 | Y6: 4.5 | Z6: =IF(OR(Y6="",F6="",F6=0),"",Y6/F6) | AA6: 120.367 | AB6: -0.046 | AC6: 0.045448312 | AD6: =IF(OR(Q6="",M6="",M6<=0),"",ROUND(40*MAX(0,MIN(N(Q6)/0.3,1))+IF(OR(R6="",N(Q6)<=0),10,20*MAX(0,1-MIN(R6/Q6,1)))+30*MAX(0,MIN((PARAMETRI!$B$5-M6)/MAX(PARAMETRI!$B$5-10,1),1))+IF(AB6="",3,10*MAX(0,MIN(AB6/0.15,1)))+IF(AND(P6<>"",N(P6)<N(Q6)*0.6),-8,0),1)) | AE6: =IF(AND(P6="",Q6=""),"DATI MANCANTI",IF(AND(N(P6)>=PARAMETRI!$B$4,N(Q6)>=PARAMETRI!$B$4),"OK","NO")) | AF6: =IF(M6="","N/D",IF(M6<PARAMETRI!$B$6,"OTTIMO",IF(M6<PARAMETRI!$B$5,"OK","NO"))) | AG6: =IF(OR(AE6="DATI MANCANTI",AF6="N/D"),"DA COMPLETARE",IF(AND(AE6="OK",AF6="OTTIMO"),"PASSA FORTE",IF(AND(AE6="OK",AF6="OK"),"PASSA","SCARTA"))) | AH6: 2026-10-12 | AI6: yahoo
A7: =IF(AD7="","",RANK(AD7,AD$2:AD$36)) | B7: Credit Agricole | C7: ACA.PA | D7: Banca | E7: Finanziario | F7: 16.33 | G7: EUR | H7: 16.33 | I7: 49534.4 | J7: 49534.4 | K7: 1.98 | L7: 2.47687 | M7: =IF(OR(F7="",K7="",K7<=0),"",F7/K7) | N7: 0.7038793 | O7: =IF(OR(N7="",M7="",M7<=0),"",N7/M7) | P7: 0.08612 | Q7: 0.088753528 | R7: 0.0055632283 | S7: 4 | U7: 0.091087018 | V7: 0.094860126 | W7: 0.089300284 | X7: 0.079766683 | Y7: 1.13 | Z7: =IF(OR(Y7="",F7="",F7=0),"",Y7/F7) | AB7: -0.063 | AC7: 0.23315943 | AD7: =IF(OR(Q7="",M7="",M7<=0),"",ROUND(40*MAX(0,MIN(N(Q7)/0.3,1))+IF(OR(R7="",N(Q7)<=0),10,20*MAX(0,1-MIN(R7/Q7,1)))+30*MAX(0,MIN((PARAMETRI!$B$5-M7)/MAX(PARAMETRI!$B$5-10,1),1))+IF(AB7="",3,10*MAX(0,MIN(AB7/0.15,1)))+IF(AND(P7<>"",N(P7)<N(Q7)*0.6),-8,0),1)) | AE7: =IF(AND(P7="",Q7=""),"DATI MANCANTI",IF(AND(N(P7)>=PARAMETRI!$B$4,N(Q7)>=PARAMETRI!$B$4),"OK","NO")) | AF7: =IF(M7="","N/D",IF(M7<PARAMETRI!$B$6,"OTTIMO",IF(M7<PARAMETRI!$B$5,"OK","NO"))) | AG7: =IF(OR(AE7="DATI MANCANTI",AF7="N/D"),"DA COMPLETARE",IF(AND(AE7="OK",AF7="OTTIMO"),"PASSA FORTE",IF(AND(AE7="OK",AF7="OK"),"PASSA","SCARTA"))) | AH7: 2026-10-12 | AI7: yahoo
A8: =IF(AD8="","",RANK(AD8,AD$2:AD$36)) | B8: Capgemini | C8: CAP.PA | D8: Servizi IT | E8: Tecnologia | F8: 115.35 | G8: EUR | H8: 115.35 | I8: 19148.4 | J8: 19148.4 | K8: 7.87 | L8: 13.80292 | M8: =IF(OR(F8="",K8="",K8<=0),"",F8/K8) | N8: 1.6717875 | O8: =IF(OR(N8="",M8="",M8<=0),"",N8/M8) | P8: 0.12202 | Q8: 0.14936976 | R8: 0.0098176989 | S8: 4 | U8: 0.13744849 | V8: 0.14191083 | W8: 0.15907786 | X8: 0.15904184 | Y8: 3.4 | Z8: =IF(OR(Y8="",F8="",F8=0),"",Y8/F8) | AA8: 87.509 | AB8: 0.088 | AC8: 0.061206324 | AD8: =IF(OR(Q8="",M8="",M8<=0),"",ROUND(40*MAX(0,MIN(N(Q8)/0.3,1))+IF(OR(R8="",N(Q8)<=0),10,20*MAX(0,1-MIN(R8/Q8,1)))+30*MAX(0,MIN((PARAMETRI!$B$5-M8)/MAX(PARAMETRI!$B$5-10,1),1))+IF(AB8="",3,10*MAX(0,MIN(AB8/0.15,1)))+IF(AND(P8<>"",N(P8)<N(Q8)*0.6),-8,0),1)) | AE8: =IF(AND(P8="",Q8=""),"DATI MANCANTI",IF(AND(N(P8)>=PARAMETRI!$B$4,N(Q8)>=PARAMETRI!$B$4),"OK","NO")) | AF8: =IF(M8="","N/D",IF(M8<PARAMETRI!$B$6,"OTTIMO",IF(M8<PARAMETRI!$B$5,"OK","NO"))) | AG8: =IF(OR(AE8="DATI MANCANTI",AF8="N/D"),"DA COMPLETARE",IF(AND(AE8="OK",AF8="OTTIMO"),"PASSA FORTE",IF(AND(AE8="OK",AF8="OK"),"PASSA","SCARTA"))) | AH8: 2026-10-12 | AI8: yahoo
A9: =IF(AD9="","",RANK(AD9,AD$2:AD$36)) | B9: Saint-Gobain | C9: SGO.PA | D9: Materiali da costruzione | E9: Materiali | F9: 65.2 | G9: EUR | H9: 65.2 | I9: 31841.1 | J9: 31841.1 | K9: 5.39 | L9: 6.80623 | M9: =IF(OR(F9="",K9="",K9<=0),"",F9/K9) | N9: 1.2561651 | O9: =IF(OR(N9="",M9="",M9<=0),"",N9/M9) | P9: 0.11038999 | Q9: 0.1193837 | R9: 0.0075755057 | S9: 4 | U9: 0.11747688 | V9: 0.113149 | W9: 0.11468225 | X9: 0.13222667 | Y9: 2.3 | Z9: =IF(OR(Y9="",F9="",F9=0),"",Y9/F9) | AA9: 66.318 | AB9: -0.011 | AC9: 0.057461869 | AD9: =IF(OR(Q9="",M9="",M9<=0),"",ROUND(40*MAX(0,MIN(N(Q9)/0.3,1))+IF(OR(R9="",N(Q9)<=0),10,20*MAX(0,1-MIN(R9/Q9,1)))+30*MAX(0,MIN((PARAMETRI!$B$5-M9)/MAX(PARAMETRI!$B$5-10,1),1))+IF(AB9="",3,10*MAX(0,MIN(AB9/0.15,1)))+IF(AND(P9<>"",N(P9)<N(Q9)*0.6),-8,0),1)) | AE9: =IF(AND(P9="",Q9=""),"DATI MANCANTI",IF(AND(N(P9)>=PARAMETRI!$B$4,N(Q9)>=PARAMETRI!$B$4),"OK","NO")) | AF9: =IF(M9="","N/D",IF(M9<PARAMETRI!$B$6,"OTTIMO",IF(M9<PARAMETRI!$B$5,"OK","NO"))) | AG9: =IF(OR(AE9="DATI MANCANTI",AF9="N/D"),"DA COMPLETARE",IF(AND(AE9="OK",AF9="OTTIMO"),"PASSA FORTE",IF(AND(AE9="OK",AF9="OK"),"PASSA","SCARTA"))) | AH9: 2026-10-12 | AI9: yahoo
A10: =IF(AD10="","",RANK(AD10,AD$2:AD$36)) | B10: Airbus | C10: AIR.PA | D10: Aerospazio | E10: Industriale | F10: 188.14 | G10: EUR | H10: 188.14 | I10: 148909.1 | J10: 148909.1 | K10: 7.51 | L10: 8.70017 | M10: =IF(OR(F10="",K10="",K10<=0),"",F10/K10) | N10: 5.7551003 | O10: =IF(OR(N10="",M10="",M10<=0),"",N10/M10) | P10: 0.23193 | Q10: 0.23948548 | R10: 0.051445684 | S10: 4 | U10: 0.20000766 | V10: 0.21585229 | W10: 0.21412828 | X10: 0.32795367 | Y10: 3.2 | Z10: =IF(OR(Y10="",F10="",F10=0),"",Y10/F10) | AA10: 54.988 | AB10: 0.277 | AC10: 0.080890763 | AD10: =IF(OR(Q10="",M10="",M10<=0),"",ROUND(40*MAX(0,MIN(N(Q10)/0.3,1))+IF(OR(R10="",N(Q10)<=0),10,20*MAX(0,1-MIN(R10/Q10,1)))+30*MAX(0,MIN((PARAMETRI!$B$5-M10)/MAX(PARAMETRI!$B$5-10,1),1))+IF(AB10="",3,10*MAX(0,MIN(AB10/0.15,1)))+IF(AND(P10<>"",N(P10)<N(Q10)*0.6),-8,0),1)) | AE10: =IF(AND(P10="",Q10=""),"DATI MANCANTI",IF(AND(N(P10)>=PARAMETRI!$B$4,N(Q10)>=PARAMETRI!$B$4),"OK","NO")) | AF10: =IF(M10="","N/D",IF(M10<PARAMETRI!$B$6,"OTTIMO",IF(M10<PARAMETRI!$B$5,"OK","NO"))) | AG10: =IF(OR(AE10="DATI MANCANTI",AF10="N/D"),"DA COMPLETARE",IF(AND(AE10="OK",AF10="OTTIMO"),"PASSA FORTE",IF(AND(AE10="OK",AF10="OK"),"PASSA","SCARTA"))) | AH10: 2026-10-12 | AI10: yahoo
A11: =IF(AD11="","",RANK(AD11,AD$2:AD$36)) | B11: Hermes International | C11: RMS.PA | D11: Lusso | E11: Consumi | F11: 1310 | G11: EUR | H11: 1310 | I11: 137211.4 | J11: 137211.4 | K11: 43 | L11: 48.68004 | M11: =IF(OR(F11="",K11="",K11<=0),"",F11/K11) | N11: 7.2129416 | O11: =IF(OR(N11="",M11="",M11<=0),"",N11/M11) | P11: 0.25452 | Q11: 0.26498913 | R11: 0.015785189 | S11: 4 | U11: 0.2401019 | V11: 0.26565476 | W11: 0.28356245 | X11: 0.27063741 | Y11: 18 | Z11: =IF(OR(Y11="",F11="",F11=0),"",Y11/F11) | AA11: 11.984 | AB11: 0.016 | AC11: 0.28223234 | AD11: =IF(OR(Q11="",M11="",M11<=0),"",ROUND(40*MAX(0,MIN(N(Q11)/0.3,1))+IF(OR(R11="",N(Q11)<=0),10,20*MAX(0,1-MIN(R11/Q11,1)))+30*MAX(0,MIN((PARAMETRI!$B$5-M11)/MAX(PARAMETRI!$B$5-10,1),1))+IF(AB11="",3,10*MAX(0,MIN(AB11/0.15,1)))+IF(AND(P11<>"",N(P11)<N(Q11)*0.6),-8,0),1)) | AE11: =IF(AND(P11="",Q11=""),"DATI MANCANTI",IF(AND(N(P11)>=PARAMETRI!$B$4,N(Q11)>=PARAMETRI!$B$4),"OK","NO")) | AF11: =IF(M11="","N/D",IF(M11<PARAMETRI!$B$6,"OTTIMO",IF(M11<PARAMETRI!$B$5,"OK","NO"))) | AG11: =IF(OR(AE11="DATI MANCANTI",AF11="N/D"),"DA COMPLETARE",IF(AND(AE11="OK",AF11="OTTIMO"),"PASSA FORTE",IF(AND(AE11="OK",AF11="OK"),"PASSA","SCARTA"))) | AH11: 2026-10-12 | AI11: yahoo
A12: =IF(AD12="","",RANK(AD12,AD$2:AD$36)) | B12: Carrefour | C12: CA.PA | D12: Grande distribuzione | E12: Consumi | F12: 15.91 | G12: EUR | H12: 15.91 | I12: 11258.1 | J12: 11258.1 | K12: 2.15 | L12: 1.87277 | M12: =IF(OR(F12="",K12="",K12<=0),"",F12/K12) | N12: 1.0172634 | O12: =IF(OR(N12="",M12="",M12<=0),"",N12/M12) | P12: 0.08428001 | Q12: 0.090154839 | R12: 0.045001836 | S12: 4 | U12: 0.029063411 | V12: 0.066820702 | W12: 0.14377329 | X12: 0.12096195 | Y12: 0.97 | Z12: =IF(OR(Y12="",F12="",F12=0),"",Y12/F12) | AA12: 185.209 | AB12: 0.02 | AC12: 0.01084214 | AD12: =IF(OR(Q12="",M12="",M12<=0),"",ROUND(40*MAX(0,MIN(N(Q12)/0.3,1))+IF(OR(R12="",N(Q12)<=0),10,20*MAX(0,1-MIN(R12/Q12,1)))+30*MAX(0,MIN((PARAMETRI!$B$5-M12)/MAX(PARAMETRI!$B$5-10,1),1))+IF(AB12="",3,10*MAX(0,MIN(AB12/0.15,1)))+IF(AND(P12<>"",N(P12)<N(Q12)*0.6),-8,0),1)) | AE12: =IF(AND(P12="",Q12=""),"DATI MANCANTI",IF(AND(N(P12)>=PARAMETRI!$B$4,N(Q12)>=PARAMETRI!$B$4),"OK","NO")) | AF12: =IF(M12="","N/D",IF(M12<PARAMETRI!$B$6,"OTTIMO",IF(M12<PARAMETRI!$B$5,"OK","NO"))) | AG12: =IF(OR(AE12="DATI MANCANTI",AF12="N/D"),"DA COMPLETARE",IF(AND(AE12="OK",AF12="OTTIMO"),"PASSA FORTE",IF(AND(AE12="OK",AF12="OK"),"PASSA","SCARTA"))) | AH12: 2026-10-12 | AI12: yahoo
A13: =IF(AD13="","",RANK(AD13,AD$2:AD$36)) | B13: Publicis Groupe | C13: PUB.PA | D13: Pubblicita' | E13: Consumi | F13: 98.74 | G13: EUR | H13: 98.74 | I13: 24657.5 | J13: 24657.5 | K13: 6.42 | L13: 8.54727 | M13: =IF(OR(F13="",K13="",K13<=0),"",F13/K13) | N13: 2.3440874 | O13: =IF(OR(N13="",M13="",M13<=0),"",N13/M13) | P13: 0.16179001 | Q13: 0.14229715 | R13: 0.012469071 | S13: 4 | U13: 0.15822724 | V13: 0.15009042 | W13: 0.13404168 | X13: 0.12682927 | Y13: 3.75 | Z13: =IF(OR(Y13="",F13="",F13=0),"",Y13/F13) | AA13: 51.925 | AB13: 0.03 | AC13: 0.093223748 | AD13: =IF(OR(Q13="",M13="",M13<=0),"",ROUND(40*MAX(0,MIN(N(Q13)/0.3,1))+IF(OR(R13="",N(Q13)<=0),10,20*MAX(0,1-MIN(R13/Q13,1)))+30*MAX(0,MIN((PARAMETRI!$B$5-M13)/MAX(PARAMETRI!$B$5-10,1),1))+IF(AB13="",3,10*MAX(0,MIN(AB13/0.15,1)))+IF(AND(P13<>"",N(P13)<N(Q13)*0.6),-8,0),1)) | AE13: =IF(AND(P13="",Q13=""),"DATI MANCANTI",IF(AND(N(P13)>=PARAMETRI!$B$4,N(Q13)>=PARAMETRI!$B$4),"OK","NO")) | AF13: =IF(M13="","N/D",IF(M13<PARAMETRI!$B$6,"OTTIMO",IF(M13<PARAMETRI!$B$5,"OK","NO"))) | AG13: =IF(OR(AE13="DATI MANCANTI",AF13="N/D"),"DA COMPLETARE",IF(AND(AE13="OK",AF13="OTTIMO"),"PASSA FORTE",IF(AND(AE13="OK",AF13="OK"),"PASSA","SCARTA"))) | AH13: 2026-10-12 | AI13: yahoo
A14: =IF(AD14="","",RANK(AD14,AD$2:AD$36)) | B14: LVMH | C14: MC.PA | D14: Lusso | E14: Consumi | F14: 384.5 | G14: EUR | H14: 384.5 | I14: 189545.1 | J14: 189545.1 | K14: 21.94 | L14: 24.57172 | M14: =IF(OR(F14="",K14="",K14<=0),"",F14/K14) | N14: 2.784295 | O14: =IF(OR(N14="",M14="",M14<=0),"",N14/M14) | P14: 0.16586 | Q14: 0.21283583 | R14: 0.040313928 | S14: 4 | U14: 0.16122243 | V14: 0.18587911 | W14: 0.24868479 | X14: 0.25555697 | Y14: 13 | Z14: =IF(OR(Y14="",F14="",F14=0),"",Y14/F14) | AA14: 53.306 | AB14: -0.029 | AC14: 0.13460467 | AD14: =IF(OR(Q14="",M14="",M14<=0),"",ROUND(40*MAX(0,MIN(N(Q14)/0.3,1))+IF(OR(R14="",N(Q14)<=0),10,20*MAX(0,1-MIN(R14/Q14,1)))+30*MAX(0,MIN((PARAMETRI!$B$5-M14)/MAX(PARAMETRI!$B$5-10,1),1))+IF(AB14="",3,10*MAX(0,MIN(AB14/0.15,1)))+IF(AND(P14<>"",N(P14)<N(Q14)*0.6),-8,0),1)) | AE14: =IF(AND(P14="",Q14=""),"DATI MANCANTI",IF(AND(N(P14)>=PARAMETRI!$B$4,N(Q14)>=PARAMETRI!$B$4),"OK","NO")) | AF14: =IF(M14="","N/D",IF(M14<PARAMETRI!$B$6,"OTTIMO",IF(M14<PARAMETRI!$B$5,"OK","NO"))) | AG14: =IF(OR(AE14="DATI MANCANTI",AF14="N/D"),"DA COMPLETARE",IF(AND(AE14="OK",AF14="OTTIMO"),"PASSA FORTE",IF(AND(AE14="OK",AF14="OK"),"PASSA","SCARTA"))) | AH14: 2026-10-12 | AI14: yahoo
A15: =IF(AD15="","",RANK(AD15,AD$2:AD$36)) | B15: Societe Generale | C15: GLE.PA | D15: Banca | E15: Finanziario | F15: 64.17 | G15: EUR | H15: 64.17 | I15: 46502.4 | J15: 46502.4 | K15: 7.79 | L15: 9.18666 | M15: =IF(OR(F15="",K15="",K15<=0),"",F15/K15) | N15: 0.6549429 | O15: =IF(OR(N15="",M15="",M15<=0),"",N15/M15) | P15: 0.09453 | Q15: 0.052596563 | R15: 0.0223628 | S15: 4 | U15: 0.085566834 | V15: 0.059781371 | W15: 0.037787041 | X15: 0.027251008 | Y15: 1.75 | Z15: =IF(OR(Y15="",F15="",F15=0),"",Y15/F15) | AB15: 0.041 | AC15: 0.10869442 | AD15: =IF(OR(Q15="",M15="",M15<=0),"",ROUND(40*MAX(0,MIN(N(Q15)/0.3,1))+IF(OR(R15="",N(Q15)<=0),10,20*MAX(0,1-MIN(R15/Q15,1)))+30*MAX(0,MIN((PARAMETRI!$B$5-M15)/MAX(PARAMETRI!$B$5-10,1),1))+IF(AB15="",3,10*MAX(0,MIN(AB15/0.15,1)))+IF(AND(P15<>"",N(P15)<N(Q15)*0.6),-8,0),1)) | AE15: =IF(AND(P15="",Q15=""),"DATI MANCANTI",IF(AND(N(P15)>=PARAMETRI!$B$4,N(Q15)>=PARAMETRI!$B$4),"OK","NO")) | AF15: =IF(M15="","N/D",IF(M15<PARAMETRI!$B$6,"OTTIMO",IF(M15<PARAMETRI!$B$5,"OK","NO"))) | AG15: =IF(OR(AE15="DATI MANCANTI",AF15="N/D"),"DA COMPLETARE",IF(AND(AE15="OK",AF15="OTTIMO"),"PASSA FORTE",IF(AND(AE15="OK",AF15="OK"),"PASSA","SCARTA"))) | AH15: 2026-10-12 | AI15: yahoo
A16: =IF(AD16="","",RANK(AD16,AD$2:AD$36)) | B16: Legrand | C16: LR.PA | D16: Materiale elettrico | E16: Industriale | F16: 139.6 | G16: EUR | H16: 139.6 | I16: 36591.1 | J16: 36591.1 | K16: 4.97 | L16: 6.86233 | M16: =IF(OR(F16="",K16="",K16<=0),"",F16/K16) | N16: 4.883168 | O16: =IF(OR(N16="",M16="",M16<=0),"",N16/M16) | P16: 0.18209 | Q16: 0.16173765 | R16: 0.0091242058 | S16: 4 | U16: 0.17062872 | V16: 0.15489217 | W16: 0.1708391 | X16: 0.15059061 | Y16: 2.38 | Z16: =IF(OR(Y16="",F16="",F16=0),"",Y16/F16) | AA16: 102.554 | AB16: 0.147 | AC16: 0.13867266 | AD16: =IF(OR(Q16="",M16="",M16<=0),"",ROUND(40*MAX(0,MIN(N(Q16)/0.3,1))+IF(OR(R16="",N(Q16)<=0),10,20*MAX(0,1-MIN(R16/Q16,1)))+30*MAX(0,MIN((PARAMETRI!$B$5-M16)/MAX(PARAMETRI!$B$5-10,1),1))+IF(AB16="",3,10*MAX(0,MIN(AB16/0.15,1)))+IF(AND(P16<>"",N(P16)<N(Q16)*0.6),-8,0),1)) | AE16: =IF(AND(P16="",Q16=""),"DATI MANCANTI",IF(AND(N(P16)>=PARAMETRI!$B$4,N(Q16)>=PARAMETRI!$B$4),"OK","NO")) | AF16: =IF(M16="","N/D",IF(M16<PARAMETRI!$B$6,"OTTIMO",IF(M16<PARAMETRI!$B$5,"OK","NO"))) | AG16: =IF(OR(AE16="DATI MANCANTI",AF16="N/D"),"DA COMPLETARE",IF(AND(AE16="OK",AF16="OTTIMO"),"PASSA FORTE",IF(AND(AE16="OK",AF16="OK"),"PASSA","SCARTA"))) | AH16: 2026-10-12 | AI16: yahoo
A17: =IF(AD17="","",RANK(AD17,AD$2:AD$36)) | B17: Pernod Ricard | C17: RI.PA | D17: Bevande | E17: Consumi | F17: 62.46 | G17: EUR | H17: 62.46 | I17: 15728.3 | J17: 15728.3 | K17: 4.77 | L17: 5.94922 | M17: =IF(OR(F17="",K17="",K17<=0),"",F17/K17) | N17: 1.0141915 | O17: =IF(OR(N17="",M17="",M17<=0),"",N17/M17) | P17: 0.07563 | Q17: 0.10553576 | R17: 0.024466917 | S17: 4 | T17: 0.077612903 | U17: 0.1068893 | V17: 0.093720236 | W17: 0.1439206 | X17: 0.12518816 | Y17: 4.7 | Z17: =IF(OR(Y17="",F17="",F17=0),"",Y17/F17) | AA17: 76.644 | AB17: -0.132 | AC17: 0.1279379 | AD17: =IF(OR(Q17="",M17="",M17<=0),"",ROUND(40*MAX(0,MIN(N(Q17)/0.3,1))+IF(OR(R17="",N(Q17)<=0),10,20*MAX(0,1-MIN(R17/Q17,1)))+30*MAX(0,MIN((PARAMETRI!$B$5-M17)/MAX(PARAMETRI!$B$5-10,1),1))+IF(AB17="",3,10*MAX(0,MIN(AB17/0.15,1)))+IF(AND(P17<>"",N(P17)<N(Q17)*0.6),-8,0),1)) | AE17: =IF(AND(P17="",Q17=""),"DATI MANCANTI",IF(AND(N(P17)>=PARAMETRI!$B$4,N(Q17)>=PARAMETRI!$B$4),"OK","NO")) | AF17: =IF(M17="","N/D",IF(M17<PARAMETRI!$B$6,"OTTIMO",IF(M17<PARAMETRI!$B$5,"OK","NO"))) | AG17: =IF(OR(AE17="DATI MANCANTI",AF17="N/D"),"DA COMPLETARE",IF(AND(AE17="OK",AF17="OTTIMO"),"PASSA FORTE",IF(AND(AE17="OK",AF17="OK"),"PASSA","SCARTA"))) | AH17: 2026-10-12 | AI17: yahoo
A18: =IF(AD18="","",RANK(AD18,AD$2:AD$36)) | B18: L'Oreal | C18: OR.PA | D18: Cosmetica | E18: Consumi | F18: 383.05 | G18: EUR | H18: 383.05 | I18: 203935.5 | J18: 203935.5 | K18: 11.78 | L18: 14.9293 | M18: =IF(OR(F18="",K18="",K18<=0),"",F18/K18) | N18: 6.0263042 | O18: =IF(OR(N18="",M18="",M18<=0),"",N18/M18) | P18: 0.19409001 | Q18: 0.19784571 | R18: 0.014962326 | S18: 4 | U18: 0.17529725 | V18: 0.19342172 | W18: 0.21269644 | X18: 0.20996744 | Y18: 7.2 | Z18: =IF(OR(Y18="",F18="",F18=0),"",Y18/F18) | AA18: 49.316 | AB18: 0.058 | AC18: 0.14315581 | AD18: =IF(OR(Q18="",M18="",M18<=0),"",ROUND(40*MAX(0,MIN(N(Q18)/0.3,1))+IF(OR(R18="",N(Q18)<=0),10,20*MAX(0,1-MIN(R18/Q18,1)))+30*MAX(0,MIN((PARAMETRI!$B$5-M18)/MAX(PARAMETRI!$B$5-10,1),1))+IF(AB18="",3,10*MAX(0,MIN(AB18/0.15,1)))+IF(AND(P18<>"",N(P18)<N(Q18)*0.6),-8,0),1)) | AE18: =IF(AND(P18="",Q18=""),"DATI MANCANTI",IF(AND(N(P18)>=PARAMETRI!$B$4,N(Q18)>=PARAMETRI!$B$4),"OK","NO")) | AF18: =IF(M18="","N/D",IF(M18<PARAMETRI!$B$6,"OTTIMO",IF(M18<PARAMETRI!$B$5,"OK","NO"))) | AG18: =IF(OR(AE18="DATI MANCANTI",AF18="N/D"),"DA COMPLETARE",IF(AND(AE18="OK",AF18="OTTIMO"),"PASSA FORTE",IF(AND(AE18="OK",AF18="OK"),"PASSA","SCARTA"))) | AH18: 2026-10-12 | AI18: yahoo
A19: =IF(AD19="","",RANK(AD19,AD$2:AD$36)) | B19: Renault | C19: RNO.PA | D19: Auto | E19: Consumi | F19: 26.84 | G19: EUR | H19: 26.84 | I19: 7766.8 | J19: 7766.8 | K19: 3.27 | L19: 6.53894 | M19: =IF(OR(F19="",K19="",K19<=0),"",F19/K19) | N19: 0.3785827 | O19: =IF(OR(N19="",M19="",M19<=0),"",N19/M19) | P19: 0.050029997 | Q19: -0.10982406 | R19: 0.24207304 | S19: 4 | U19: -0.52575634 | V19: 0.024811112 | W19: 0.073877386 | X19: -0.012228402 | Y19: 2.2 | Z19: =IF(OR(Y19="",F19="",F19=0),"",Y19/F19) | AA19: 327.722 | AB19: 0.094 | AC19: 0.016349574 | AD19: =IF(OR(Q19="",M19="",M19<=0),"",ROUND(40*MAX(0,MIN(N(Q19)/0.3,1))+IF(OR(R19="",N(Q19)<=0),10,20*MAX(0,1-MIN(R19/Q19,1)))+30*MAX(0,MIN((PARAMETRI!$B$5-M19)/MAX(PARAMETRI!$B$5-10,1),1))+IF(AB19="",3,10*MAX(0,MIN(AB19/0.15,1)))+IF(AND(P19<>"",N(P19)<N(Q19)*0.6),-8,0),1)) | AE19: =IF(AND(P19="",Q19=""),"DATI MANCANTI",IF(AND(N(P19)>=PARAMETRI!$B$4,N(Q19)>=PARAMETRI!$B$4),"OK","NO")) | AF19: =IF(M19="","N/D",IF(M19<PARAMETRI!$B$6,"OTTIMO",IF(M19<PARAMETRI!$B$5,"OK","NO"))) | AG19: =IF(OR(AE19="DATI MANCANTI",AF19="N/D"),"DA COMPLETARE",IF(AND(AE19="OK",AF19="OTTIMO"),"PASSA FORTE",IF(AND(AE19="OK",AF19="OK"),"PASSA","SCARTA"))) | AH19: 2026-10-12 | AI19: yahoo
A20: =IF(AD20="","",RANK(AD20,AD$2:AD$36)) | B20: Thales | C20: HO.PA | D20: Difesa / Elettronica | E20: Industriale | F20: 222.6 | G20: EUR | H20: 222.6 | I20: 45779.4 | J20: 45779.4 | K20: 7.26 | L20: 12.39188 | M20: =IF(OR(F20="",K20="",K20<=0),"",F20/K20) | N20: 5.712086 | O20: =IF(OR(N20="",M20="",M20<=0),"",N20/M20) | P20: 0.19353001 | Q20: 0.17626763 | R20: 0.024533954 | S20: 4 | U20: 0.21014256 | V20: 0.18888386 | W20: 0.14983895 | X20: 0.15620513 | Y20: 3.9 | Z20: =IF(OR(Y20="",F20="",F20=0),"",Y20/F20) | AA20: 69.537 | AB20: 0.067 | AC20: 0.067571966 | AD20: =IF(OR(Q20="",M20="",M20<=0),"",ROUND(40*MAX(0,MIN(N(Q20)/0.3,1))+IF(OR(R20="",N(Q20)<=0),10,20*MAX(0,1-MIN(R20/Q20,1)))+30*MAX(0,MIN((PARAMETRI!$B$5-M20)/MAX(PARAMETRI!$B$5-10,1),1))+IF(AB20="",3,10*MAX(0,MIN(AB20/0.15,1)))+IF(AND(P20<>"",N(P20)<N(Q20)*0.6),-8,0),1)) | AE20: =IF(AND(P20="",Q20=""),"DATI MANCANTI",IF(AND(N(P20)>=PARAMETRI!$B$4,N(Q20)>=PARAMETRI!$B$4),"OK","NO")) | AF20: =IF(M20="","N/D",IF(M20<PARAMETRI!$B$6,"OTTIMO",IF(M20<PARAMETRI!$B$5,"OK","NO"))) | AG20: =IF(OR(AE20="DATI MANCANTI",AF20="N/D"),"DA COMPLETARE",IF(AND(AE20="OK",AF20="OTTIMO"),"PASSA FORTE",IF(AND(AE20="OK",AF20="OK"),"PASSA","SCARTA"))) | AH20: 2026-10-12 | AI20: yahoo
A21: =IF(AD21="","",RANK(AD21,AD$2:AD$36)) | B21: Orange | C21: ORA.PA | D21: Telecomunicazioni | E21: Industriale | F21: 13.735 | G21: EUR | H21: 13.735 | I21: 36504.5 | J21: 36504.5 | K21: 1.07 | L21: 1.1481 | M21: =IF(OR(F21="",K21="",K21<=0),"",F21/K21) | N21: 1.1470686 | O21: =IF(OR(N21="",M21="",M21<=0),"",N21/M21) | P21: 0.14163 | Q21: 0.059060106 | R21: 0.023886111 | S21: 4 | U21: 0.018090723 | V21: 0.073962169 | W21: 0.076669285 | X21: 0.067518248 | Y21: 0.75 | Z21: =IF(OR(Y21="",F21="",F21=0),"",Y21/F21) | AA21: 161.477 | AB21: 0.055 | AC21: 0.098373645 | AD21: =IF(OR(Q21="",M21="",M21<=0),"",ROUND(40*MAX(0,MIN(N(Q21)/0.3,1))+IF(OR(R21="",N(Q21)<=0),10,20*MAX(0,1-MIN(R21/Q21,1)))+30*MAX(0,MIN((PARAMETRI!$B$5-M21)/MAX(PARAMETRI!$B$5-10,1),1))+IF(AB21="",3,10*MAX(0,MIN(AB21/0.15,1)))+IF(AND(P21<>"",N(P21)<N(Q21)*0.6),-8,0),1)) | AE21: =IF(AND(P21="",Q21=""),"DATI MANCANTI",IF(AND(N(P21)>=PARAMETRI!$B$4,N(Q21)>=PARAMETRI!$B$4),"OK","NO")) | AF21: =IF(M21="","N/D",IF(M21<PARAMETRI!$B$6,"OTTIMO",IF(M21<PARAMETRI!$B$5,"OK","NO"))) | AG21: =IF(OR(AE21="DATI MANCANTI",AF21="N/D"),"DA COMPLETARE",IF(AND(AE21="OK",AF21="OTTIMO"),"PASSA FORTE",IF(AND(AE21="OK",AF21="OK"),"PASSA","SCARTA"))) | AH21: 2026-10-12 | AI21: yahoo
A22: =IF(AD22="","",RANK(AD22,AD$2:AD$36)) | B22: Schneider Electric | C22: SU.PA | D22: Elettrificazione | E22: Industriale | F22: 265.35 | G22: EUR | H22: 265.35 | I22: 149472 | J22: 149472 | K22: 8.32 | L22: 12.34839 | M22: =IF(OR(F22="",K22="",K22<=0),"",F22/K22) | N22: 6.09958 | O22: =IF(OR(N22="",M22="",M22<=0),"",N22/M22) | P22: 0.18620001 | Q22: 0.15000076 | R22: 0.013821159 | S22: 4 | U22: 0.1720319 | V22: 0.14001771 | W22: 0.15127352 | X22: 0.1366799 | Y22: 4.2 | Z22: =IF(OR(Y22="",F22="",F22=0),"",Y22/F22) | AA22: 84.124 | AB22: 0.098 | AC22: 0.11800159 | AD22: =IF(OR(Q22="",M22="",M22<=0),"",ROUND(40*MAX(0,MIN(N(Q22)/0.3,1))+IF(OR(R22="",N(Q22)<=0),10,20*MAX(0,1-MIN(R22/Q22,1)))+30*MAX(0,MIN((PARAMETRI!$B$5-M22)/MAX(PARAMETRI!$B$5-10,1),1))+IF(AB22="",3,10*MAX(0,MIN(AB22/0.15,1)))+IF(AND(P22<>"",N(P22)<N(Q22)*0.6),-8,0),1)) | AE22: =IF(AND(P22="",Q22=""),"DATI MANCANTI",IF(AND(N(P22)>=PARAMETRI!$B$4,N(Q22)>=PARAMETRI!$B$4),"OK","NO")) | AF22: =IF(M22="","N/D",IF(M22<PARAMETRI!$B$6,"OTTIMO",IF(M22<PARAMETRI!$B$5,"OK","NO"))) | AG22: =IF(OR(AE22="DATI MANCANTI",AF22="N/D"),"DA COMPLETARE",IF(AND(AE22="OK",AF22="OTTIMO"),"PASSA FORTE",IF(AND(AE22="OK",AF22="OK"),"PASSA","SCARTA"))) | AH22: 2026-10-12 | AI22: yahoo
A23: =IF(AD23="","",RANK(AD23,AD$2:AD$36)) | B23: Unibail-Rodamco-Westfield | C23: URW.PA | D23: REIT / Centri commerciali | E23: Immobiliare | F23: 86.96 | G23: EUR | H23: 86.96 | I23: 12567.6 | J23: 12567.6 | K23: 10.8 | L23: 9.41441 | M23: =IF(OR(F23="",K23="",K23<=0),"",F23/K23) | N23: 0.7652437 | O23: =IF(OR(N23="",M23="",M23<=0),"",N23/M23) | P23: 0.086260006 | Q23: -0.0013678525 | R23: 0.059673124 | S23: 4 | U23: 0.071640408 | V23: 0.0082735828 | W23: -0.094677686 | X23: 0.0092922846 | Y23: 4.5 | Z23: =IF(OR(Y23="",F23="",F23=0),"",Y23/F23) | AA23: 108.102 | AB23: -0.004 | AC23: 0.5164792 | AD23: =IF(OR(Q23="",M23="",M23<=0),"",ROUND(40*MAX(0,MIN(N(Q23)/0.3,1))+IF(OR(R23="",N(Q23)<=0),10,20*MAX(0,1-MIN(R23/Q23,1)))+30*MAX(0,MIN((PARAMETRI!$B$5-M23)/MAX(PARAMETRI!$B$5-10,1),1))+IF(AB23="",3,10*MAX(0,MIN(AB23/0.15,1)))+IF(AND(P23<>"",N(P23)<N(Q23)*0.6),-8,0),1)) | AE23: =IF(AND(P23="",Q23=""),"DATI MANCANTI",IF(AND(N(P23)>=PARAMETRI!$B$4,N(Q23)>=PARAMETRI!$B$4),"OK","NO")) | AF23: =IF(M23="","N/D",IF(M23<PARAMETRI!$B$6,"OTTIMO",IF(M23<PARAMETRI!$B$5,"OK","NO"))) | AG23: =IF(OR(AE23="DATI MANCANTI",AF23="N/D"),"DA COMPLETARE",IF(AND(AE23="OK",AF23="OTTIMO"),"PASSA FORTE",IF(AND(AE23="OK",AF23="OK"),"PASSA","SCARTA"))) | AH23: 2026-10-12 | AI23: yahoo
A24: =IF(AD24="","",RANK(AD24,AD$2:AD$36)) | B24: Dassault Systemes | C24: DSY.PA | D24: Software | E24: Tecnologia | F24: 22.17 | G24: EUR | H24: 22.17 | I24: 29133.2 | J24: 29133.2 | K24: 0.97 | L24: 1.40815 | M24: =IF(OR(F24="",K24="",K24<=0),"",F24/K24) | N24: 3.1500425 | O24: =IF(OR(N24="",M24="",M24<=0),"",N24/M24) | P24: 0.15088001 | Q24: 0.13248994 | R24: 0.0032008161 | S24: 4 | U24: 0.13602347 | V24: 0.13237597 | W24: 0.13414432 | X24: 0.12741598 | Y24: 0.27 | Z24: =IF(OR(Y24="",F24="",F24=0),"",Y24/F24) | AA24: 36.229 | AB24: 0.022 | AC24: 0.21229374 | AD24: =IF(OR(Q24="",M24="",M24<=0),"",ROUND(40*MAX(0,MIN(N(Q24)/0.3,1))+IF(OR(R24="",N(Q24)<=0),10,20*MAX(0,1-MIN(R24/Q24,1)))+30*MAX(0,MIN((PARAMETRI!$B$5-M24)/MAX(PARAMETRI!$B$5-10,1),1))+IF(AB24="",3,10*MAX(0,MIN(AB24/0.15,1)))+IF(AND(P24<>"",N(P24)<N(Q24)*0.6),-8,0),1)) | AE24: =IF(AND(P24="",Q24=""),"DATI MANCANTI",IF(AND(N(P24)>=PARAMETRI!$B$4,N(Q24)>=PARAMETRI!$B$4),"OK","NO")) | AF24: =IF(M24="","N/D",IF(M24<PARAMETRI!$B$6,"OTTIMO",IF(M24<PARAMETRI!$B$5,"OK","NO"))) | AG24: =IF(OR(AE24="DATI MANCANTI",AF24="N/D"),"DA COMPLETARE",IF(AND(AE24="OK",AF24="OTTIMO"),"PASSA FORTE",IF(AND(AE24="OK",AF24="OK"),"PASSA","SCARTA"))) | AH24: 2026-10-12 | AI24: yahoo
A25: =IF(AD25="","",RANK(AD25,AD$2:AD$36)) | B25: Sanofi | C25: SAN.PA | D25: Farmaceutica | E25: Salute | F25: 71.6 | G25: EUR | H25: 71.6 | I25: 85781.7 | J25: 85781.7 | K25: 3.25 | L25: 9.0539 | M25: =IF(OR(F25="",K25="",K25<=0),"",F25/K25) | N25: 1.2395049 | O25: =IF(OR(N25="",M25="",M25<=0),"",N25/M25) | P25: 0.05709 | Q25: 0.09151682 | R25: 0.019206907 | S25: 4 | U25: 0.10946256 | V25: 0.071735456 | W25: 0.072933549 | X25: 0.11193571 | Y25: 4.12 | Z25: =IF(OR(Y25="",F25="",F25=0),"",Y25/F25) | AA25: 33.89 | AB25: 0.146 | AC25: 0.084318008 | AD25: =IF(OR(Q25="",M25="",M25<=0),"",ROUND(40*MAX(0,MIN(N(Q25)/0.3,1))+IF(OR(R25="",N(Q25)<=0),10,20*MAX(0,1-MIN(R25/Q25,1)))+30*MAX(0,MIN((PARAMETRI!$B$5-M25)/MAX(PARAMETRI!$B$5-10,1),1))+IF(AB25="",3,10*MAX(0,MIN(AB25/0.15,1)))+IF(AND(P25<>"",N(P25)<N(Q25)*0.6),-8,0),1)) | AE25: =IF(AND(P25="",Q25=""),"DATI MANCANTI",IF(AND(N(P25)>=PARAMETRI!$B$4,N(Q25)>=PARAMETRI!$B$4),"OK","NO")) | AF25: =IF(M25="","N/D",IF(M25<PARAMETRI!$B$6,"OTTIMO",IF(M25<PARAMETRI!$B$5,"OK","NO"))) | AG25: =IF(OR(AE25="DATI MANCANTI",AF25="N/D"),"DA COMPLETARE",IF(AND(AE25="OK",AF25="OTTIMO"),"PASSA FORTE",IF(AND(AE25="OK",AF25="OK"),"PASSA","SCARTA"))) | AH25: 2026-10-12 | AI25: yahoo
A26: =IF(AD26="","",RANK(AD26,AD$2:AD$36)) | B26: Engie | C26: ENGI.PA | D26: Utility | E26: Utility | F26: 22.94 | G26: EUR | H26: 22.94 | I26: 58281.5 | J26: 58281.5 | K26: 1.63 | L26: 2.11061 | M26: =IF(OR(F26="",K26="",K26<=0),"",F26/K26) | N26: 1.7100261 | O26: =IF(OR(N26="",M26="",M26<=0),"",N26/M26) | P26: 0.12218001 | Q26: 0.078683481 | R26: 0.045497905 | S26: 4 | U26: 0.11614568 | V26: 0.11882162 | W26: 0.073460425 | X26: 0.0063062011 | Y26: 1.35 | Z26: =IF(OR(Y26="",F26="",F26=0),"",Y26/F26) | AA26: 143.77 | AB26: -0.036 | AC26: 0.056502279 | AD26: =IF(OR(Q26="",M26="",M26<=0),"",ROUND(40*MAX(0,MIN(N(Q26)/0.3,1))+IF(OR(R26="",N(Q26)<=0),10,20*MAX(0,1-MIN(R26/Q26,1)))+30*MAX(0,MIN((PARAMETRI!$B$5-M26)/MAX(PARAMETRI!$B$5-10,1),1))+IF(AB26="",3,10*MAX(0,MIN(AB26/0.15,1)))+IF(AND(P26<>"",N(P26)<N(Q26)*0.6),-8,0),1)) | AE26: =IF(AND(P26="",Q26=""),"DATI MANCANTI",IF(AND(N(P26)>=PARAMETRI!$B$4,N(Q26)>=PARAMETRI!$B$4),"OK","NO")) | AF26: =IF(M26="","N/D",IF(M26<PARAMETRI!$B$6,"OTTIMO",IF(M26<PARAMETRI!$B$5,"OK","NO"))) | AG26: =IF(OR(AE26="DATI MANCANTI",AF26="N/D"),"DA COMPLETARE",IF(AND(AE26="OK",AF26="OTTIMO"),"PASSA FORTE",IF(AND(AE26="OK",AF26="OK"),"PASSA","SCARTA"))) | AH26: 2026-10-12 | AI26: yahoo
A27: =IF(AD27="","",RANK(AD27,AD$2:AD$36)) | B27: Air Liquide | C27: AI.PA | D27: Gas industriali | E27: Materiali | F27: 168.7 | G27: EUR | H27: 168.7 | I27: 107658.3 | J27: 107658.3 | K27: 5.55 | L27: 7.1769 | M27: =IF(OR(F27="",K27="",K27<=0),"",F27/K27) | N27: 4.0491567 | O27: =IF(OR(N27="",M27="",M27<=0),"",N27/M27) | P27: 0.13967 | Q27: 0.12501685 | R27: 0.0064747097 | S27: 4 | U27: 0.13419979 | V27: 0.12308637 | W27: 0.12655469 | X27: 0.11622655 | Y27: 3.36 | Z27: =IF(OR(Y27="",F27="",F27=0),"",Y27/F27) | AA27: 63.307 | AB27: 0.008 | AC27: 0.13137987 | AD27: =IF(OR(Q27="",M27="",M27<=0),"",ROUND(40*MAX(0,MIN(N(Q27)/0.3,1))+IF(OR(R27="",N(Q27)<=0),10,20*MAX(0,1-MIN(R27/Q27,1)))+30*MAX(0,MIN((PARAMETRI!$B$5-M27)/MAX(PARAMETRI!$B$5-10,1),1))+IF(AB27="",3,10*MAX(0,MIN(AB27/0.15,1)))+IF(AND(P27<>"",N(P27)<N(Q27)*0.6),-8,0),1)) | AE27: =IF(AND(P27="",Q27=""),"DATI MANCANTI",IF(AND(N(P27)>=PARAMETRI!$B$4,N(Q27)>=PARAMETRI!$B$4),"OK","NO")) | AF27: =IF(M27="","N/D",IF(M27<PARAMETRI!$B$6,"OTTIMO",IF(M27<PARAMETRI!$B$5,"OK","NO"))) | AG27: =IF(OR(AE27="DATI MANCANTI",AF27="N/D"),"DA COMPLETARE",IF(AND(AE27="OK",AF27="OTTIMO"),"PASSA FORTE",IF(AND(AE27="OK",AF27="OK"),"PASSA","SCARTA"))) | AH27: 2026-10-12 | AI27: yahoo
A28: =IF(AD28="","",RANK(AD28,AD$2:AD$36)) | B28: Veolia Environnement | C28: VIE.PA | D28: Servizi ambientali | E28: Utility | F28: 31.28 | G28: EUR | H28: 31.28 | I28: 23211.8 | J28: 23211.8 | K28: 1.72 | L28: 2.62209 | M28: =IF(OR(F28="",K28="",K28<=0),"",F28/K28) | N28: 2.3355486 | O28: =IF(OR(N28="",M28="",M28<=0),"",N28/M28) | P28: 0.13434 | Q28: 0.082916896 | R28: 0.019384699 | S28: 4 | U28: 0.11211423 | V28: 0.085017422 | W28: 0.076110795 | X28: 0.058425133 | Y28: 1.5 | Z28: =IF(OR(Y28="",F28="",F28=0),"",Y28/F28) | AA28: 250.259 | AB28: 0.007 | AC28: 0.028245788 | AD28: =IF(OR(Q28="",M28="",M28<=0),"",ROUND(40*MAX(0,MIN(N(Q28)/0.3,1))+IF(OR(R28="",N(Q28)<=0),10,20*MAX(0,1-MIN(R28/Q28,1)))+30*MAX(0,MIN((PARAMETRI!$B$5-M28)/MAX(PARAMETRI!$B$5-10,1),1))+IF(AB28="",3,10*MAX(0,MIN(AB28/0.15,1)))+IF(AND(P28<>"",N(P28)<N(Q28)*0.6),-8,0),1)) | AE28: =IF(AND(P28="",Q28=""),"DATI MANCANTI",IF(AND(N(P28)>=PARAMETRI!$B$4,N(Q28)>=PARAMETRI!$B$4),"OK","NO")) | AF28: =IF(M28="","N/D",IF(M28<PARAMETRI!$B$6,"OTTIMO",IF(M28<PARAMETRI!$B$5,"OK","NO"))) | AG28: =IF(OR(AE28="DATI MANCANTI",AF28="N/D"),"DA COMPLETARE",IF(AND(AE28="OK",AF28="OTTIMO"),"PASSA FORTE",IF(AND(AE28="OK",AF28="OK"),"PASSA","SCARTA"))) | AH28: 2026-10-12 | AI28: yahoo
A29: =IF(AD29="","",RANK(AD29,AD$2:AD$36)) | B29: EssilorLuxottica | C29: EL.PA | D29: Ottica | E29: Consumi | F29: 146.75 | G29: EUR | H29: 146.75 | I29: 67266.1 | J29: 67266.1 | K29: 5.35 | L29: 7.87709 | M29: =IF(OR(F29="",K29="",K29<=0),"",F29/K29) | N29: 1.7197937 | O29: =IF(OR(N29="",M29="",M29<=0),"",N29/M29) | P29: 0.06723 | Q29: 0.058817541 | R29: 0.00094882651 | S29: 4 | U29: 0.059528401 | V29: 0.058425798 | W29: 0.059860352 | X29: 0.057455613 | Y29: 4 | Z29: =IF(OR(Y29="",F29="",F29=0),"",Y29/F29) | AA29: 38.359 | AB29: 0.057 | AC29: 0.08753642 | AD29: =IF(OR(Q29="",M29="",M29<=0),"",ROUND(40*MAX(0,MIN(N(Q29)/0.3,1))+IF(OR(R29="",N(Q29)<=0),10,20*MAX(0,1-MIN(R29/Q29,1)))+30*MAX(0,MIN((PARAMETRI!$B$5-M29)/MAX(PARAMETRI!$B$5-10,1),1))+IF(AB29="",3,10*MAX(0,MIN(AB29/0.15,1)))+IF(AND(P29<>"",N(P29)<N(Q29)*0.6),-8,0),1)) | AE29: =IF(AND(P29="",Q29=""),"DATI MANCANTI",IF(AND(N(P29)>=PARAMETRI!$B$4,N(Q29)>=PARAMETRI!$B$4),"OK","NO")) | AF29: =IF(M29="","N/D",IF(M29<PARAMETRI!$B$6,"OTTIMO",IF(M29<PARAMETRI!$B$5,"OK","NO"))) | AG29: =IF(OR(AE29="DATI MANCANTI",AF29="N/D"),"DA COMPLETARE",IF(AND(AE29="OK",AF29="OTTIMO"),"PASSA FORTE",IF(AND(AE29="OK",AF29="OK"),"PASSA","SCARTA"))) | AH29: 2026-10-12 | AI29: yahoo
... A32: =IF(AD32="","",RANK(AD32,AD$2:AD$36)) | B32: Safran | C32: SAF.PA | D32: Aerospazio | E32: Industriale | F32: 318.4 | G32: EUR | H32: 318.4 | I32: 131937.3 | J32: 131937.3 | K32: 9.31 | L32: 12.94776 | M32: =IF(OR(F32="",K32="",K32<=0),"",F32/K32) | N32: 9.095843 | O32: =IF(OR(N32="",M32="",M32<=0),"",N32/M32) | P32: 0.2749 | Q32: 0.11985136 | R32: 0.28506533 | S32: 4 | U32: 0.48365793 | V32: -0.065546384 | W32: 0.2974864 | X32: -0.23619249 | Y32: 3.35 | Z32: =IF(OR(Y32="",F32="",F32=0),"",Y32/F32) | AA32: 33.745 | AB32: 0.16 | AC32: 0.12446696 | AD32: =IF(OR(Q32="",M32="",M32<=0),"",ROUND(40*MAX(0,MIN(N(Q32)/0.3,1))+IF(OR(R32="",N(Q32)<=0),10,20*MAX(0,1-MIN(R32/Q32,1)))+30*MAX(0,MIN((PARAMETRI!$B$5-M32)/MAX(PARAMETRI!$B$5-10,1),1))+IF(AB32="",3,10*MAX(0,MIN(AB32/0.15,1)))+IF(AND(P32<>"",N(P32)<N(Q32)*0.6),-8,0),1)) | AE32: =IF(AND(P32="",Q32=""),"DATI MANCANTI",IF(AND(N(P32)>=PARAMETRI!$B$4,N(Q32)>=PARAMETRI!$B$4),"OK","NO")) | AF32: =IF(M32="","N/D",IF(M32<PARAMETRI!$B$6,"OTTIMO",IF(M32<PARAMETRI!$B$5,"OK","NO"))) | AG32: =IF(OR(AE32="DATI MANCANTI",AF32="N/D"),"DA COMPLETARE",IF(AND(AE32="OK",AF32="OTTIMO"),"PASSA FORTE",IF(AND(AE32="OK",AF32="OK"),"PASSA","SCARTA"))) | AH32: 2026-10-12 | AI32: yahoo
A33: =IF(AD33="","",RANK(AD33,AD$2:AD$36)) | B33: Edenred | C33: EDEN.PA | D33: Servizi di pagamento | E33: Finanziario | F33: 28.3 | G33: EUR | H33: 28.3 | I33: 6460 | J33: 6460 | K33: 2.06 | L33: 2.44361 | M33: =IF(OR(F33="",K33="",K33<=0),"",F33/K33) | N33: -6.6447525 | O33: =IF(OR(N33="",M33="",M33<=0),"",N33/M33) | S33: 0 | Y33: 1.33 | Z33: =IF(OR(Y33="",F33="",F33=0),"",Y33/F33) | AB33: 0.015 | AC33: 0.16886187 | AD33: =IF(OR(Q33="",M33="",M33<=0),"",ROUND(40*MAX(0,MIN(N(Q33)/0.3,1))+IF(OR(R33="",N(Q33)<=0),10,20*MAX(0,1-MIN(R33/Q33,1)))+30*MAX(0,MIN((PARAMETRI!$B$5-M33)/MAX(PARAMETRI!$B$5-10,1),1))+IF(AB33="",3,10*MAX(0,MIN(AB33/0.15,1)))+IF(AND(P33<>"",N(P33)<N(Q33)*0.6),-8,0),1)) | AE33: =IF(AND(P33="",Q33=""),"DATI MANCANTI",IF(AND(N(P33)>=PARAMETRI!$B$4,N(Q33)>=PARAMETRI!$B$4),"OK","NO")) | AF33: =IF(M33="","N/D",IF(M33<PARAMETRI!$B$6,"OTTIMO",IF(M33<PARAMETRI!$B$5,"OK","NO"))) | AG33: =IF(OR(AE33="DATI MANCANTI",AF33="N/D"),"DA COMPLETARE",IF(AND(AE33="OK",AF33="OTTIMO"),"PASSA FORTE",IF(AND(AE33="OK",AF33="OK"),"PASSA","SCARTA"))) | AH33: 2026-10-12 | AI33: yahoo
A34: =IF(AD34="","",RANK(AD34,AD$2:AD$36)) | B34: Kering | C34: KER.PA | D34: Lusso | E34: Consumi | F34: 213.1 | G34: EUR | H34: 213.1 | I34: 26129.9 | J34: 26129.9 | K34: -2.98 | L34: 9.76874 | M34: =IF(OR(F34="",K34="",K34<=0),"",F34/K34) | N34: 1.8043114 | O34: =IF(OR(N34="",M34="",M34<=0),"",N34/M34) | P34: -0.01601 | Q34: 0.13379769 | R34: 0.09912846 | S34: 4 | U34: 0.0048959608 | V34: 0.07601986 | W34: 0.19609519 | X34: 0.25817974 | Y34: 3 | Z34: =IF(OR(Y34="",F34="",F34=0),"",Y34/F34) | AA34: 116.567 | AB34: -0.029 | AC34: -0.021942078 | AD34: =IF(OR(Q34="",M34="",M34<=0),"",ROUND(40*MAX(0,MIN(N(Q34)/0.3,1))+IF(OR(R34="",N(Q34)<=0),10,20*MAX(0,1-MIN(R34/Q34,1)))+30*MAX(0,MIN((PARAMETRI!$B$5-M34)/MAX(PARAMETRI!$B$5-10,1),1))+IF(AB34="",3,10*MAX(0,MIN(AB34/0.15,1)))+IF(AND(P34<>"",N(P34)<N(Q34)*0.6),-8,0),1)) | AE34: =IF(AND(P34="",Q34=""),"DATI MANCANTI",IF(AND(N(P34)>=PARAMETRI!$B$4,N(Q34)>=PARAMETRI!$B$4),"OK","NO")) | AF34: =IF(M34="","N/D",IF(M34<PARAMETRI!$B$6,"OTTIMO",IF(M34<PARAMETRI!$B$5,"OK","NO"))) | AG34: =IF(OR(AE34="DATI MANCANTI",AF34="N/D"),"DA COMPLETARE",IF(AND(AE34="OK",AF34="OTTIMO"),"PASSA FORTE",IF(AND(AE34="OK",AF34="OK"),"PASSA","SCARTA"))) | AH34: 2026-10-12 | AI34: yahoo
A35: =IF(AD35="","",RANK(AD35,AD$2:AD$36)) | B35: Michelin | C35: ML.PA | D35: Pneumatici | E35: Industriale | F35: 33.3 | G35: EUR | H35: 33.3 | M35: =IF(OR(F35="",K35="",K35<=0),"",F35/K35) | N35: 0.3970241 | O35: =IF(OR(N35="",M35="",M35<=0),"",N35/M35) | P35: 0.092131474 | Q35: 0.10516944 | R35: 0.0093898759 | S35: 4 | U35: 0.092131474 | V35: 0.10115436 | W35: 0.11044277 | X35: 0.11694915 | Z35: =IF(OR(Y35="",F35="",F35=0),"",Y35/F35) | AD35: =IF(OR(Q35="",M35="",M35<=0),"",ROUND(40*MAX(0,MIN(N(Q35)/0.3,1))+IF(OR(R35="",N(Q35)<=0),10,20*MAX(0,1-MIN(R35/Q35,1)))+30*MAX(0,MIN((PARAMETRI!$B$5-M35)/MAX(PARAMETRI!$B$5-10,1),1))+IF(AB35="",3,10*MAX(0,MIN(AB35/0.15,1)))+IF(AND(P35<>"",N(P35)<N(Q35)*0.6),-8,0),1)) | AE35: =IF(AND(P35="",Q35=""),"DATI MANCANTI",IF(AND(N(P35)>=PARAMETRI!$B$4,N(Q35)>=PARAMETRI!$B$4),"OK","NO")) | AF35: =IF(M35="","N/D",IF(M35<PARAMETRI!$B$6,"OTTIMO",IF(M35<PARAMETRI!$B$5,"OK","NO"))) | AG35: =IF(OR(AE35="DATI MANCANTI",AF35="N/D"),"DA COMPLETARE",IF(AND(AE35="OK",AF35="OTTIMO"),"PASSA FORTE",IF(AND(AE35="OK",AF35="OK"),"PASSA","SCARTA"))) | AH35: 2026-10-12 | AI35: yahoo
A36: =IF(AD36="","",RANK(AD36,AD$2:AD$36)) | B36: Worldline | C36: WLN.PA | D36: Pagamenti | E36: Tecnologia | F36: 10.722 | G36: EUR | H36: 10.722 | I36: 606.4 | J36: 606.4 | K36: -37.13 | L36: 3.44281 | M36: =IF(OR(F36="",K36="",K36<=0),"",F36/K36) | N36: 0.16268872 | O36: =IF(OR(N36="",M36="",M36<=0),"",N36/M36) | P36: -0.21247 | Q36: -0.42134371 | R36: 0.67388001 | S36: 4 | U36: -1.5859322 | V36: -0.0360179 | W36: -0.095310842 | X36: 0.031886097 | Z36: =IF(OR(Y36="",F36="",F36=0),"",Y36/F36) | AA36: 66.775 | AB36: -0.037 | AC36: -0.24526663 | AD36: =IF(OR(Q36="",M36="",M36<=0),"",ROUND(40*MAX(0,MIN(N(Q36)/0.3,1))+IF(OR(R36="",N(Q36)<=0),10,20*MAX(0,1-MIN(R36/Q36,1)))+30*MAX(0,MIN((PARAMETRI!$B$5-M36)/MAX(PARAMETRI!$B$5-10,1),1))+IF(AB36="",3,10*MAX(0,MIN(AB36/0.15,1)))+IF(AND(P36<>"",N(P36)<N(Q36)*0.6),-8,0),1)) | AE36: =IF(AND(P36="",Q36=""),"DATI MANCANTI",IF(AND(N(P36)>=PARAMETRI!$B$4,N(Q36)>=PARAMETRI!$B$4),"OK","NO")) | AF36: =IF(M36="","N/D",IF(M36<PARAMETRI!$B$6,"OTTIMO",IF(M36<PARAMETRI!$B$5,"OK","NO"))) | AG36: =IF(OR(AE36="DATI MANCANTI",AF36="N/D"),"DA COMPLETARE",IF(AND(AE36="OK",AF36="OTTIMO"),"PASSA FORTE",IF(AND(AE36="OK",AF36="OK"),"PASSA","SCARTA"))) | AH36: 2026-10-12 | AI36: yahoo

Sheet PAESI BASSI
A1: POS. | B1: TITOLO | C1: TICKER | D1: SETTORE | E1: CLASSE | F1: PREZZO | G1: VAL. | H1: PREZZO € | I1: CAP. MLN € | J1: CAP. MLN locale | K1: EPS TTM | L1: EPS ATTESO | M1: P/E | N1: P/B | O1: ROE IMPL. | P1: ROE 1a | Q1: ROE 5a | R1: VARIAB. ROE | S1: ANNI | T1: 2026 | U1: 2025 | V1: 2024 | W1: 2023 | X1: 2022 | Y1: DIVID. | Z1: RENDIM. | AA1: DEBITO/MP | AB1: CRESC. RICAVI | AC1: MARGINE | AD1: PUNTEGGIO | AE1: ESITO ROE | AF1: ESITO P/E | AG1: GIUDIZIO | AH1: RILEVATO | AI1: FONTE | AJ1: NOTE
A2: =IF(AD2="","",RANK(AD2,AD$2:AD$21)) | B2: Prosus | C2: PRX.AS | D2: Holding tecnologica | E2: Finanziario | F2: 35.87 | G2: EUR | H2: 35.87 | I2: 74966.7 | J2: 74966.7 | K2: 4.51 | L2: 4.325 | M2: =IF(OR(F2="",K2="",K2<=0),"",F2/K2) | N2: 1.6586562 | O2: =IF(OR(N2="",M2="",M2<=0),"",N2/M2) | P2: 0.22213 | Q2: 0.21138412 | R2: 0.03100412 | S2: 4 | T2: 0.21639613 | U2: 0.24227168 | V2: 0.16010664 | W2: 0.22676205 | Y2: 0.28 | Z2: =IF(OR(Y2="",F2="",F2=0),"",Y2/F2) | AA2: 32.874 | AC2: 1.2003092 | AD2: =IF(OR(Q2="",M2="",M2<=0),"",ROUND(40*MAX(0,MIN(N(Q2)/0.3,1))+IF(OR(R2="",N(Q2)<=0),10,20*MAX(0,1-MIN(R2/Q2,1)))+30*MAX(0,MIN((PARAMETRI!$B$5-M2)/MAX(PARAMETRI!$B$5-10,1),1))+IF(AB2="",3,10*MAX(0,MIN(AB2/0.15,1)))+IF(AND(P2<>"",N(P2)<N(Q2)*0.6),-8,0),1)) | AE2: =IF(AND(P2="",Q2=""),"DATI MANCANTI",IF(AND(N(P2)>=PARAMETRI!$B$4,N(Q2)>=PARAMETRI!$B$4),"OK","NO")) | AF2: =IF(M2="","N/D",IF(M2<PARAMETRI!$B$6,"OTTIMO",IF(M2<PARAMETRI!$B$5,"OK","NO"))) | AG2: =IF(OR(AE2="DATI MANCANTI",AF2="N/D"),"DA COMPLETARE",IF(AND(AE2="OK",AF2="OTTIMO"),"PASSA FORTE",IF(AND(AE2="OK",AF2="OK"),"PASSA","SCARTA"))) | AH2: 2026-10-12 | AI2: yahoo
A3: =IF(AD3="","",RANK(AD3,AD$2:AD$21)) | B3: Wolters Kluwer | C3: WKL.AS | D3: Informazione professionale | E3: Tecnologia | F3: 77.16 | G3: EUR | H3: 77.16 | I3: 17163.2 | J3: 17163.2 | K3: 5.85 | L3: 6.18606 | M3: =IF(OR(F3="",K3="",K3<=0),"",F3/K3) | N3: 18.32344 | O3: =IF(OR(N3="",M3="",M3<=0),"",N3/M3) | P3: 1.46141 | Q3: 0.83945649 | R3: 0.47031528 | S3: 4 | U3: 1.6390977 | V3: 0.69838188 | W3: 0.57575758 | X3: 0.44458874 | Y3: 2.6 | Z3: =IF(OR(Y3="",F3="",F3=0),"",Y3/F3) | AA3: 590.213 | AB3: -0.006 | AC3: 0.21795919 | AD3: =IF(OR(Q3="",M3="",M3<=0),"",ROUND(40*MAX(0,MIN(N(Q3)/0.3,1))+IF(OR(R3="",N(Q3)<=0),10,20*MAX(0,1-MIN(R3/Q3,1)))+30*MAX(0,MIN((PARAMETRI!$B$5-M3)/MAX(PARAMETRI!$B$5-10,1),1))+IF(AB3="",3,10*MAX(0,MIN(AB3/0.15,1)))+IF(AND(P3<>"",N(P3)<N(Q3)*0.6),-8,0),1)) | AE3: =IF(AND(P3="",Q3=""),"DATI MANCANTI",IF(AND(N(P3)>=PARAMETRI!$B$4,N(Q3)>=PARAMETRI!$B$4),"OK","NO")) | AF3: =IF(M3="","N/D",IF(M3<PARAMETRI!$B$6,"OTTIMO",IF(M3<PARAMETRI!$B$5,"OK","NO"))) | AG3: =IF(OR(AE3="DATI MANCANTI",AF3="N/D"),"DA COMPLETARE",IF(AND(AE3="OK",AF3="OTTIMO"),"PASSA FORTE",IF(AND(AE3="OK",AF3="OK"),"PASSA","SCARTA"))) | AH3: 2026-10-12 | AI3: yahoo
A4: =IF(AD4="","",RANK(AD4,AD$2:AD$21)) | B4: BE Semiconductor | C4: BESI.AS | D4: Apparecchiature semicond. | E4: Tecnologia | F4: 175.6 | G4: EUR | H4: 175.6 | I4: 13892.4 | J4: 13892.4 | K4: 2.62 | L4: 6.56014 | M4: =IF(OR(F4="",K4="",K4<=0),"",F4/K4) | N4: 24.756804 | O4: =IF(OR(N4="",M4="",M4<=0),"",N4/M4) | P4: 0.44873002 | Q4: 0.37057343 | R4: 0.037531648 | S4: 4 | U4: 0.31614301 | V4: 0.36306617 | W4: 0.42021485 | X4: 0.38286969 | Y4: 1.58 | Z4: =IF(OR(Y4="",F4="",F4=0),"",Y4/F4) | AA4: 62.453 | AB4: 0.687 | AC4: 0.35287512 | AD4: =IF(OR(Q4="",M4="",M4<=0),"",ROUND(40*MAX(0,MIN(N(Q4)/0.3,1))+IF(OR(R4="",N(Q4)<=0),10,20*MAX(0,1-MIN(R4/Q4,1)))+30*MAX(0,MIN((PARAMETRI!$B$5-M4)/MAX(PARAMETRI!$B$5-10,1),1))+IF(AB4="",3,10*MAX(0,MIN(AB4/0.15,1)))+IF(AND(P4<>"",N(P4)<N(Q4)*0.6),-8,0),1)) | AE4: =IF(AND(P4="",Q4=""),"DATI MANCANTI",IF(AND(N(P4)>=PARAMETRI!$B$4,N(Q4)>=PARAMETRI!$B$4),"OK","NO")) | AF4: =IF(M4="","N/D",IF(M4<PARAMETRI!$B$6,"OTTIMO",IF(M4<PARAMETRI!$B$5,"OK","NO"))) | AG4: =IF(OR(AE4="DATI MANCANTI",AF4="N/D"),"DA COMPLETARE",IF(AND(AE4="OK",AF4="OTTIMO"),"PASSA FORTE",IF(AND(AE4="OK",AF4="OK"),"PASSA","SCARTA"))) | AH4: 2026-10-12 | AI4: yahoo
A5: =IF(AD5="","",RANK(AD5,AD$2:AD$21)) | B5: ASML Holding | C5: ASML.AS | D5: Apparecchiature semicond. | E5: Tecnologia | F5: 1575.8 | G5: EUR | H5: 1575.8 | I5: 605264.8 | J5: 605264.8 | K5: 26.41 | L5: 52.19599 | M5: =IF(OR(F5="",K5="",K5<=0),"",F5/K5) | N5: 27.732218 | O5: =IF(OR(N5="",M5="",M5<=0),"",N5/M5) | P5: 0.53942 | Q5: 0.53942 | S5: 0 | U5: 0.48997053 | V5: 0.40978957 | W5: 0.5827213 | X5: 0.63833023 | Y5: 7.78 | Z5: =IF(OR(Y5="",F5="",F5=0),"",Y5/F5) | AA5: 9.092 | AB5: 0.213 | AC5: 0.32565898 | AD5: =IF(OR(Q5="",M5="",M5<=0),"",ROUND(40*MAX(0,MIN(N(Q5)/0.3,1))+IF(OR(R5="",N(Q5)<=0),10,20*MAX(0,1-MIN(R5/Q5,1)))+30*MAX(0,MIN((PARAMETRI!$B$5-M5)/MAX(PARAMETRI!$B$5-10,1),1))+IF(AB5="",3,10*MAX(0,MIN(AB5/0.15,1)))+IF(AND(P5<>"",N(P5)<N(Q5)*0.6),-8,0),1)) | AE5: =IF(AND(P5="",Q5=""),"DATI MANCANTI",IF(AND(N(P5)>=PARAMETRI!$B$4,N(Q5)>=PARAMETRI!$B$4),"OK","NO")) | AF5: =IF(M5="","N/D",IF(M5<PARAMETRI!$B$6,"OTTIMO",IF(M5<PARAMETRI!$B$5,"OK","NO"))) | AG5: =IF(OR(AE5="DATI MANCANTI",AF5="N/D"),"DA COMPLETARE",IF(AND(AE5="OK",AF5="OTTIMO"),"PASSA FORTE",IF(AND(AE5="OK",AF5="OK"),"PASSA","SCARTA"))) | AH5: 2026-10-12 | AI5: yahoo
